Workbook
Name actuals: OFFSET('[1]Actuals Update'!$A$1,0,0,COUNTA('[1]Actuals Update'!$A$1:$A$65536),13)
Name altdesc: '[1]Tables and Customizations'!$A$25:$B$140
Name ASSN: [1]Assumptions!$C$4
Name Beg_Bal: #REF!
Name curbudget: OFFSET('[1]Current Budget Update'!$A$1,0,0,COUNTA('[1]Current Budget Update'!$A$1:$A$65536),13)
Name End_Bal: '[2]Loan Amortization Schedule'!$I$18:$I$377
Name Extra_Pay: #REF!
Name Extra_Pay: #REF!
Name Extra_Pay: #REF!
Name Extra_Pay: #REF!
Name glai: '[1]PM Budget Input'!$F$7:$AA$971
Name Header_Row: ROW('[2]Loan Amortization Schedule'!$A$17:$IV$17)
Name INSPREAD: OFFSET('[1]PM Budget Input'!$A$1,0,0,COUNTA('[1]PM Budget Input'!$A$1:$A$65536),19)
Name Int: #REF!
Name intable: OFFSET('[1]PM Budget Input'!$F$8,0,0,COUNTA('[1]PM Budget Input'!$F$1:$F$65536),7)
Name Interest_Rate: '[2]Loan Amortization Schedule'!$D$6
Name Last_Row: IF(Values_Entered,Header_Row+Number_of_Payments,Header_Row)
Name listg: OFFSET('[1]PM Budget Input'!$F$8,0,0,COUNTA('[1]PM Budget Input'!$A$1:$A$65536),2)
Name Loan_Amount: '[2]Loan Amortization Schedule'!$D$5
Name Loan_Start: '[2]Loan Amortization Schedule'!$D$9
Name Loan_Years: '[2]Loan Amortization Schedule'!$D$7
Name Monkey: '[2]Lead Sheet'!$B$7:$I$67
Name Num_Pmt_Per_Year: #REF!
Name Num_Pmt_Per_Year: #REF!
Name Num_Pmt_Per_Year: #REF!
Name Num_Pmt_Per_Year: #REF!
Name Number_of_Payments: MATCH(0.01,End_Bal,-1)+1
Name outtable: OFFSET('[1]PM Budget Input'!$F$103,0,0,COUNTA('[1]PM Budget Input'!$F$1:$F$65536),10)
Name Pay_Num: #REF!
Name prevbudget: OFFSET('[1]Previous Budget Update'!$A$1,0,0,COUNTA('[1]Previous Budget Update'!$A$1:$A$65536),13)
Name Princ: #REF!
Name projection: OFFSET('[1]Projection Update'!$A$1,0,0,COUNTA('[1]Projection Update'!$A$1:$A$65536),13)
Name Sched_Pay: #REF!
Name Scheduled_Extra_Payments: #REF!
Name Scheduled_Monthly_Payment: #REF!
Name Total_Pay: #REF!
Name Total_Pay: #REF!
Name Total_Pay: #REF!
Name Total_Pay: #REF!
Name Units: #REF!
Name Values_Entered: IF(Loan_Amount*Interest_Rate*Loan_Years*Loan_Start>0,1,0)
Name YEAR: '[1]Tables and Customizations'!$B$17

Sheet Calc
F4: Assessments for Option 1
B6: =DATE(C9+1,B9,26) -> 26
B9: =MONTH(Assumptions!B23)-MONTH(Assumptions!D8) -> -11 | C9: =YEAR(Assumptions!B23) -> 1900 | D9: =MONTH(Assumptions!B23) -> 1 | E9: =DAY(Assumptions!B23) -> 0 | G9: =IF(YEAR(Assumptions!$D$8)=12,MONTH(Assumptions!$D$16)+1-MONTH(Assumptions!$D$8),IF(MONTH(Assumptions!$D$8)<MONTH(Assumptions!$D$16),12-(MONTH(Assumptions!D16)-MONTH(Assumptions!D8)),MONTH(Assumptions!$D$8)-MONTH(Assumptions!$D$16))) -> 5 | H9: =IF(YEAR(Assumptions!$D$8)=12,MONTH(Assumptions!$D$16)+1-MONTH(Assumptions!$D$8),IF(MONTH(Assumptions!$D$8)<MONTH(Assumptions!$D$16),12-(MONTH(Assumptions!$D$16)-MONTH(Assumptions!$D$8)),MONTH(Assumptions!$D$8)-MONTH(Assumptions!$D$16))) -> 5
B13: =Assumptions!B24*12 -> 0
A15: Loan Clac | B15: =IF((MONTH(B18)-MONTH(Assumptions!B32))+1=12,0,(MONTH(B18)-MONTH(Assumptions!B32))+1) -> 0 | C15: =IF((MONTH(C18)-MONTH(Assumptions!B32))+1=12,0,(MONTH(C18)-MONTH(Assumptions!B32))+1) -> 0 | D15: =IF((MONTH(D18)-MONTH(Assumptions!B32))+1=12,0,(MONTH(D18)-MONTH(Assumptions!B32))+1) -> 0 | E15: =IF((MONTH(E18)-MONTH(Assumptions!B32))+1=12,0,(MONTH(E18)-MONTH(Assumptions!B32))+1) -> 0 | F15: =IF((MONTH(F18)-MONTH(Assumptions!B32))+1=12,0,(MONTH(F18)-MONTH(Assumptions!B32))+1) -> 0 | G15: =IF((MONTH(G18)-MONTH(Assumptions!B32))+1=12,0,(MONTH(G18)-MONTH(Assumptions!B32))+1) -> 0 | H15: =IF((MONTH(H18)-MONTH(Assumptions!B32))+1=12,0,(MONTH(H18)-MONTH(Assumptions!B32))+1) -> 0 | I15: =IF((MONTH(I18)-MONTH(Assumptions!B32))+1=12,0,(MONTH(I18)-MONTH(Assumptions!B32))+1) -> 0 | J15: =IF((MONTH(J18)-MONTH(Assumptions!B32))+1=12,0,(MONTH(J18)-MONTH(Assumptions!B32))+1) -> 0 | K15: =IF((MONTH(K18)-MONTH(Assumptions!B32))+1=12,0,(MONTH(K18)-MONTH(Assumptions!B32))+1) -> 0 | L15: =IF((MONTH(L18)-MONTH(Assumptions!B32))+1=12,0,(MONTH(L18)-MONTH(Assumptions!B32))+1) -> 0 | M15: =IF((MONTH(M18)-MONTH(Assumptions!B32))+1=12,0,(MONTH(M18)-MONTH(Assumptions!B32))+1) -> 0 | N15: =IF((MONTH(N18)-MONTH(Assumptions!B32))+1=12,0,(MONTH(N18)-MONTH(Assumptions!B32))+1) -> 0 | O15: =IF((MONTH(O18)-MONTH(Assumptions!B32))+1=12,0,(MONTH(O18)-MONTH(Assumptions!B32))+1) -> 0 | P15: =IF((MONTH(P18)-MONTH(Assumptions!B32))+1=12,0,(MONTH(P18)-MONTH(Assumptions!B32))+1) -> 0
A16: SA Calc | B16: =IF((MONTH(B18)-MONTH(Assumptions!B22))+1=12,0,(MONTH(B18)-MONTH(Assumptions!B22))+1) -> 0 | C16: =IF((MONTH(C18)-MONTH(Assumptions!B22))+1=12,0,(MONTH(C18)-MONTH(Assumptions!B22))+1) -> 0 | D16: =IF((MONTH(D18)-MONTH(Assumptions!B22))+1=12,0,(MONTH(D18)-MONTH(Assumptions!B22))+1) -> 0 | E16: =IF((MONTH(E18)-MONTH(Assumptions!B22))+1=12,0,(MONTH(E18)-MONTH(Assumptions!B22))+1) -> 0 | F16: =IF((MONTH(F18)-MONTH(Assumptions!B22))+1=12,0,(MONTH(F18)-MONTH(Assumptions!B22))+1) -> 0 | G16: =IF((MONTH(G18)-MONTH(Assumptions!B22))+1=12,0,(MONTH(G18)-MONTH(Assumptions!B22))+1) -> 0 | H16: =IF((MONTH(H18)-MONTH(Assumptions!B22))+1=12,0,(MONTH(H18)-MONTH(Assumptions!B22))+1) -> 0 | I16: =IF((MONTH(I18)-MONTH(Assumptions!B22))+1=12,0,(MONTH(I18)-MONTH(Assumptions!B22))+1) -> 0 | J16: =IF((MONTH(J18)-MONTH(Assumptions!B22))+1=12,0,(MONTH(J18)-MONTH(Assumptions!B22))+1) -> 0 | K16: =IF((MONTH(K18)-MONTH(Assumptions!B22))+1=12,0,(MONTH(K18)-MONTH(Assumptions!B22))+1) -> 0 | L16: =IF((MONTH(L18)-MONTH(Assumptions!B22))+1=12,0,(MONTH(L18)-MONTH(Assumptions!B22))+1) -> 0 | M16: =IF((MONTH(M18)-MONTH(Assumptions!B22))+1=12,0,(MONTH(M18)-MONTH(Assumptions!B22))+1) -> 0 | N16: =IF((MONTH(N18)-MONTH(Assumptions!B22))+1=12,0,(MONTH(N18)-MONTH(Assumptions!B22))+1) -> 0 | O16: =IF((MONTH(O18)-MONTH(Assumptions!B22))+1=12,0,(MONTH(O18)-MONTH(Assumptions!B22))+1) -> 0 | P16: =IF((MONTH(P18)-MONTH(Assumptions!B22))+1=12,0,(MONTH(P18)-MONTH(Assumptions!B22))+1) -> 0
A17: Beg | B17: =DATE(B19,IF(MONTH(Assumptions!D8)=12,1,MONTH(Assumptions!D8)+1),1) -> 41275 | C17: =DATE(C19,IF(MONTH(Assumptions!D8)=12,1,MONTH(Assumptions!D8)+1),1) -> 41640 | D17: =DATE(D19,IF(MONTH(Assumptions!D8)=12,1,MONTH(Assumptions!D8)+1),1) -> 42005 | E17: =DATE(E19,IF(MONTH(Assumptions!D8)=12,1,MONTH(Assumptions!D8)+1),1) -> 42370 | F17: =DATE(F19,IF(MONTH(Assumptions!D8)=12,1,MONTH(Assumptions!D8)+1),1) -> 42736 | G17: =DATE(G19,IF(MONTH(Assumptions!D8)=12,1,MONTH(Assumptions!D8)+1),1) -> 43101 | H17: =DATE(H19,IF(MONTH(Assumptions!D8)=12,1,MONTH(Assumptions!D8)+1),1) -> 43466 | I17: =DATE(I19,IF(MONTH(Assumptions!D8)=12,1,MONTH(Assumptions!D8)+1),1) -> 43831 | J17: =DATE(J19,IF(MONTH(Assumptions!D8)=12,1,MONTH(Assumptions!D8)+1),1) -> 44197 | K17: =DATE(K19,IF(MONTH(Assumptions!D8)=12,1,MONTH(Assumptions!D8)+1),1) -> 44562 | L17: =DATE(L19,IF(MONTH(Assumptions!D8)=12,1,MONTH(Assumptions!D8)+1),1) -> 44927 | M17: =DATE(M19,IF(MONTH(Assumptions!D8)=12,1,MONTH(Assumptions!D8)+1),1) -> 45292 | N17: =DATE(N19,IF(MONTH(Assumptions!D8)=12,1,MONTH(Assumptions!D8)+1),1) -> 45658 | O17: =DATE(O19,IF(MONTH(Assumptions!D8)=12,1,MONTH(Assumptions!D8)+1),1) -> 46023 | P17: =DATE(P19,IF(MONTH(Assumptions!D8)=12,1,MONTH(Assumptions!D8)+1),1) -> 46388
A18: End | B18: =DATE(IF(MONTH(Assumptions!D8)=12,B19,B19+1),MONTH(Assumptions!D8),DAY(Assumptions!D8)) -> 41639 | C18: =DATE(IF(MONTH(Assumptions!D8)=12,C19,C19+1),MONTH(Assumptions!D8),DAY(Assumptions!D8)) -> 42004 | D18: =DATE(IF(MONTH(Assumptions!D8)=12,D19,D19+1),MONTH(Assumptions!D8),DAY(Assumptions!D8)) -> 42369 | E18: =DATE(IF(MONTH(Assumptions!D8)=12,E19,E19+1),MONTH(Assumptions!D8),DAY(Assumptions!D8)) -> 42735 | F18: =DATE(IF(MONTH(Assumptions!D8)=12,F19,F19+1),MONTH(Assumptions!D8),DAY(Assumptions!D8)) -> 43100 | G18: =DATE(IF(MONTH(Assumptions!D8)=12,G19,G19+1),MONTH(Assumptions!D8),DAY(Assumptions!D8)) -> 43465 | H18: =DATE(IF(MONTH(Assumptions!D8)=12,H19,H19+1),MONTH(Assumptions!D8),DAY(Assumptions!D8)) -> 43830 | I18: =DATE(IF(MONTH(Assumptions!D8)=12,I19,I19+1),MONTH(Assumptions!D8),DAY(Assumptions!D8)) -> 44196 | J18: =DATE(IF(MONTH(Assumptions!D8)=12,J19,J19+1),MONTH(Assumptions!D8),DAY(Assumptions!D8)) -> 44561 | K18: =DATE(IF(MONTH(Assumptions!D8)=12,K19,K19+1),MONTH(Assumptions!D8),DAY(Assumptions!D8)) -> 44926 | L18: =DATE(IF(MONTH(Assumptions!D8)=12,L19,L19+1),MONTH(Assumptions!D8),DAY(Assumptions!D8)) -> 45291 | M18: =DATE(IF(MONTH(Assumptions!D8)=12,M19,M19+1),MONTH(Assumptions!D8),DAY(Assumptions!D8)) -> 45657 | N18: =DATE(IF(MONTH(Assumptions!D8)=12,N19,N19+1),MONTH(Assumptions!D8),DAY(Assumptions!D8)) -> 46022 | O18: =DATE(IF(MONTH(Assumptions!D8)=12,O19,O19+1),MONTH(Assumptions!D8),DAY(Assumptions!D8)) -> 46387 | P18: =DATE(IF(MONTH(Assumptions!D8)=12,P19,P19+1),MONTH(Assumptions!D8),DAY(Assumptions!D8)) -> 46752
B19: =Assumptions!D7 -> 2013 | C19: =+B19+1 -> 2014 | D19: =+C19+1 -> 2015 | E19: =+D19+1 -> 2016 | F19: =+E19+1 -> 2017 | G19: =+F19+1 -> 2018 | H19: =+G19+1 -> 2019 | I19: =+H19+1 -> 2020 | J19: =+I19+1 -> 2021 | ... P19: =+O19+1 -> 2027
A20: SA Month | B20: =IF(YEAR(Assumptions!B22)=B19,IF(MONTH(Assumptions!D8)=12,12-MONTH(Assumptions!B22)+1,IF(MONTH(Assumptions!B22)<MONTH(Assumptions!D8),(MONTH(Assumptions!D8)-MONTH(Assumptions!B22))+1,IF(MONTH(Assumptions!B22)=MONTH(Assumptions!D8),1,""))),IF(AND(A20="",YEAR(Assumptions!B22)+1=B19),((MONTH(B18)+12)-MONTH(Assumptions!B22))+1,IF(YEAR($B$6)=B19,$B$13-SUM(A$20:$B20),IF(B19<YEAR(Assumptions!B22),0,IF(B19<YEAR($B$6),12,IF(B19>YEAR($B$6),0)))))) -> 0 | C20: =IF(YEAR(Assumptions!B22)=C19,IF(MONTH(Assumptions!D8)=12,12-MONTH(Assumptions!B22)+1,IF(MONTH(Assumptions!B22)<MONTH(Assumptions!D8),(MONTH(Assumptions!D8)-MONTH(Assumptions!B22))+1,IF(MONTH(Assumptions!B22)=MONTH(Assumptions!D8),1,""))),IF(AND(B20="",YEAR(Assumptions!B22)+1=C19),((MONTH(C18)+12)-MONTH(Assumptions!B22))+1,IF(YEAR($B$6)=C19,$B$13-SUM(B$20:$B20),IF(C19<YEAR(Assumptions!B22),"",IF(C19<YEAR($B$6),12,IF(C19>YEAR($B$6),"")))))) | D20: =IF(YEAR(Assumptions!B22)=D19,IF(MONTH(Assumptions!D8)=12,12-MONTH(Assumptions!B22)+1,IF(MONTH(Assumptions!B22)<MONTH(Assumptions!D8),(MONTH(Assumptions!D8)-MONTH(Assumptions!B22))+1,IF(MONTH(Assumptions!B22)=MONTH(Assumptions!D8),1,""))),IF(AND(C20="",YEAR(Assumptions!B22)+1=D19),((MONTH(D18)+12)-MONTH(Assumptions!B22))+1,IF(YEAR($B$6)=D19,$B$13-SUM($B$20:C20),IF(D19<YEAR(Assumptions!B22),"",IF(D19<YEAR($B$6),12,IF(D19>YEAR($B$6),"")))))) | E20: =IF(YEAR(Assumptions!B22)=E19,IF(MONTH(Assumptions!D8)=12,12-MONTH(Assumptions!B22)+1,IF(MONTH(Assumptions!B22)<MONTH(Assumptions!D8),(MONTH(Assumptions!D8)-MONTH(Assumptions!B22))+1,IF(MONTH(Assumptions!B22)=MONTH(Assumptions!D8),1,""))),IF(AND(D20="",YEAR(Assumptions!B22)+1=E19),((MONTH(E18)+12)-MONTH(Assumptions!B22))+1,IF(YEAR($B$6)=E19,$B$13-SUM($B$20:D20),IF(E19<YEAR(Assumptions!B22),"",IF(E19<YEAR($B$6),12,IF(E19>YEAR($B$6),"")))))) | F20: =IF(YEAR(Assumptions!B22)=F19,IF(MONTH(Assumptions!D8)=12,12-MONTH(Assumptions!B22)+1,IF(MONTH(Assumptions!B22)<MONTH(Assumptions!D8),(MONTH(Assumptions!D8)-MONTH(Assumptions!B22))+1,IF(MONTH(Assumptions!B22)=MONTH(Assumptions!D8),1,""))),IF(AND(E20="",YEAR(Assumptions!B22)+1=F19),((MONTH(F18)+12)-MONTH(Assumptions!B22))+1,IF(YEAR($B$6)=F19,$B$13-SUM($B$20:E20),IF(F19<YEAR(Assumptions!B22),"",IF(F19<YEAR($B$6),12,IF(F19>YEAR($B$6),"")))))) | G20: =IF(YEAR(Assumptions!B22)=G19,IF(MONTH(Assumptions!D8)=12,12-MONTH(Assumptions!B22)+1,IF(MONTH(Assumptions!B22)<MONTH(Assumptions!D8),(MONTH(Assumptions!D8)-MONTH(Assumptions!B22))+1,IF(MONTH(Assumptions!B22)=MONTH(Assumptions!D8),1,""))),IF(AND(F20="",YEAR(Assumptions!B22)+1=G19),((MONTH(G18)+12)-MONTH(Assumptions!B22))+1,IF(YEAR($B$6)=G19,$B$13-SUM($B$20:F20),IF(G19<YEAR(Assumptions!B22),"",IF(G19<YEAR($B$6),12,IF(G19>YEAR($B$6),"")))))) | H20: =IF(YEAR(Assumptions!B22)=H19,IF(MONTH(Assumptions!D8)=12,12-MONTH(Assumptions!B22)+1,IF(MONTH(Assumptions!B22)<MONTH(Assumptions!D8),(MONTH(Assumptions!D8)-MONTH(Assumptions!B22))+1,IF(MONTH(Assumptions!B22)=MONTH(Assumptions!D8),1,""))),IF(AND(G20="",YEAR(Assumptions!B22)+1=H19),((MONTH(H18)+12)-MONTH(Assumptions!B22))+1,IF(YEAR($B$6)=H19,$B$13-SUM($B$20:G20),IF(H19<YEAR(Assumptions!B22),"",IF(H19<YEAR($B$6),12,IF(H19>YEAR($B$6),"")))))) | I20: =IF(YEAR(Assumptions!B22)=I19,IF(MONTH(Assumptions!D8)=12,12-MONTH(Assumptions!B22)+1,IF(MONTH(Assumptions!B22)<MONTH(Assumptions!D8),(MONTH(Assumptions!D8)-MONTH(Assumptions!B22))+1,IF(MONTH(Assumptions!B22)=MONTH(Assumptions!D8),1,""))),IF(AND(H20="",YEAR(Assumptions!B22)+1=I19),((MONTH(I18)+12)-MONTH(Assumptions!B22))+1,IF(YEAR($B$6)=I19,$B$13-SUM($B$20:H20),IF(I19<YEAR(Assumptions!B22),"",IF(I19<YEAR($B$6),12,IF(I19>YEAR($B$6),"")))))) | J20: =IF(YEAR(Assumptions!B22)=J19,IF(MONTH(Assumptions!D8)=12,12-MONTH(Assumptions!B22)+1,IF(MONTH(Assumptions!B22)<MONTH(Assumptions!D8),(MONTH(Assumptions!D8)-MONTH(Assumptions!B22))+1,IF(MONTH(Assumptions!B22)=MONTH(Assumptions!D8),1,""))),IF(AND(I20="",YEAR(Assumptions!B22)+1=J19),((MONTH(J18)+12)-MONTH(Assumptions!B22))+1,IF(YEAR($B$6)=J19,$B$13-SUM($B$20:I20),IF(J19<YEAR(Assumptions!B22),"",IF(J19<YEAR($B$6),12,IF(J19>YEAR($B$6),"")))))) | K20: =IF(YEAR(Assumptions!B22)=K19,IF(MONTH(Assumptions!D8)=12,12-MONTH(Assumptions!B22)+1,IF(MONTH(Assumptions!B22)<MONTH(Assumptions!D8),(MONTH(Assumptions!D8)-MONTH(Assumptions!B22))+1,IF(MONTH(Assumptions!B22)=MONTH(Assumptions!D8),1,""))),IF(AND(J20="",YEAR(Assumptions!B22)+1=K19),((MONTH(K18)+12)-MONTH(Assumptions!B22))+1,IF(YEAR($B$6)=K19,$B$13-SUM($B$20:J20),IF(K19<YEAR(Assumptions!B22),"",IF(K19<YEAR($B$6),12,IF(K19>YEAR($B$6),"")))))) | L20: =IF(YEAR(Assumptions!B22)=L19,IF(MONTH(Assumptions!D8)=12,12-MONTH(Assumptions!B22)+1,IF(MONTH(Assumptions!B22)<MONTH(Assumptions!D8),(MONTH(Assumptions!D8)-MONTH(Assumptions!B22))+1,IF(MONTH(Assumptions!B22)=MONTH(Assumptions!D8),1,""))),IF(AND(K20="",YEAR(Assumptions!B22)+1=L19),((MONTH(L18)+12)-MONTH(Assumptions!B22))+1,IF(YEAR($B$6)=L19,$B$13-SUM($B$20:K20),IF(L19<YEAR(Assumptions!B22),"",IF(L19<YEAR($B$6),12,IF(L19>YEAR($B$6),"")))))) | M20: =IF(YEAR(Assumptions!B22)=M19,IF(MONTH(Assumptions!D8)=12,12-MONTH(Assumptions!B22)+1,IF(MONTH(Assumptions!B22)<MONTH(Assumptions!D8),(MONTH(Assumptions!D8)-MONTH(Assumptions!B22))+1,IF(MONTH(Assumptions!B22)=MONTH(Assumptions!D8),1,""))),IF(AND(L20="",YEAR(Assumptions!B22)+1=M19),((MONTH(M18)+12)-MONTH(Assumptions!B22))+1,IF(YEAR($B$6)=M19,$B$13-SUM($B$20:L20),IF(M19<YEAR(Assumptions!B22),"",IF(M19<YEAR($B$6),12,IF(M19>YEAR($B$6),"")))))) | N20: =IF(YEAR(Assumptions!B22)=N19,IF(MONTH(Assumptions!D8)=12,12-MONTH(Assumptions!B22)+1,IF(MONTH(Assumptions!B22)<MONTH(Assumptions!D8),(MONTH(Assumptions!D8)-MONTH(Assumptions!B22))+1,IF(MONTH(Assumptions!B22)=MONTH(Assumptions!D8),1,""))),IF(AND(M20="",YEAR(Assumptions!B22)+1=N19),((MONTH(N18)+12)-MONTH(Assumptions!B22))+1,IF(YEAR($B$6)=N19,$B$13-SUM($B$20:M20),IF(N19<YEAR(Assumptions!B22),"",IF(N19<YEAR($B$6),12,IF(N19>YEAR($B$6),"")))))) | O20: =IF(YEAR(Assumptions!B22)=O19,IF(MONTH(Assumptions!D8)=12,12-MONTH(Assumptions!B22)+1,IF(MONTH(Assumptions!B22)<MONTH(Assumptions!D8),(MONTH(Assumptions!D8)-MONTH(Assumptions!B22))+1,IF(MONTH(Assumptions!B22)=MONTH(Assumptions!D8),1,""))),IF(AND(N20="",YEAR(Assumptions!B22)+1=O19),((MONTH(O18)+12)-MONTH(Assumptions!B22))+1,IF(YEAR($B$6)=O19,$B$13-SUM($B$20:N20),IF(O19<YEAR(Assumptions!B22),"",IF(O19<YEAR($B$6),12,IF(O19>YEAR($B$6),"")))))) | P20: =IF(YEAR(Assumptions!B22)=P19,IF(MONTH(Assumptions!D8)=12,12-MONTH(Assumptions!B22)+1,IF(MONTH(Assumptions!B22)<MONTH(Assumptions!D8),(MONTH(Assumptions!D8)-MONTH(Assumptions!B22))+1,IF(MONTH(Assumptions!B22)=MONTH(Assumptions!D8),1,""))),IF(AND(O20="",YEAR(Assumptions!B22)+1=P19),((MONTH(P18)+12)-MONTH(Assumptions!B22))+1,IF(YEAR($B$6)=P19,$B$13-SUM($B$20:O20),IF(P19<YEAR(Assumptions!B22),"",IF(P19<YEAR($B$6),12,IF(P19>YEAR($B$6),""))))))
A21: Loan | B21: =IF(YEAR(Assumptions!B32)=B19,IF(MONTH(Assumptions!D8)=12,MONTH(Assumptions!B32),IF(MONTH(Assumptions!B32)<MONTH(Assumptions!D8),12-((MONTH(Assumptions!D8)-MONTH(Assumptions!B32))),IF(MONTH(Assumptions!B32)=MONTH(Assumptions!D8),1,IF(MONTH(Assumptions!B32)>MONTH(Assumptions!D8),IF(YEAR(Assumptions!B32)+1=B19,(MONTH(Assumptions!B32)-MONTH(B17))+1,""),"")))),IF(YEAR(Assumptions!B32)+1=B19,(MONTH(Assumptions!B32)-MONTH(B17))+1,"")) | C21: =IF(B21="",IF(YEAR(Assumptions!B32)=C19,IF(MONTH(Assumptions!D8)=12,MONTH(Assumptions!B32),IF(MONTH(Assumptions!B32)<MONTH(Assumptions!D8),12-((MONTH(Assumptions!D8)-MONTH(Assumptions!B32))),IF(MONTH(Assumptions!B32)=MONTH(Assumptions!D8),1,IF(MONTH(Assumptions!B32)>MONTH(Assumptions!D8),IF(YEAR(Assumptions!B32)+1=C19,(MONTH(Assumptions!B32)-MONTH(C17))+1,""),"")))),IF(YEAR(Assumptions!B32)+1=C19,(MONTH(Assumptions!B32)-MONTH(C17))+1,"")),"") | D21: =IF(C21="",IF(YEAR(Assumptions!B32)=D19,IF(MONTH(Assumptions!D8)=12,MONTH(Assumptions!B32),IF(MONTH(Assumptions!B32)<MONTH(Assumptions!D8),12-((MONTH(Assumptions!D8)-MONTH(Assumptions!B32))),IF(MONTH(Assumptions!B32)=MONTH(Assumptions!D8),1,IF(MONTH(Assumptions!B32)>MONTH(Assumptions!D8),IF(YEAR(Assumptions!B32)+1=D19,(MONTH(Assumptions!B32)-MONTH(D17))+1,""),"")))),IF(YEAR(Assumptions!B32)+1=D19,(MONTH(Assumptions!B32)-MONTH(D17))+1,"")),"") | E21: =IF(D21="",IF(YEAR(Assumptions!B32)=E19,IF(MONTH(Assumptions!D8)=12,MONTH(Assumptions!B32),IF(MONTH(Assumptions!B32)<MONTH(Assumptions!D8),12-((MONTH(Assumptions!D8)-MONTH(Assumptions!B32))),IF(MONTH(Assumptions!B32)=MONTH(Assumptions!D8),1,IF(MONTH(Assumptions!B32)>MONTH(Assumptions!D8),IF(YEAR(Assumptions!B32)+1=E19,(MONTH(Assumptions!B32)-MONTH(E17))+1,""),"")))),IF(YEAR(Assumptions!B32)+1=E19,(MONTH(Assumptions!B32)-MONTH(E17))+1,"")),"") | F21: =IF(E21="",IF(YEAR(Assumptions!B32)=F19,IF(MONTH(Assumptions!D8)=12,MONTH(Assumptions!B32),IF(MONTH(Assumptions!B32)<MONTH(Assumptions!D8),12-((MONTH(Assumptions!D8)-MONTH(Assumptions!B32))),IF(MONTH(Assumptions!B32)=MONTH(Assumptions!D8),1,IF(MONTH(Assumptions!B32)>MONTH(Assumptions!D8),IF(YEAR(Assumptions!B32)+1=F19,(MONTH(Assumptions!B32)-MONTH(F17))+1,""),"")))),IF(YEAR(Assumptions!B32)+1=F19,(MONTH(Assumptions!B32)-MONTH(F17))+1,"")),"") | G21: =IF(F21="",IF(YEAR(Assumptions!B32)=G19,IF(MONTH(Assumptions!D8)=12,MONTH(Assumptions!B32),IF(MONTH(Assumptions!B32)<MONTH(Assumptions!D8),12-((MONTH(Assumptions!D8)-MONTH(Assumptions!B32))),IF(MONTH(Assumptions!B32)=MONTH(Assumptions!D8),1,IF(MONTH(Assumptions!B32)>MONTH(Assumptions!D8),IF(YEAR(Assumptions!B32)+1=G19,(MONTH(Assumptions!B32)-MONTH(G17))+1,""),"")))),IF(YEAR(Assumptions!B32)+1=G19,(MONTH(Assumptions!B32)-MONTH(G17))+1,"")),"") | H21: =IF(G21="",IF(YEAR(Assumptions!B32)=H19,IF(MONTH(Assumptions!D8)=12,MONTH(Assumptions!B32),IF(MONTH(Assumptions!B32)<MONTH(Assumptions!D8),12-((MONTH(Assumptions!D8)-MONTH(Assumptions!B32))),IF(MONTH(Assumptions!B32)=MONTH(Assumptions!D8),1,IF(MONTH(Assumptions!B32)>MONTH(Assumptions!D8),IF(YEAR(Assumptions!B32)+1=H19,(MONTH(Assumptions!B32)-MONTH(H17))+1,""),"")))),IF(YEAR(Assumptions!B32)+1=H19,(MONTH(Assumptions!B32)-MONTH(H17))+1,"")),"") | I21: =IF(H21="",IF(YEAR(Assumptions!B32)=I19,IF(MONTH(Assumptions!D8)=12,MONTH(Assumptions!B32),IF(MONTH(Assumptions!B32)<MONTH(Assumptions!D8),12-((MONTH(Assumptions!D8)-MONTH(Assumptions!B32))),IF(MONTH(Assumptions!B32)=MONTH(Assumptions!D8),1,IF(MONTH(Assumptions!B32)>MONTH(Assumptions!D8),IF(YEAR(Assumptions!B32)+1=I19,(MONTH(Assumptions!B32)-MONTH(I17))+1,""),"")))),IF(YEAR(Assumptions!B32)+1=I19,(MONTH(Assumptions!B32)-MONTH(I17))+1,"")),"") | J21: =IF(I21="",IF(YEAR(Assumptions!B32)=J19,IF(MONTH(Assumptions!D8)=12,MONTH(Assumptions!B32),IF(MONTH(Assumptions!B32)<MONTH(Assumptions!D8),12-((MONTH(Assumptions!D8)-MONTH(Assumptions!B32))),IF(MONTH(Assumptions!B32)=MONTH(Assumptions!D8),1,IF(MONTH(Assumptions!B32)>MONTH(Assumptions!D8),IF(YEAR(Assumptions!B32)+1=J19,(MONTH(Assumptions!B32)-MONTH(J17))+1,""),"")))),IF(YEAR(Assumptions!B32)+1=J19,(MONTH(Assumptions!B32)-MONTH(J17))+1,"")),"") | K21: =IF(J21="",IF(YEAR(Assumptions!B32)=K19,IF(MONTH(Assumptions!D8)=12,MONTH(Assumptions!B32),IF(MONTH(Assumptions!B32)<MONTH(Assumptions!D8),12-((MONTH(Assumptions!D8)-MONTH(Assumptions!B32))),IF(MONTH(Assumptions!B32)=MONTH(Assumptions!D8),1,IF(MONTH(Assumptions!B32)>MONTH(Assumptions!D8),IF(YEAR(Assumptions!B32)+1=K19,(MONTH(Assumptions!B32)-MONTH(K17))+1,""),"")))),IF(YEAR(Assumptions!B32)+1=K19,(MONTH(Assumptions!B32)-MONTH(K17))+1,"")),"") | L21: =IF(K21="",IF(YEAR(Assumptions!B32)=L19,IF(MONTH(Assumptions!D8)=12,MONTH(Assumptions!B32),IF(MONTH(Assumptions!B32)<MONTH(Assumptions!D8),12-((MONTH(Assumptions!D8)-MONTH(Assumptions!B32))),IF(MONTH(Assumptions!B32)=MONTH(Assumptions!D8),1,IF(MONTH(Assumptions!B32)>MONTH(Assumptions!D8),IF(YEAR(Assumptions!B32)+1=L19,(MONTH(Assumptions!B32)-MONTH(L17))+1,""),"")))),IF(YEAR(Assumptions!B32)+1=L19,(MONTH(Assumptions!B32)-MONTH(L17))+1,"")),"") | M21: =IF(L21="",IF(YEAR(Assumptions!B32)=M19,IF(MONTH(Assumptions!D8)=12,MONTH(Assumptions!B32),IF(MONTH(Assumptions!B32)<MONTH(Assumptions!D8),12-((MONTH(Assumptions!D8)-MONTH(Assumptions!B32))),IF(MONTH(Assumptions!B32)=MONTH(Assumptions!D8),1,IF(MONTH(Assumptions!B32)>MONTH(Assumptions!D8),IF(YEAR(Assumptions!B32)+1=M19,(MONTH(Assumptions!B32)-MONTH(M17))+1,""),"")))),IF(YEAR(Assumptions!B32)+1=M19,(MONTH(Assumptions!B32)-MONTH(M17))+1,"")),"") | N21: =IF(M21="",IF(YEAR(Assumptions!B32)=N19,IF(MONTH(Assumptions!D8)=12,MONTH(Assumptions!B32),IF(MONTH(Assumptions!B32)<MONTH(Assumptions!D8),12-((MONTH(Assumptions!D8)-MONTH(Assumptions!B32))),IF(MONTH(Assumptions!B32)=MONTH(Assumptions!D8),1,IF(MONTH(Assumptions!B32)>MONTH(Assumptions!D8),IF(YEAR(Assumptions!B32)+1=N19,(MONTH(Assumptions!B32)-MONTH(N17))+1,""),"")))),IF(YEAR(Assumptions!B32)+1=N19,(MONTH(Assumptions!B32)-MONTH(N17))+1,"")),"") | O21: =IF(N21="",IF(YEAR(Assumptions!B32)=O19,IF(MONTH(Assumptions!D8)=12,MONTH(Assumptions!B32),IF(MONTH(Assumptions!B32)<MONTH(Assumptions!D8),12-((MONTH(Assumptions!D8)-MONTH(Assumptions!B32))),IF(MONTH(Assumptions!B32)=MONTH(Assumptions!D8),1,IF(MONTH(Assumptions!B32)>MONTH(Assumptions!D8),IF(YEAR(Assumptions!B32)+1=O19,(MONTH(Assumptions!B32)-MONTH(O17))+1,""),"")))),IF(YEAR(Assumptions!B32)+1=O19,(MONTH(Assumptions!B32)-MONTH(O17))+1,"")),"") | P21: =IF(O21="",IF(YEAR(Assumptions!B32)=P19,IF(MONTH(Assumptions!D8)=12,MONTH(Assumptions!B32),IF(MONTH(Assumptions!B32)<MONTH(Assumptions!D8),12-((MONTH(Assumptions!D8)-MONTH(Assumptions!B32))),IF(MONTH(Assumptions!B32)=MONTH(Assumptions!D8),1,IF(MONTH(Assumptions!B32)>MONTH(Assumptions!D8),IF(YEAR(Assumptions!B32)+1=P19,(MONTH(Assumptions!B32)-MONTH(P17))+1,""),"")))),IF(YEAR(Assumptions!B32)+1=P19,(MONTH(Assumptions!B32)-MONTH(P17))+1,"")),"")
A22: SA Fee | B22: =IF(YEAR(Assumptions!B22)=B19,IF(MONTH(Assumptions!D8)=12,1,IF(MONTH(Assumptions!B22)<MONTH(B17),1,"")),IF(A22="",IF(B19=YEAR(Assumptions!B22)+1,1,""),"")) | C22: =IF(YEAR(Assumptions!B22)=C19,IF(MONTH(Assumptions!D8)=12,1,IF(MONTH(Assumptions!B22)<MONTH(C17),1,"")),IF(B22="",IF(C19=YEAR(Assumptions!B22)+1,1,""),"")) | D22: =IF(YEAR(Assumptions!B22)=D19,IF(MONTH(Assumptions!D8)=12,1,IF(MONTH(Assumptions!B22)<MONTH(D17),1,"")),IF(C22="",IF(D19=YEAR(Assumptions!B22)+1,1,""),"")) | E22: =IF(YEAR(Assumptions!B22)=E19,IF(MONTH(Assumptions!D8)=12,1,IF(MONTH(Assumptions!B22)<MONTH(E17),1,"")),IF(D22="",IF(E19=YEAR(Assumptions!B22)+1,1,""),"")) | F22: =IF(YEAR(Assumptions!B22)=F19,IF(MONTH(Assumptions!D8)=12,1,IF(MONTH(Assumptions!B22)<MONTH(F17),1,"")),IF(E22="",IF(F19=YEAR(Assumptions!B22)+1,1,""),"")) | G22: =IF(YEAR(Assumptions!B22)=G19,IF(MONTH(Assumptions!D8)=12,1,IF(MONTH(Assumptions!B22)<MONTH(G17),1,"")),IF(F22="",IF(G19=YEAR(Assumptions!B22)+1,1,""),"")) | H22: =IF(YEAR(Assumptions!B22)=H19,IF(MONTH(Assumptions!D8)=12,1,IF(MONTH(Assumptions!B22)<MONTH(H17),1,"")),IF(G22="",IF(H19=YEAR(Assumptions!B22)+1,1,""),"")) | I22: =IF(YEAR(Assumptions!B22)=I19,IF(MONTH(Assumptions!D8)=12,1,IF(MONTH(Assumptions!B22)<MONTH(I17),1,"")),IF(H22="",IF(I19=YEAR(Assumptions!B22)+1,1,""),"")) | J22: =IF(YEAR(Assumptions!B22)=J19,IF(MONTH(Assumptions!D8)=12,1,IF(MONTH(Assumptions!B22)<MONTH(J17),1,"")),IF(I22="",IF(J19=YEAR(Assumptions!B22)+1,1,""),"")) | K22: =IF(YEAR(Assumptions!B22)=K19,IF(MONTH(Assumptions!D8)=12,1,IF(MONTH(Assumptions!B22)<MONTH(K17),1,"")),IF(J22="",IF(K19=YEAR(Assumptions!B22)+1,1,""),"")) | L22: =IF(YEAR(Assumptions!B22)=L19,IF(MONTH(Assumptions!D8)=12,1,IF(MONTH(Assumptions!B22)<MONTH(L17),1,"")),IF(K22="",IF(L19=YEAR(Assumptions!B22)+1,1,""),"")) | M22: =IF(YEAR(Assumptions!B22)=M19,IF(MONTH(Assumptions!D8)=12,1,IF(MONTH(Assumptions!B22)<MONTH(M17),1,"")),IF(L22="",IF(M19=YEAR(Assumptions!B22)+1,1,""),"")) | N22: =IF(YEAR(Assumptions!B22)=N19,IF(MONTH(Assumptions!D8)=12,1,IF(MONTH(Assumptions!B22)<MONTH(N17),1,"")),IF(M22="",IF(N19=YEAR(Assumptions!B22)+1,1,""),"")) | O22: =IF(YEAR(Assumptions!B22)=O19,IF(MONTH(Assumptions!D8)=12,1,IF(MONTH(Assumptions!B22)<MONTH(O17),1,"")),IF(N22="",IF(O19=YEAR(Assumptions!B22)+1,1,""),"")) | P22: =IF(YEAR(Assumptions!B22)=P19,IF(MONTH(Assumptions!D8)=12,1,IF(MONTH(Assumptions!B22)<MONTH(P17),1,"")),IF(O22="",IF(P19=YEAR(Assumptions!B22)+1,1,""),""))
A23: Loan Proceed | B23: =IF(YEAR(Assumptions!B32)=B19,IF(MONTH(Assumptions!D8)=12,1,IF(MONTH(Assumptions!B32)<MONTH(B17),1,"")),IF(A23="",IF(B19=YEAR(Assumptions!B32)+1,1,""),"")) | C23: =IF(YEAR(Assumptions!B32)=C19,IF(MONTH(Assumptions!D8)=12,1,IF(MONTH(Assumptions!B32)<MONTH(C17),1,"")),IF(B23="",IF(C19=YEAR(Assumptions!B32)+1,1,""),"")) | D23: =IF(YEAR(Assumptions!B32)=D19,IF(MONTH(Assumptions!D8)=12,1,IF(MONTH(Assumptions!B32)<MONTH(D17),1,"")),IF(C23="",IF(D19=YEAR(Assumptions!B32)+1,1,""),"")) | E23: =IF(YEAR(Assumptions!B32)=E19,IF(MONTH(Assumptions!D8)=12,1,IF(MONTH(Assumptions!B32)<MONTH(E17),1,"")),IF(D23="",IF(E19=YEAR(Assumptions!B32)+1,1,""),"")) | F23: =IF(YEAR(Assumptions!B32)=F19,IF(MONTH(Assumptions!D8)=12,1,IF(MONTH(Assumptions!B32)<MONTH(F17),1,"")),IF(E23="",IF(F19=YEAR(Assumptions!B32)+1,1,""),"")) | G23: =IF(YEAR(Assumptions!B32)=G19,IF(MONTH(Assumptions!D8)=12,1,IF(MONTH(Assumptions!B32)<MONTH(G17),1,"")),IF(F23="",IF(G19=YEAR(Assumptions!B32)+1,1,""),"")) | H23: =IF(YEAR(Assumptions!B32)=H19,IF(MONTH(Assumptions!D8)=12,1,IF(MONTH(Assumptions!B32)<MONTH(H17),1,"")),IF(G23="",IF(H19=YEAR(Assumptions!B32)+1,1,""),"")) | I23: =IF(YEAR(Assumptions!B32)=I19,IF(MONTH(Assumptions!D8)=12,1,IF(MONTH(Assumptions!B32)<MONTH(I17),1,"")),IF(H23="",IF(I19=YEAR(Assumptions!B32)+1,1,""),"")) | J23: =IF(YEAR(Assumptions!B32)=J19,IF(MONTH(Assumptions!D8)=12,1,IF(MONTH(Assumptions!B32)<MONTH(J17),1,"")),IF(I23="",IF(J19=YEAR(Assumptions!B32)+1,1,""),"")) | K23: =IF(YEAR(Assumptions!B32)=K19,IF(MONTH(Assumptions!D8)=12,1,IF(MONTH(Assumptions!B32)<MONTH(K17),1,"")),IF(J23="",IF(K19=YEAR(Assumptions!B32)+1,1,""),"")) | L23: =IF(YEAR(Assumptions!B32)=L19,IF(MONTH(Assumptions!D8)=12,1,IF(MONTH(Assumptions!B32)<MONTH(L17),1,"")),IF(K23="",IF(L19=YEAR(Assumptions!B32)+1,1,""),"")) | M23: =IF(YEAR(Assumptions!B32)=M19,IF(MONTH(Assumptions!D8)=12,1,IF(MONTH(Assumptions!B32)<MONTH(M17),1,"")),IF(L23="",IF(M19=YEAR(Assumptions!B32)+1,1,""),"")) | N23: =IF(YEAR(Assumptions!B32)=N19,IF(MONTH(Assumptions!D8)=12,1,IF(MONTH(Assumptions!B32)<MONTH(N17),1,"")),IF(M23="",IF(N19=YEAR(Assumptions!B32)+1,1,""),"")) | O23: =IF(YEAR(Assumptions!B32)=O19,IF(MONTH(Assumptions!D8)=12,1,IF(MONTH(Assumptions!B32)<MONTH(O17),1,"")),IF(N23="",IF(O19=YEAR(Assumptions!B32)+1,1,""),"")) | P23: =IF(YEAR(Assumptions!B32)=P19,IF(MONTH(Assumptions!D8)=12,1,IF(MONTH(Assumptions!B32)<MONTH(P17),1,"")),IF(O23="",IF(P19=YEAR(Assumptions!B32)+1,1,""),""))
F27: Assessments for Option 2
B29: =DATE(C32+1,B32,26) -> 26
B32: =MONTH(Assumptions!C23)-MONTH(Assumptions!D8) -> -11 | C32: =YEAR(Assumptions!C23) -> 1900 | D32: =MONTH(Assumptions!C23) -> 1 | E32: =DAY(Assumptions!C23) -> 0 | G32: =IF(B43="",1,B43) -> 0
B36: =Assumptions!C24*12 -> 0
A38: Loan Clac | B38: =IF((MONTH(B41)-MONTH(Assumptions!C32))+1=12,0,(MONTH(B41)-MONTH(Assumptions!C32))+1) -> 0 | C38: =IF((MONTH(C41)-MONTH(Assumptions!C32))+1=12,0,(MONTH(C41)-MONTH(Assumptions!C32))+1) -> 0 | D38: =IF((MONTH(D41)-MONTH(Assumptions!C32))+1=12,0,(MONTH(D41)-MONTH(Assumptions!C32))+1) -> 0 | E38: =IF((MONTH(E41)-MONTH(Assumptions!C32))+1=12,0,(MONTH(E41)-MONTH(Assumptions!C32))+1) -> 0 | F38: =IF((MONTH(F41)-MONTH(Assumptions!C32))+1=12,0,(MONTH(F41)-MONTH(Assumptions!C32))+1) -> 0 | G38: =IF((MONTH(G41)-MONTH(Assumptions!C32))+1=12,0,(MONTH(G41)-MONTH(Assumptions!C32))+1) -> 0 | H38: =IF((MONTH(H41)-MONTH(Assumptions!C32))+1=12,0,(MONTH(H41)-MONTH(Assumptions!C32))+1) -> 0 | I38: =IF((MONTH(I41)-MONTH(Assumptions!C32))+1=12,0,(MONTH(I41)-MONTH(Assumptions!C32))+1) -> 0 | J38: =IF((MONTH(J41)-MONTH(Assumptions!C32))+1=12,0,(MONTH(J41)-MONTH(Assumptions!C32))+1) -> 0 | K38: =IF((MONTH(K41)-MONTH(Assumptions!C32))+1=12,0,(MONTH(K41)-MONTH(Assumptions!C32))+1) -> 0 | L38: =IF((MONTH(L41)-MONTH(Assumptions!C32))+1=12,0,(MONTH(L41)-MONTH(Assumptions!C32))+1) -> 0 | M38: =IF((MONTH(M41)-MONTH(Assumptions!C32))+1=12,0,(MONTH(M41)-MONTH(Assumptions!C32))+1) -> 0 | N38: =IF((MONTH(N41)-MONTH(Assumptions!C32))+1=12,0,(MONTH(N41)-MONTH(Assumptions!C32))+1) -> 0 | O38: =IF((MONTH(O41)-MONTH(Assumptions!C32))+1=12,0,(MONTH(O41)-MONTH(Assumptions!C32))+1) -> 0 | P38: =IF((MONTH(P41)-MONTH(Assumptions!C32))+1=12,0,(MONTH(P41)-MONTH(Assumptions!C32))+1) -> 0
A39: SA Calc | B39: =IF((MONTH(B41)-MONTH(Assumptions!C22))+1=12,0,(MONTH(B41)-MONTH(Assumptions!C22))+1) -> 0 | C39: =IF((MONTH(C41)-MONTH(Assumptions!C22))+1=12,0,(MONTH(C41)-MONTH(Assumptions!C22))+1) -> 0 | D39: =IF((MONTH(D41)-MONTH(Assumptions!C22))+1=12,0,(MONTH(D41)-MONTH(Assumptions!C22))+1) -> 0 | E39: =IF((MONTH(E41)-MONTH(Assumptions!C22))+1=12,0,(MONTH(E41)-MONTH(Assumptions!C22))+1) -> 0 | F39: =IF((MONTH(F41)-MONTH(Assumptions!C22))+1=12,0,(MONTH(F41)-MONTH(Assumptions!C22))+1) -> 0 | G39: =IF((MONTH(G41)-MONTH(Assumptions!C22))+1=12,0,(MONTH(G41)-MONTH(Assumptions!C22))+1) -> 0 | H39: =IF((MONTH(H41)-MONTH(Assumptions!C22))+1=12,0,(MONTH(H41)-MONTH(Assumptions!C22))+1) -> 0 | I39: =IF((MONTH(I41)-MONTH(Assumptions!C22))+1=12,0,(MONTH(I41)-MONTH(Assumptions!C22))+1) -> 0 | J39: =IF((MONTH(J41)-MONTH(Assumptions!C22))+1=12,0,(MONTH(J41)-MONTH(Assumptions!C22))+1) -> 0 | K39: =IF((MONTH(K41)-MONTH(Assumptions!C22))+1=12,0,(MONTH(K41)-MONTH(Assumptions!C22))+1) -> 0 | L39: =IF((MONTH(L41)-MONTH(Assumptions!C22))+1=12,0,(MONTH(L41)-MONTH(Assumptions!C22))+1) -> 0 | M39: =IF((MONTH(M41)-MONTH(Assumptions!C22))+1=12,0,(MONTH(M41)-MONTH(Assumptions!C22))+1) -> 0 | N39: =IF((MONTH(N41)-MONTH(Assumptions!C22))+1=12,0,(MONTH(N41)-MONTH(Assumptions!C22))+1) -> 0 | O39: =IF((MONTH(O41)-MONTH(Assumptions!C22))+1=12,0,(MONTH(O41)-MONTH(Assumptions!C22))+1) -> 0 | P39: =IF((MONTH(P41)-MONTH(Assumptions!C22))+1=12,0,(MONTH(P41)-MONTH(Assumptions!C22))+1) -> 0
A40: Beg | B40: =DATE(B42,IF(MONTH(Assumptions!D8)=12,1,MONTH(Assumptions!D8)+1),1) -> 41275 | C40: =DATE(C42,IF(MONTH(Assumptions!D8)=12,1,MONTH(Assumptions!D8)+1),1) -> 41640 | D40: =DATE(D42,IF(MONTH(Assumptions!D8)=12,1,MONTH(Assumptions!D8)+1),1) -> 42005 | E40: =DATE(E42,IF(MONTH(Assumptions!D8)=12,1,MONTH(Assumptions!D8)+1),1) -> 42370 | F40: =DATE(F42,IF(MONTH(Assumptions!D8)=12,1,MONTH(Assumptions!D8)+1),1) -> 42736 | G40: =DATE(G42,IF(MONTH(Assumptions!D8)=12,1,MONTH(Assumptions!D8)+1),1) -> 43101 | H40: =DATE(H42,IF(MONTH(Assumptions!D8)=12,1,MONTH(Assumptions!D8)+1),1) -> 43466 | I40: =DATE(I42,IF(MONTH(Assumptions!D8)=12,1,MONTH(Assumptions!D8)+1),1) -> 43831 | J40: =DATE(J42,IF(MONTH(Assumptions!D8)=12,1,MONTH(Assumptions!D8)+1),1) -> 44197 | K40: =DATE(K42,IF(MONTH(Assumptions!D8)=12,1,MONTH(Assumptions!D8)+1),1) -> 44562 | L40: =DATE(L42,IF(MONTH(Assumptions!D8)=12,1,MONTH(Assumptions!D8)+1),1) -> 44927 | M40: =DATE(M42,IF(MONTH(Assumptions!D8)=12,1,MONTH(Assumptions!D8)+1),1) -> 45292 | N40: =DATE(N42,IF(MONTH(Assumptions!D8)=12,1,MONTH(Assumptions!D8)+1),1) -> 45658 | O40: =DATE(O42,IF(MONTH(Assumptions!D8)=12,1,MONTH(Assumptions!D8)+1),1) -> 46023 | P40: =DATE(P42,IF(MONTH(Assumptions!D8)=12,1,MONTH(Assumptions!D8)+1),1) -> 46388
A41: End | B41: =DATE(IF(MONTH(Assumptions!D8)=12,B42,B42+1),MONTH(Assumptions!D8),DAY(Assumptions!D8)) -> 41639 | C41: =DATE(IF(MONTH(Assumptions!D8)=12,C42,C42+1),MONTH(Assumptions!D8),DAY(Assumptions!D8)) -> 42004 | D41: =DATE(IF(MONTH(Assumptions!D8)=12,D42,D42+1),MONTH(Assumptions!D8),DAY(Assumptions!D8)) -> 42369 | E41: =DATE(IF(MONTH(Assumptions!D8)=12,E42,E42+1),MONTH(Assumptions!D8),DAY(Assumptions!D8)) -> 42735 | F41: =DATE(IF(MONTH(Assumptions!D8)=12,F42,F42+1),MONTH(Assumptions!D8),DAY(Assumptions!D8)) -> 43100 | G41: =DATE(IF(MONTH(Assumptions!D8)=12,G42,G42+1),MONTH(Assumptions!D8),DAY(Assumptions!D8)) -> 43465 | H41: =DATE(IF(MONTH(Assumptions!D8)=12,H42,H42+1),MONTH(Assumptions!D8),DAY(Assumptions!D8)) -> 43830 | I41: =DATE(IF(MONTH(Assumptions!D8)=12,I42,I42+1),MONTH(Assumptions!D8),DAY(Assumptions!D8)) -> 44196 | J41: =DATE(IF(MONTH(Assumptions!D8)=12,J42,J42+1),MONTH(Assumptions!D8),DAY(Assumptions!D8)) -> 44561 | K41: =DATE(IF(MONTH(Assumptions!D8)=12,K42,K42+1),MONTH(Assumptions!D8),DAY(Assumptions!D8)) -> 44926 | L41: =DATE(IF(MONTH(Assumptions!D8)=12,L42,L42+1),MONTH(Assumptions!D8),DAY(Assumptions!D8)) -> 45291 | M41: =DATE(IF(MONTH(Assumptions!D8)=12,M42,M42+1),MONTH(Assumptions!D8),DAY(Assumptions!D8)) -> 45657 | N41: =DATE(IF(MONTH(Assumptions!D8)=12,N42,N42+1),MONTH(Assumptions!D8),DAY(Assumptions!D8)) -> 46022 | O41: =DATE(IF(MONTH(Assumptions!D8)=12,O42,O42+1),MONTH(Assumptions!D8),DAY(Assumptions!D8)) -> 46387 | P41: =DATE(IF(MONTH(Assumptions!D8)=12,P42,P42+1),MONTH(Assumptions!D8),DAY(Assumptions!D8)) -> 46752
B42: =Assumptions!$D$7 -> 2013 | C42: =+B42+1 -> 2014 | D42: =+C42+1 -> 2015 | E42: =+D42+1 -> 2016 | F42: =+E42+1 -> 2017 | G42: =+F42+1 -> 2018 | H42: =+G42+1 -> 2019 | I42: =+H42+1 -> 2020 | J42: =+I42+1 -> 2021 | ... P42: =+O42+1 -> 2027
A43: SA Month | B43: =IF(YEAR(Assumptions!C22)=B42,IF(MONTH(Assumptions!D8)=12,12-MONTH(Assumptions!C22)+1,IF(MONTH(Assumptions!C22)<MONTH(Assumptions!D8),(MONTH(Assumptions!D8)-MONTH(Assumptions!C22))+1,IF(MONTH(Assumptions!C22)=MONTH(Assumptions!D8),1,""))),IF(AND(A43="",YEAR(Assumptions!C22)+1=B42),((MONTH(B41)+12)-MONTH(Assumptions!C22))+1,IF(YEAR($B$29)=B42,$B$36-SUM(A$43:$B43),IF(B42<YEAR(Assumptions!C22),0,IF(B42<YEAR($B$29),12,IF(B42>YEAR($B$29),0)))))) -> 0 | C43: =IF(YEAR(Assumptions!C22)=C42,IF(MONTH(Assumptions!D8)=12,12-MONTH(Assumptions!C22)+1,IF(MONTH(Assumptions!C22)<MONTH(Assumptions!D8),(MONTH(Assumptions!D8)-MONTH(Assumptions!C22))+1,IF(MONTH(Assumptions!C22)=MONTH(Assumptions!D8),1,""))),IF(AND(B43="",YEAR(Assumptions!C22)+1=C42),((MONTH(C41)+12)-MONTH(Assumptions!C22))+1,IF(YEAR($B$29)=C42,$B$36-SUM(B$43:$B43),IF(C42<YEAR(Assumptions!C22),"",IF(C42<YEAR($B$29),12,IF(C42>YEAR($B$29),"")))))) | D43: =IF(YEAR(Assumptions!C22)=D42,IF(MONTH(Assumptions!D8)=12,12-MONTH(Assumptions!C22)+1,IF(MONTH(Assumptions!C22)<MONTH(Assumptions!D8),(MONTH(Assumptions!D8)-MONTH(Assumptions!C22))+1,IF(MONTH(Assumptions!C22)=MONTH(Assumptions!D8),1,""))),IF(AND(C43="",YEAR(Assumptions!C22)+1=D42),((MONTH(D41)+12)-MONTH(Assumptions!C22))+1,IF(YEAR($B$29)=D42,$B$36-SUM($B$43:C43),IF(D42<YEAR(Assumptions!C22),"",IF(D42<YEAR($B$29),12,IF(D42>YEAR($B$29),"")))))) | E43: =IF(YEAR(Assumptions!C22)=E42,IF(MONTH(Assumptions!D8)=12,12-MONTH(Assumptions!C22)+1,IF(MONTH(Assumptions!C22)<MONTH(Assumptions!D8),(MONTH(Assumptions!D8)-MONTH(Assumptions!C22))+1,IF(MONTH(Assumptions!C22)=MONTH(Assumptions!D8),1,""))),IF(AND(D43="",YEAR(Assumptions!C22)+1=E42),((MONTH(E41)+12)-MONTH(Assumptions!C22))+1,IF(YEAR($B$29)=E42,$B$36-SUM($B$43:D43),IF(E42<YEAR(Assumptions!C22),"",IF(E42<YEAR($B$29),12,IF(E42>YEAR($B$29),"")))))) | F43: =IF(YEAR(Assumptions!C22)=F42,IF(MONTH(Assumptions!D8)=12,12-MONTH(Assumptions!C22)+1,IF(MONTH(Assumptions!C22)<MONTH(Assumptions!D8),(MONTH(Assumptions!D8)-MONTH(Assumptions!C22))+1,IF(MONTH(Assumptions!C22)=MONTH(Assumptions!D8),1,""))),IF(AND(E43="",YEAR(Assumptions!C22)+1=F42),((MONTH(F41)+12)-MONTH(Assumptions!C22))+1,IF(YEAR($B$29)=F42,$B$36-SUM($B$43:E43),IF(F42<YEAR(Assumptions!C22),"",IF(F42<YEAR($B$29),12,IF(F42>YEAR($B$29),"")))))) | G43: =IF(YEAR(Assumptions!C22)=G42,IF(MONTH(Assumptions!D8)=12,12-MONTH(Assumptions!C22)+1,IF(MONTH(Assumptions!C22)<MONTH(Assumptions!D8),(MONTH(Assumptions!D8)-MONTH(Assumptions!C22))+1,IF(MONTH(Assumptions!C22)=MONTH(Assumptions!D8),1,""))),IF(AND(F43="",YEAR(Assumptions!C22)+1=G42),((MONTH(G41)+12)-MONTH(Assumptions!C22))+1,IF(YEAR($B$29)=G42,$B$36-SUM($B$43:F43),IF(G42<YEAR(Assumptions!C22),"",IF(G42<YEAR($B$29),12,IF(G42>YEAR($B$29),"")))))) | H43: =IF(YEAR(Assumptions!C22)=H42,IF(MONTH(Assumptions!D8)=12,12-MONTH(Assumptions!C22)+1,IF(MONTH(Assumptions!C22)<MONTH(Assumptions!D8),(MONTH(Assumptions!D8)-MONTH(Assumptions!C22))+1,IF(MONTH(Assumptions!C22)=MONTH(Assumptions!D8),1,""))),IF(AND(G43="",YEAR(Assumptions!C22)+1=H42),((MONTH(H41)+12)-MONTH(Assumptions!C22))+1,IF(YEAR($B$29)=H42,$B$36-SUM($B$43:G43),IF(H42<YEAR(Assumptions!C22),"",IF(H42<YEAR($B$29),12,IF(H42>YEAR($B$29),"")))))) | I43: =IF(YEAR(Assumptions!C22)=I42,IF(MONTH(Assumptions!D8)=12,12-MONTH(Assumptions!C22)+1,IF(MONTH(Assumptions!C22)<MONTH(Assumptions!D8),(MONTH(Assumptions!D8)-MONTH(Assumptions!C22))+1,IF(MONTH(Assumptions!C22)=MONTH(Assumptions!D8),1,""))),IF(AND(H43="",YEAR(Assumptions!C22)+1=I42),((MONTH(I41)+12)-MONTH(Assumptions!C22))+1,IF(YEAR($B$29)=I42,$B$36-SUM($B$43:H43),IF(I42<YEAR(Assumptions!C22),"",IF(I42<YEAR($B$29),12,IF(I42>YEAR($B$29),"")))))) | J43: =IF(YEAR(Assumptions!C22)=J42,IF(MONTH(Assumptions!D8)=12,12-MONTH(Assumptions!C22)+1,IF(MONTH(Assumptions!C22)<MONTH(Assumptions!D8),(MONTH(Assumptions!D8)-MONTH(Assumptions!C22))+1,IF(MONTH(Assumptions!C22)=MONTH(Assumptions!D8),1,""))),IF(AND(I43="",YEAR(Assumptions!C22)+1=J42),((MONTH(J41)+12)-MONTH(Assumptions!C22))+1,IF(YEAR($B$29)=J42,$B$36-SUM($B$43:I43),IF(J42<YEAR(Assumptions!C22),"",IF(J42<YEAR($B$29),12,IF(J42>YEAR($B$29),"")))))) | K43: =IF(YEAR(Assumptions!C22)=K42,IF(MONTH(Assumptions!D8)=12,12-MONTH(Assumptions!C22)+1,IF(MONTH(Assumptions!C22)<MONTH(Assumptions!D8),(MONTH(Assumptions!D8)-MONTH(Assumptions!C22))+1,IF(MONTH(Assumptions!C22)=MONTH(Assumptions!D8),1,""))),IF(AND(J43="",YEAR(Assumptions!C22)+1=K42),((MONTH(K41)+12)-MONTH(Assumptions!C22))+1,IF(YEAR($B$29)=K42,$B$36-SUM($B$43:J43),IF(K42<YEAR(Assumptions!C22),"",IF(K42<YEAR($B$29),12,IF(K42>YEAR($B$29),"")))))) | L43: =IF(YEAR(Assumptions!C22)=L42,IF(MONTH(Assumptions!D8)=12,12-MONTH(Assumptions!C22)+1,IF(MONTH(Assumptions!C22)<MONTH(Assumptions!D8),(MONTH(Assumptions!D8)-MONTH(Assumptions!C22))+1,IF(MONTH(Assumptions!C22)=MONTH(Assumptions!D8),1,""))),IF(AND(K43="",YEAR(Assumptions!C22)+1=L42),((MONTH(L41)+12)-MONTH(Assumptions!C22))+1,IF(YEAR($B$29)=L42,$B$36-SUM($B$43:K43),IF(L42<YEAR(Assumptions!C22),"",IF(L42<YEAR($B$29),12,IF(L42>YEAR($B$29),"")))))) | M43: =IF(YEAR(Assumptions!C22)=M42,IF(MONTH(Assumptions!D8)=12,12-MONTH(Assumptions!C22)+1,IF(MONTH(Assumptions!C22)<MONTH(Assumptions!D8),(MONTH(Assumptions!D8)-MONTH(Assumptions!C22))+1,IF(MONTH(Assumptions!C22)=MONTH(Assumptions!D8),1,""))),IF(AND(L43="",YEAR(Assumptions!C22)+1=M42),((MONTH(M41)+12)-MONTH(Assumptions!C22))+1,IF(YEAR($B$29)=M42,$B$36-SUM($B$43:L43),IF(M42<YEAR(Assumptions!C22),"",IF(M42<YEAR($B$29),12,IF(M42>YEAR($B$29),"")))))) | N43: =IF(YEAR(Assumptions!C22)=N42,IF(MONTH(Assumptions!D8)=12,12-MONTH(Assumptions!C22)+1,IF(MONTH(Assumptions!C22)<MONTH(Assumptions!D8),(MONTH(Assumptions!D8)-MONTH(Assumptions!C22))+1,IF(MONTH(Assumptions!C22)=MONTH(Assumptions!D8),1,""))),IF(AND(M43="",YEAR(Assumptions!C22)+1=N42),((MONTH(N41)+12)-MONTH(Assumptions!C22))+1,IF(YEAR($B$29)=N42,$B$36-SUM($B$43:M43),IF(N42<YEAR(Assumptions!C22),"",IF(N42<YEAR($B$29),12,IF(N42>YEAR($B$29),"")))))) | O43: =IF(YEAR(Assumptions!C22)=O42,IF(MONTH(Assumptions!D8)=12,12-MONTH(Assumptions!C22)+1,IF(MONTH(Assumptions!C22)<MONTH(Assumptions!D8),(MONTH(Assumptions!D8)-MONTH(Assumptions!C22))+1,IF(MONTH(Assumptions!C22)=MONTH(Assumptions!D8),1,""))),IF(AND(N43="",YEAR(Assumptions!C22)+1=O42),((MONTH(O41)+12)-MONTH(Assumptions!C22))+1,IF(YEAR($B$29)=O42,$B$36-SUM($B$43:N43),IF(O42<YEAR(Assumptions!C22),"",IF(O42<YEAR($B$29),12,IF(O42>YEAR($B$29),"")))))) | P43: =IF(YEAR(Assumptions!C22)=P42,IF(MONTH(Assumptions!D8)=12,12-MONTH(Assumptions!C22)+1,IF(MONTH(Assumptions!C22)<MONTH(Assumptions!D8),(MONTH(Assumptions!D8)-MONTH(Assumptions!C22))+1,IF(MONTH(Assumptions!C22)=MONTH(Assumptions!D8),1,""))),IF(AND(O43="",YEAR(Assumptions!C22)+1=P42),((MONTH(P41)+12)-MONTH(Assumptions!C22))+1,IF(YEAR($B$29)=P42,$B$36-SUM($B$43:O43),IF(P42<YEAR(Assumptions!C22),"",IF(P42<YEAR($B$29),12,IF(P42>YEAR($B$29),""))))))
A44: Loan | B44: =IF(YEAR(Assumptions!C32)=B42,IF(MONTH(Assumptions!D8)=12,MONTH(Assumptions!C32),IF(MONTH(Assumptions!C32)<MONTH(Assumptions!D8),12-((MONTH(Assumptions!D8)-MONTH(Assumptions!C32))),IF(MONTH(Assumptions!C32)=MONTH(Assumptions!D8),1,IF(MONTH(Assumptions!C32)>MONTH(Assumptions!D8),IF(YEAR(Assumptions!C32)+1=B42,(MONTH(Assumptions!C32)-MONTH(B40))+1,""),"")))),IF(YEAR(Assumptions!C32)+1=B42,(MONTH(Assumptions!C32)-MONTH(B40))+1,"")) | C44: =IF(B44="",IF(YEAR(Assumptions!C32)=C42,IF(MONTH(Assumptions!D8)=12,MONTH(Assumptions!C32),IF(MONTH(Assumptions!C32)<MONTH(Assumptions!D8),12-((MONTH(Assumptions!D8)-MONTH(Assumptions!C32))),IF(MONTH(Assumptions!C32)=MONTH(Assumptions!D8),1,IF(MONTH(Assumptions!C32)>MONTH(Assumptions!D8),IF(YEAR(Assumptions!C32)+1=C42,(MONTH(Assumptions!C32)-MONTH(C40))+1,""),"")))),IF(YEAR(Assumptions!C32)+1=C42,(MONTH(Assumptions!C32)-MONTH(C40))+1,"")),"") | D44: =IF(C44="",IF(YEAR(Assumptions!C32)=D42,IF(MONTH(Assumptions!D8)=12,MONTH(Assumptions!C32),IF(MONTH(Assumptions!C32)<MONTH(Assumptions!D8),12-((MONTH(Assumptions!D8)-MONTH(Assumptions!C32))),IF(MONTH(Assumptions!C32)=MONTH(Assumptions!D8),1,IF(MONTH(Assumptions!C32)>MONTH(Assumptions!D8),IF(YEAR(Assumptions!C32)+1=D42,(MONTH(Assumptions!C32)-MONTH(D40))+1,""),"")))),IF(YEAR(Assumptions!C32)+1=D42,(MONTH(Assumptions!C32)-MONTH(D40))+1,"")),"") | E44: =IF(D44="",IF(YEAR(Assumptions!C32)=E42,IF(MONTH(Assumptions!D8)=12,MONTH(Assumptions!C32),IF(MONTH(Assumptions!C32)<MONTH(Assumptions!D8),12-((MONTH(Assumptions!D8)-MONTH(Assumptions!C32))),IF(MONTH(Assumptions!C32)=MONTH(Assumptions!D8),1,IF(MONTH(Assumptions!C32)>MONTH(Assumptions!D8),IF(YEAR(Assumptions!C32)+1=E42,(MONTH(Assumptions!C32)-MONTH(E40))+1,""),"")))),IF(YEAR(Assumptions!C32)+1=E42,(MONTH(Assumptions!C32)-MONTH(E40))+1,"")),"") | F44: =IF(E44="",IF(YEAR(Assumptions!C32)=F42,IF(MONTH(Assumptions!D8)=12,MONTH(Assumptions!C32),IF(MONTH(Assumptions!C32)<MONTH(Assumptions!D8),12-((MONTH(Assumptions!D8)-MONTH(Assumptions!C32))),IF(MONTH(Assumptions!C32)=MONTH(Assumptions!D8),1,IF(MONTH(Assumptions!C32)>MONTH(Assumptions!D8),IF(YEAR(Assumptions!C32)+1=F42,(MONTH(Assumptions!C32)-MONTH(F40))+1,""),"")))),IF(YEAR(Assumptions!C32)+1=F42,(MONTH(Assumptions!C32)-MONTH(F40))+1,"")),"") | G44: =IF(F44="",IF(YEAR(Assumptions!C32)=G42,IF(MONTH(Assumptions!D8)=12,MONTH(Assumptions!C32),IF(MONTH(Assumptions!C32)<MONTH(Assumptions!D8),12-((MONTH(Assumptions!D8)-MONTH(Assumptions!C32))),IF(MONTH(Assumptions!C32)=MONTH(Assumptions!D8),1,IF(MONTH(Assumptions!C32)>MONTH(Assumptions!D8),IF(YEAR(Assumptions!C32)+1=G42,(MONTH(Assumptions!C32)-MONTH(G40))+1,""),"")))),IF(YEAR(Assumptions!C32)+1=G42,(MONTH(Assumptions!C32)-MONTH(G40))+1,"")),"") -> 1 | H44: =IF(G44="",IF(YEAR(Assumptions!C32)=H42,IF(MONTH(Assumptions!D8)=12,MONTH(Assumptions!C32),IF(MONTH(Assumptions!C32)<MONTH(Assumptions!D8),12-((MONTH(Assumptions!D8)-MONTH(Assumptions!C32))),IF(MONTH(Assumptions!C32)=MONTH(Assumptions!D8),1,IF(MONTH(Assumptions!C32)>MONTH(Assumptions!D8),IF(YEAR(Assumptions!C32)+1=H42,(MONTH(Assumptions!C32)-MONTH(H40))+1,""),"")))),IF(YEAR(Assumptions!C32)+1=H42,(MONTH(Assumptions!C32)-MONTH(H40))+1,"")),"") | I44: =IF(H44="",IF(YEAR(Assumptions!C32)=I42,IF(MONTH(Assumptions!D8)=12,MONTH(Assumptions!C32),IF(MONTH(Assumptions!C32)<MONTH(Assumptions!D8),12-((MONTH(Assumptions!D8)-MONTH(Assumptions!C32))),IF(MONTH(Assumptions!C32)=MONTH(Assumptions!D8),1,IF(MONTH(Assumptions!C32)>MONTH(Assumptions!D8),IF(YEAR(Assumptions!C32)+1=I42,(MONTH(Assumptions!C32)-MONTH(I40))+1,""),"")))),IF(YEAR(Assumptions!C32)+1=I42,(MONTH(Assumptions!C32)-MONTH(I40))+1,"")),"") | J44: =IF(I44="",IF(YEAR(Assumptions!C32)=J42,IF(MONTH(Assumptions!D8)=12,MONTH(Assumptions!C32),IF(MONTH(Assumptions!C32)<MONTH(Assumptions!D8),12-((MONTH(Assumptions!D8)-MONTH(Assumptions!C32))),IF(MONTH(Assumptions!C32)=MONTH(Assumptions!D8),1,IF(MONTH(Assumptions!C32)>MONTH(Assumptions!D8),IF(YEAR(Assumptions!C32)+1=J42,(MONTH(Assumptions!C32)-MONTH(J40))+1,""),"")))),IF(YEAR(Assumptions!C32)+1=J42,(MONTH(Assumptions!C32)-MONTH(J40))+1,"")),"") | K44: =IF(J44="",IF(YEAR(Assumptions!C32)=K42,IF(MONTH(Assumptions!D8)=12,MONTH(Assumptions!C32),IF(MONTH(Assumptions!C32)<MONTH(Assumptions!D8),12-((MONTH(Assumptions!D8)-MONTH(Assumptions!C32))),IF(MONTH(Assumptions!C32)=MONTH(Assumptions!D8),1,IF(MONTH(Assumptions!C32)>MONTH(Assumptions!D8),IF(YEAR(Assumptions!C32)+1=K42,(MONTH(Assumptions!C32)-MONTH(K40))+1,""),"")))),IF(YEAR(Assumptions!C32)+1=K42,(MONTH(Assumptions!C32)-MONTH(K40))+1,"")),"") | L44: =IF(K44="",IF(YEAR(Assumptions!C32)=L42,IF(MONTH(Assumptions!D8)=12,MONTH(Assumptions!C32),IF(MONTH(Assumptions!C32)<MONTH(Assumptions!D8),12-((MONTH(Assumptions!D8)-MONTH(Assumptions!C32))),IF(MONTH(Assumptions!C32)=MONTH(Assumptions!D8),1,IF(MONTH(Assumptions!C32)>MONTH(Assumptions!D8),IF(YEAR(Assumptions!C32)+1=L42,(MONTH(Assumptions!C32)-MONTH(L40))+1,""),"")))),IF(YEAR(Assumptions!C32)+1=L42,(MONTH(Assumptions!C32)-MONTH(L40))+1,"")),"") | M44: =IF(L44="",IF(YEAR(Assumptions!C32)=M42,IF(MONTH(Assumptions!D8)=12,MONTH(Assumptions!C32),IF(MONTH(Assumptions!C32)<MONTH(Assumptions!D8),12-((MONTH(Assumptions!D8)-MONTH(Assumptions!C32))),IF(MONTH(Assumptions!C32)=MONTH(Assumptions!D8),1,IF(MONTH(Assumptions!C32)>MONTH(Assumptions!D8),IF(YEAR(Assumptions!C32)+1=M42,(MONTH(Assumptions!C32)-MONTH(M40))+1,""),"")))),IF(YEAR(Assumptions!C32)+1=M42,(MONTH(Assumptions!C32)-MONTH(M40))+1,"")),"") | N44: =IF(M44="",IF(YEAR(Assumptions!C32)=N42,IF(MONTH(Assumptions!D8)=12,MONTH(Assumptions!C32),IF(MONTH(Assumptions!C32)<MONTH(Assumptions!D8),12-((MONTH(Assumptions!D8)-MONTH(Assumptions!C32))),IF(MONTH(Assumptions!C32)=MONTH(Assumptions!D8),1,IF(MONTH(Assumptions!C32)>MONTH(Assumptions!D8),IF(YEAR(Assumptions!C32)+1=N42,(MONTH(Assumptions!C32)-MONTH(N40))+1,""),"")))),IF(YEAR(Assumptions!C32)+1=N42,(MONTH(Assumptions!C32)-MONTH(N40))+1,"")),"") | O44: =IF(N44="",IF(YEAR(Assumptions!C32)=O42,IF(MONTH(Assumptions!D8)=12,MONTH(Assumptions!C32),IF(MONTH(Assumptions!C32)<MONTH(Assumptions!D8),12-((MONTH(Assumptions!D8)-MONTH(Assumptions!C32))),IF(MONTH(Assumptions!C32)=MONTH(Assumptions!D8),1,IF(MONTH(Assumptions!C32)>MONTH(Assumptions!D8),IF(YEAR(Assumptions!C32)+1=O42,(MONTH(Assumptions!C32)-MONTH(O40))+1,""),"")))),IF(YEAR(Assumptions!C32)+1=O42,(MONTH(Assumptions!C32)-MONTH(O40))+1,"")),"") | P44: =IF(O44="",IF(YEAR(Assumptions!C32)=P42,IF(MONTH(Assumptions!D8)=12,MONTH(Assumptions!C32),IF(MONTH(Assumptions!C32)<MONTH(Assumptions!D8),12-((MONTH(Assumptions!D8)-MONTH(Assumptions!C32))),IF(MONTH(Assumptions!C32)=MONTH(Assumptions!D8),1,IF(MONTH(Assumptions!C32)>MONTH(Assumptions!D8),IF(YEAR(Assumptions!C32)+1=P42,(MONTH(Assumptions!C32)-MONTH(P40))+1,""),"")))),IF(YEAR(Assumptions!C32)+1=P42,(MONTH(Assumptions!C32)-MONTH(P40))+1,"")),"")
A45: SA Fee | B45: =IF(YEAR(Assumptions!C22)=B42,IF(MONTH(Assumptions!D8)=12,1,IF(MONTH(Assumptions!C22)<MONTH(B40),1,"")),IF(A45="",IF(B42=YEAR(Assumptions!C22)+1,1,""),"")) | C45: =IF(YEAR(Assumptions!C22)=C42,IF(MONTH(Assumptions!D8)=12,1,IF(MONTH(Assumptions!C22)<MONTH(C40),1,"")),IF(B45="",IF(C42=YEAR(Assumptions!C22)+1,1,""),"")) | D45: =IF(YEAR(Assumptions!C22)=D42,IF(MONTH(Assumptions!D8)=12,1,IF(MONTH(Assumptions!C22)<MONTH(D40),1,"")),IF(C45="",IF(D42=YEAR(Assumptions!C22)+1,1,""),"")) | E45: =IF(YEAR(Assumptions!C22)=E42,IF(MONTH(Assumptions!D8)=12,1,IF(MONTH(Assumptions!C22)<MONTH(E40),1,"")),IF(D45="",IF(E42=YEAR(Assumptions!C22)+1,1,""),"")) | F45: =IF(YEAR(Assumptions!C22)=F42,IF(MONTH(Assumptions!D8)=12,1,IF(MONTH(Assumptions!C22)<MONTH(F40),1,"")),IF(E45="",IF(F42=YEAR(Assumptions!C22)+1,1,""),"")) | G45: =IF(YEAR(Assumptions!C22)=G42,IF(MONTH(Assumptions!D8)=12,1,IF(MONTH(Assumptions!C22)<MONTH(G40),1,"")),IF(F45="",IF(G42=YEAR(Assumptions!C22)+1,1,""),"")) | H45: =IF(YEAR(Assumptions!C22)=H42,IF(MONTH(Assumptions!D8)=12,1,IF(MONTH(Assumptions!C22)<MONTH(H40),1,"")),IF(G45="",IF(H42=YEAR(Assumptions!C22)+1,1,""),"")) | I45: =IF(YEAR(Assumptions!C22)=I42,IF(MONTH(Assumptions!D8)=12,1,IF(MONTH(Assumptions!C22)<MONTH(I40),1,"")),IF(H45="",IF(I42=YEAR(Assumptions!C22)+1,1,""),"")) | J45: =IF(YEAR(Assumptions!C22)=J42,IF(MONTH(Assumptions!D8)=12,1,IF(MONTH(Assumptions!C22)<MONTH(J40),1,"")),IF(I45="",IF(J42=YEAR(Assumptions!C22)+1,1,""),"")) | K45: =IF(YEAR(Assumptions!C22)=K42,IF(MONTH(Assumptions!D8)=12,1,IF(MONTH(Assumptions!C22)<MONTH(K40),1,"")),IF(J45="",IF(K42=YEAR(Assumptions!C22)+1,1,""),"")) | L45: =IF(YEAR(Assumptions!C22)=L42,IF(MONTH(Assumptions!D8)=12,1,IF(MONTH(Assumptions!C22)<MONTH(L40),1,"")),IF(K45="",IF(L42=YEAR(Assumptions!C22)+1,1,""),"")) | M45: =IF(YEAR(Assumptions!C22)=M42,IF(MONTH(Assumptions!D8)=12,1,IF(MONTH(Assumptions!C22)<MONTH(M40),1,"")),IF(L45="",IF(M42=YEAR(Assumptions!C22)+1,1,""),"")) | N45: =IF(YEAR(Assumptions!C22)=N42,IF(MONTH(Assumptions!D8)=12,1,IF(MONTH(Assumptions!C22)<MONTH(N40),1,"")),IF(M45="",IF(N42=YEAR(Assumptions!C22)+1,1,""),"")) | O45: =IF(YEAR(Assumptions!C22)=O42,IF(MONTH(Assumptions!D8)=12,1,IF(MONTH(Assumptions!C22)<MONTH(O40),1,"")),IF(N45="",IF(O42=YEAR(Assumptions!C22)+1,1,""),"")) | P45: =IF(YEAR(Assumptions!C22)=P42,IF(MONTH(Assumptions!D8)=12,1,IF(MONTH(Assumptions!C22)<MONTH(P40),1,"")),IF(O45="",IF(P42=YEAR(Assumptions!C22)+1,1,""),""))
A46: Loan Proceed | B46: =IF(YEAR(Assumptions!C32)=B42,IF(MONTH(Assumptions!D8)=12,1,IF(MONTH(Assumptions!C32)<MONTH(B40),1,"")),IF(A46="",IF(B42=YEAR(Assumptions!C32)+1,1,""),"")) | C46: =IF(YEAR(Assumptions!C32)=C42,IF(MONTH(Assumptions!D8)=12,1,IF(MONTH(Assumptions!C32)<MONTH(C40),1,"")),IF(B46="",IF(C42=YEAR(Assumptions!C32)+1,1,""),"")) | D46: =IF(YEAR(Assumptions!C32)=D42,IF(MONTH(Assumptions!D8)=12,1,IF(MONTH(Assumptions!C32)<MONTH(D40),1,"")),IF(C46="",IF(D42=YEAR(Assumptions!C32)+1,1,""),"")) | E46: =IF(YEAR(Assumptions!C32)=E42,IF(MONTH(Assumptions!D8)=12,1,IF(MONTH(Assumptions!C32)<MONTH(E40),1,"")),IF(D46="",IF(E42=YEAR(Assumptions!C32)+1,1,""),"")) | F46: =IF(YEAR(Assumptions!C32)=F42,IF(MONTH(Assumptions!D8)=12,1,IF(MONTH(Assumptions!C32)<MONTH(F40),1,"")),IF(E46="",IF(F42=YEAR(Assumptions!C32)+1,1,""),"")) | G46: =IF(YEAR(Assumptions!C32)=G42,IF(MONTH(Assumptions!D8)=12,1,IF(MONTH(Assumptions!C32)<MONTH(G40),1,"")),IF(F46="",IF(G42=YEAR(Assumptions!C32)+1,1,""),"")) -> 1 | H46: =IF(YEAR(Assumptions!C32)=H42,IF(MONTH(Assumptions!D8)=12,1,IF(MONTH(Assumptions!C32)<MONTH(H40),1,"")),IF(G46="",IF(H42=YEAR(Assumptions!C32)+1,1,""),"")) | I46: =IF(YEAR(Assumptions!C32)=I42,IF(MONTH(Assumptions!D8)=12,1,IF(MONTH(Assumptions!C32)<MONTH(I40),1,"")),IF(H46="",IF(I42=YEAR(Assumptions!C32)+1,1,""),"")) | J46: =IF(YEAR(Assumptions!C32)=J42,IF(MONTH(Assumptions!D8)=12,1,IF(MONTH(Assumptions!C32)<MONTH(J40),1,"")),IF(I46="",IF(J42=YEAR(Assumptions!C32)+1,1,""),"")) | K46: =IF(YEAR(Assumptions!C32)=K42,IF(MONTH(Assumptions!D8)=12,1,IF(MONTH(Assumptions!C32)<MONTH(K40),1,"")),IF(J46="",IF(K42=YEAR(Assumptions!C32)+1,1,""),"")) | L46: =IF(YEAR(Assumptions!C32)=L42,IF(MONTH(Assumptions!D8)=12,1,IF(MONTH(Assumptions!C32)<MONTH(L40),1,"")),IF(K46="",IF(L42=YEAR(Assumptions!C32)+1,1,""),"")) | M46: =IF(YEAR(Assumptions!C32)=M42,IF(MONTH(Assumptions!D8)=12,1,IF(MONTH(Assumptions!C32)<MONTH(M40),1,"")),IF(L46="",IF(M42=YEAR(Assumptions!C32)+1,1,""),"")) | N46: =IF(YEAR(Assumptions!C32)=N42,IF(MONTH(Assumptions!D8)=12,1,IF(MONTH(Assumptions!C32)<MONTH(N40),1,"")),IF(M46="",IF(N42=YEAR(Assumptions!C32)+1,1,""),"")) | O46: =IF(YEAR(Assumptions!C32)=O42,IF(MONTH(Assumptions!D8)=12,1,IF(MONTH(Assumptions!C32)<MONTH(O40),1,"")),IF(N46="",IF(O42=YEAR(Assumptions!C32)+1,1,""),"")) | P46: =IF(YEAR(Assumptions!C32)=P42,IF(MONTH(Assumptions!D8)=12,1,IF(MONTH(Assumptions!C32)<MONTH(P40),1,"")),IF(O46="",IF(P42=YEAR(Assumptions!C32)+1,1,""),""))
F49: Assessments for Option 3
B51: =DATE(C54+1,B54,26) -> 45286
B54: =MONTH(Assumptions!D23)-MONTH(Assumptions!D8) -> 0 | C54: =YEAR(Assumptions!D23) -> 2023 | D54: =MONTH(Assumptions!D23) -> 12 | E54: =DAY(Assumptions!D23) -> 30 | G54: =IF(B65="",1,B65) -> 0
B58: =Assumptions!D24*12 -> 120
A60: Loan Clac | B60: =IF((MONTH(B63)-MONTH(Assumptions!D32))+1=12,0,(MONTH(B63)-MONTH(Assumptions!D32))+1) -> 0 | C60: =IF((MONTH(C63)-MONTH(Assumptions!D32))+1=12,0,(MONTH(C63)-MONTH(Assumptions!D32))+1) -> 0 | D60: =IF((MONTH(D63)-MONTH(Assumptions!D32))+1=12,0,(MONTH(D63)-MONTH(Assumptions!D32))+1) -> 0 | E60: =IF((MONTH(E63)-MONTH(Assumptions!D32))+1=12,0,(MONTH(E63)-MONTH(Assumptions!D32))+1) -> 0 | F60: =IF((MONTH(F63)-MONTH(Assumptions!D32))+1=12,0,(MONTH(F63)-MONTH(Assumptions!D32))+1) -> 0 | G60: =IF((MONTH(G63)-MONTH(Assumptions!D32))+1=12,0,(MONTH(G63)-MONTH(Assumptions!D32))+1) -> 0 | H60: =IF((MONTH(H63)-MONTH(Assumptions!D32))+1=12,0,(MONTH(H63)-MONTH(Assumptions!D32))+1) -> 0 | I60: =IF((MONTH(I63)-MONTH(Assumptions!D32))+1=12,0,(MONTH(I63)-MONTH(Assumptions!D32))+1) -> 0 | J60: =IF((MONTH(J63)-MONTH(Assumptions!D32))+1=12,0,(MONTH(J63)-MONTH(Assumptions!D32))+1) -> 0 | K60: =IF((MONTH(K63)-MONTH(Assumptions!D32))+1=12,0,(MONTH(K63)-MONTH(Assumptions!D32))+1) -> 0 | L60: =IF((MONTH(L63)-MONTH(Assumptions!D32))+1=12,0,(MONTH(L63)-MONTH(Assumptions!D32))+1) -> 0 | M60: =IF((MONTH(M63)-MONTH(Assumptions!D32))+1=12,0,(MONTH(M63)-MONTH(Assumptions!D32))+1) -> 0 | N60: =IF((MONTH(N63)-MONTH(Assumptions!D32))+1=12,0,(MONTH(N63)-MONTH(Assumptions!D32))+1) -> 0 | O60: =IF((MONTH(O63)-MONTH(Assumptions!D32))+1=12,0,(MONTH(O63)-MONTH(Assumptions!D32))+1) -> 0 | P60: =IF((MONTH(P63)-MONTH(Assumptions!D32))+1=12,0,(MONTH(P63)-MONTH(Assumptions!D32))+1) -> 0
A61: SA Calc | B61: =IF((MONTH(B63)-MONTH(Assumptions!D22))+1=12,0,(MONTH(B63)-MONTH(Assumptions!D22))+1) -> 0 | C61: =IF((MONTH(C63)-MONTH(Assumptions!D22))+1=12,0,(MONTH(C63)-MONTH(Assumptions!D22))+1) -> 0 | D61: =IF((MONTH(D63)-MONTH(Assumptions!D22))+1=12,0,(MONTH(D63)-MONTH(Assumptions!D22))+1) -> 0 | E61: =IF((MONTH(E63)-MONTH(Assumptions!D22))+1=12,0,(MONTH(E63)-MONTH(Assumptions!D22))+1) -> 0 | F61: =IF((MONTH(F63)-MONTH(Assumptions!D22))+1=12,0,(MONTH(F63)-MONTH(Assumptions!D22))+1) -> 0 | G61: =IF((MONTH(G63)-MONTH(Assumptions!D22))+1=12,0,(MONTH(G63)-MONTH(Assumptions!D22))+1) -> 0 | H61: =IF((MONTH(H63)-MONTH(Assumptions!D22))+1=12,0,(MONTH(H63)-MONTH(Assumptions!D22))+1) -> 0 | I61: =IF((MONTH(I63)-MONTH(Assumptions!D22))+1=12,0,(MONTH(I63)-MONTH(Assumptions!D22))+1) -> 0 | J61: =IF((MONTH(J63)-MONTH(Assumptions!D22))+1=12,0,(MONTH(J63)-MONTH(Assumptions!D22))+1) -> 0 | K61: =IF((MONTH(K63)-MONTH(Assumptions!D22))+1=12,0,(MONTH(K63)-MONTH(Assumptions!D22))+1) -> 0 | L61: =IF((MONTH(L63)-MONTH(Assumptions!D22))+1=12,0,(MONTH(L63)-MONTH(Assumptions!D22))+1) -> 0 | M61: =IF((MONTH(M63)-MONTH(Assumptions!D22))+1=12,0,(MONTH(M63)-MONTH(Assumptions!D22))+1) -> 0 | N61: =IF((MONTH(N63)-MONTH(Assumptions!D22))+1=12,0,(MONTH(N63)-MONTH(Assumptions!D22))+1) -> 0 | O61: =IF((MONTH(O63)-MONTH(Assumptions!D22))+1=12,0,(MONTH(O63)-MONTH(Assumptions!D22))+1) -> 0 | P61: =IF((MONTH(P63)-MONTH(Assumptions!D22))+1=12,0,(MONTH(P63)-MONTH(Assumptions!D22))+1) -> 0
A62: Beg | B62: =DATE(B64,IF(MONTH(Assumptions!D8)=12,1,MONTH(Assumptions!D8)+1),1) -> 41275 | C62: =DATE(C64,IF(MONTH(Assumptions!D8)=12,1,MONTH(Assumptions!D8)+1),1) -> 41640 | D62: =DATE(D64,IF(MONTH(Assumptions!D8)=12,1,MONTH(Assumptions!D8)+1),1) -> 42005 | E62: =DATE(E64,IF(MONTH(Assumptions!D8)=12,1,MONTH(Assumptions!D8)+1),1) -> 42370 | F62: =DATE(F64,IF(MONTH(Assumptions!D8)=12,1,MONTH(Assumptions!D8)+1),1) -> 42736 | G62: =DATE(G64,IF(MONTH(Assumptions!D8)=12,1,MONTH(Assumptions!D8)+1),1) -> 43101 | H62: =DATE(H64,IF(MONTH(Assumptions!D8)=12,1,MONTH(Assumptions!D8)+1),1) -> 43466 | I62: =DATE(I64,IF(MONTH(Assumptions!D8)=12,1,MONTH(Assumptions!D8)+1),1) -> 43831 | J62: =DATE(J64,IF(MONTH(Assumptions!D8)=12,1,MONTH(Assumptions!D8)+1),1) -> 44197 | K62: =DATE(K64,IF(MONTH(Assumptions!D8)=12,1,MONTH(Assumptions!D8)+1),1) -> 44562 | L62: =DATE(L64,IF(MONTH(Assumptions!D8)=12,1,MONTH(Assumptions!D8)+1),1) -> 44927 | M62: =DATE(M64,IF(MONTH(Assumptions!D8)=12,1,MONTH(Assumptions!D8)+1),1) -> 45292 | N62: =DATE(N64,IF(MONTH(Assumptions!D8)=12,1,MONTH(Assumptions!D8)+1),1) -> 45658 | O62: =DATE(O64,IF(MONTH(Assumptions!D8)=12,1,MONTH(Assumptions!D8)+1),1) -> 46023 | P62: =DATE(P64,IF(MONTH(Assumptions!D8)=12,1,MONTH(Assumptions!D8)+1),1) -> 46388
A63: End | B63: =DATE(IF(MONTH(Assumptions!D8)=12,B64,B64+1),MONTH(Assumptions!D8),DAY(Assumptions!D8)) -> 41639 | C63: =DATE(IF(MONTH(Assumptions!D8)=12,C64,C64+1),MONTH(Assumptions!D8),DAY(Assumptions!D8)) -> 42004 | D63: =DATE(IF(MONTH(Assumptions!D8)=12,D64,D64+1),MONTH(Assumptions!D8),DAY(Assumptions!D8)) -> 42369 | E63: =DATE(IF(MONTH(Assumptions!D8)=12,E64,E64+1),MONTH(Assumptions!D8),DAY(Assumptions!D8)) -> 42735 | F63: =DATE(IF(MONTH(Assumptions!D8)=12,F64,F64+1),MONTH(Assumptions!D8),DAY(Assumptions!D8)) -> 43100 | G63: =DATE(IF(MONTH(Assumptions!D8)=12,G64,G64+1),MONTH(Assumptions!D8),DAY(Assumptions!D8)) -> 43465 | H63: =DATE(IF(MONTH(Assumptions!D8)=12,H64,H64+1),MONTH(Assumptions!D8),DAY(Assumptions!D8)) -> 43830 | I63: =DATE(IF(MONTH(Assumptions!D8)=12,I64,I64+1),MONTH(Assumptions!D8),DAY(Assumptions!D8)) -> 44196 | J63: =DATE(IF(MONTH(Assumptions!D8)=12,J64,J64+1),MONTH(Assumptions!D8),DAY(Assumptions!D8)) -> 44561 | K63: =DATE(IF(MONTH(Assumptions!D8)=12,K64,K64+1),MONTH(Assumptions!D8),DAY(Assumptions!D8)) -> 44926 | L63: =DATE(IF(MONTH(Assumptions!D8)=12,L64,L64+1),MONTH(Assumptions!D8),DAY(Assumptions!D8)) -> 45291 | M63: =DATE(IF(MONTH(Assumptions!D8)=12,M64,M64+1),MONTH(Assumptions!D8),DAY(Assumptions!D8)) -> 45657 | N63: =DATE(IF(MONTH(Assumptions!D8)=12,N64,N64+1),MONTH(Assumptions!D8),DAY(Assumptions!D8)) -> 46022 | O63: =DATE(IF(MONTH(Assumptions!D8)=12,O64,O64+1),MONTH(Assumptions!D8),DAY(Assumptions!D8)) -> 46387 | P63: =DATE(IF(MONTH(Assumptions!D8)=12,P64,P64+1),MONTH(Assumptions!D8),DAY(Assumptions!D8)) -> 46752
B64: =Assumptions!$D$7 -> 2013 | C64: =+B64+1 -> 2014 | D64: =+C64+1 -> 2015 | E64: =+D64+1 -> 2016 | F64: =+E64+1 -> 2017 | G64: =+F64+1 -> 2018 | H64: =+G64+1 -> 2019 | I64: =+H64+1 -> 2020 | J64: =+I64+1 -> 2021 | ... P64: =+O64+1 -> 2027
A65: SA Month | B65: =IF(YEAR(Assumptions!D22)=B64,IF(MONTH(Assumptions!D8)=12,12-MONTH(Assumptions!D22)+1,IF(MONTH(Assumptions!D22)<MONTH(Assumptions!D8),(MONTH(Assumptions!D8)-MONTH(Assumptions!D22))+1,IF(MONTH(Assumptions!D22)=MONTH(Assumptions!D8),1,""))),IF(AND(A65="",YEAR(Assumptions!D22)+1=B64),((MONTH(B63)+12)-MONTH(Assumptions!D22))+1,IF(YEAR($B$51)=B64,$B$58-SUM(A$65:$B65),IF(B64<YEAR(Assumptions!D22),0,IF(B64<YEAR($B$51),12,IF(B64>YEAR($B$51),0)))))) -> 0 | C65: =IF(YEAR(Assumptions!D22)=C64,IF(MONTH(Assumptions!D8)=12,12-MONTH(Assumptions!D22)+1,IF(MONTH(Assumptions!D22)<MONTH(Assumptions!D8),(MONTH(Assumptions!D8)-MONTH(Assumptions!D22))+1,IF(MONTH(Assumptions!D22)=MONTH(Assumptions!D8),1,""))),IF(AND(B65="",YEAR(Assumptions!D22)+1=C64),((MONTH(C63)+12)-MONTH(Assumptions!D22))+1,IF(YEAR($B$51)=C64,$B$58-SUM(B$65:$B65),IF(C64<YEAR(Assumptions!D22),"",IF(C64<YEAR($B$51),12,IF(C64>YEAR($B$51),"")))))) -> 12 | D65: =IF(YEAR(Assumptions!D22)=D64,IF(MONTH(Assumptions!D8)=12,12-MONTH(Assumptions!D22)+1,IF(MONTH(Assumptions!D22)<MONTH(Assumptions!D8),(MONTH(Assumptions!D8)-MONTH(Assumptions!D22))+1,IF(MONTH(Assumptions!D22)=MONTH(Assumptions!D8),1,""))),IF(AND(C65="",YEAR(Assumptions!D22)+1=D64),((MONTH(D63)+12)-MONTH(Assumptions!D22))+1,IF(YEAR($B$51)=D64,$B$58-SUM($B$65:C65),IF(D64<YEAR(Assumptions!D22),"",IF(D64<YEAR($B$51),12,IF(D64>YEAR($B$51),"")))))) -> 12 | E65: =IF(YEAR(Assumptions!D22)=E64,IF(MONTH(Assumptions!D8)=12,12-MONTH(Assumptions!D22)+1,IF(MONTH(Assumptions!D22)<MONTH(Assumptions!D8),(MONTH(Assumptions!D8)-MONTH(Assumptions!D22))+1,IF(MONTH(Assumptions!D22)=MONTH(Assumptions!D8),1,""))),IF(AND(D65="",YEAR(Assumptions!D22)+1=E64),((MONTH(E63)+12)-MONTH(Assumptions!D22))+1,IF(YEAR($B$51)=E64,$B$58-SUM($B$65:D65),IF(E64<YEAR(Assumptions!D22),"",IF(E64<YEAR($B$51),12,IF(E64>YEAR($B$51),"")))))) -> 12 | F65: =IF(YEAR(Assumptions!D22)=F64,IF(MONTH(Assumptions!D8)=12,12-MONTH(Assumptions!D22)+1,IF(MONTH(Assumptions!D22)<MONTH(Assumptions!D8),(MONTH(Assumptions!D8)-MONTH(Assumptions!D22))+1,IF(MONTH(Assumptions!D22)=MONTH(Assumptions!D8),1,""))),IF(AND(E65="",YEAR(Assumptions!D22)+1=F64),((MONTH(F63)+12)-MONTH(Assumptions!D22))+1,IF(YEAR($B$51)=F64,$B$58-SUM($B$65:E65),IF(F64<YEAR(Assumptions!D22),"",IF(F64<YEAR($B$51),12,IF(F64>YEAR($B$51),"")))))) -> 12 | G65: =IF(YEAR(Assumptions!D22)=G64,IF(MONTH(Assumptions!D8)=12,12-MONTH(Assumptions!D22)+1,IF(MONTH(Assumptions!D22)<MONTH(Assumptions!D8),(MONTH(Assumptions!D8)-MONTH(Assumptions!D22))+1,IF(MONTH(Assumptions!D22)=MONTH(Assumptions!D8),1,""))),IF(AND(F65="",YEAR(Assumptions!D22)+1=G64),((MONTH(G63)+12)-MONTH(Assumptions!D22))+1,IF(YEAR($B$51)=G64,$B$58-SUM($B$65:F65),IF(G64<YEAR(Assumptions!D22),"",IF(G64<YEAR($B$51),12,IF(G64>YEAR($B$51),"")))))) -> 12 | H65: =IF(YEAR(Assumptions!D22)=H64,IF(MONTH(Assumptions!D8)=12,12-MONTH(Assumptions!D22)+1,IF(MONTH(Assumptions!D22)<MONTH(Assumptions!D8),(MONTH(Assumptions!D8)-MONTH(Assumptions!D22))+1,IF(MONTH(Assumptions!D22)=MONTH(Assumptions!D8),1,""))),IF(AND(G65="",YEAR(Assumptions!D22)+1=H64),((MONTH(H63)+12)-MONTH(Assumptions!D22))+1,IF(YEAR($B$51)=H64,$B$58-SUM($B$65:G65),IF(H64<YEAR(Assumptions!D22),"",IF(H64<YEAR($B$51),12,IF(H64>YEAR($B$51),"")))))) -> 12 | I65: =IF(YEAR(Assumptions!D22)=I64,IF(MONTH(Assumptions!D8)=12,12-MONTH(Assumptions!D22)+1,IF(MONTH(Assumptions!D22)<MONTH(Assumptions!D8),(MONTH(Assumptions!D8)-MONTH(Assumptions!D22))+1,IF(MONTH(Assumptions!D22)=MONTH(Assumptions!D8),1,""))),IF(AND(H65="",YEAR(Assumptions!D22)+1=I64),((MONTH(I63)+12)-MONTH(Assumptions!D22))+1,IF(YEAR($B$51)=I64,$B$58-SUM($B$65:H65),IF(I64<YEAR(Assumptions!D22),"",IF(I64<YEAR($B$51),12,IF(I64>YEAR($B$51),"")))))) -> 12 | J65: =IF(YEAR(Assumptions!D22)=J64,IF(MONTH(Assumptions!D8)=12,12-MONTH(Assumptions!D22)+1,IF(MONTH(Assumptions!D22)<MONTH(Assumptions!D8),(MONTH(Assumptions!D8)-MONTH(Assumptions!D22))+1,IF(MONTH(Assumptions!D22)=MONTH(Assumptions!D8),1,""))),IF(AND(I65="",YEAR(Assumptions!D22)+1=J64),((MONTH(J63)+12)-MONTH(Assumptions!D22))+1,IF(YEAR($B$51)=J64,$B$58-SUM($B$65:I65),IF(J64<YEAR(Assumptions!D22),"",IF(J64<YEAR($B$51),12,IF(J64>YEAR($B$51),"")))))) -> 12 | K65: =IF(YEAR(Assumptions!D22)=K64,IF(MONTH(Assumptions!D8)=12,12-MONTH(Assumptions!D22)+1,IF(MONTH(Assumptions!D22)<MONTH(Assumptions!D8),(MONTH(Assumptions!D8)-MONTH(Assumptions!D22))+1,IF(MONTH(Assumptions!D22)=MONTH(Assumptions!D8),1,""))),IF(AND(J65="",YEAR(Assumptions!D22)+1=K64),((MONTH(K63)+12)-MONTH(Assumptions!D22))+1,IF(YEAR($B$51)=K64,$B$58-SUM($B$65:J65),IF(K64<YEAR(Assumptions!D22),"",IF(K64<YEAR($B$51),12,IF(K64>YEAR($B$51),"")))))) -> 12 | L65: =IF(YEAR(Assumptions!D22)=L64,IF(MONTH(Assumptions!D8)=12,12-MONTH(Assumptions!D22)+1,IF(MONTH(Assumptions!D22)<MONTH(Assumptions!D8),(MONTH(Assumptions!D8)-MONTH(Assumptions!D22))+1,IF(MONTH(Assumptions!D22)=MONTH(Assumptions!D8),1,""))),IF(AND(K65="",YEAR(Assumptions!D22)+1=L64),((MONTH(L63)+12)-MONTH(Assumptions!D22))+1,IF(YEAR($B$51)=L64,$B$58-SUM($B$65:K65),IF(L64<YEAR(Assumptions!D22),"",IF(L64<YEAR($B$51),12,IF(L64>YEAR($B$51),"")))))) -> 12 | M65: =IF(YEAR(Assumptions!D22)=M64,IF(MONTH(Assumptions!D8)=12,12-MONTH(Assumptions!D22)+1,IF(MONTH(Assumptions!D22)<MONTH(Assumptions!D8),(MONTH(Assumptions!D8)-MONTH(Assumptions!D22))+1,IF(MONTH(Assumptions!D22)=MONTH(Assumptions!D8),1,""))),IF(AND(L65="",YEAR(Assumptions!D22)+1=M64),((MONTH(M63)+12)-MONTH(Assumptions!D22))+1,IF(YEAR($B$51)=M64,$B$58-SUM($B$65:L65),IF(M64<YEAR(Assumptions!D22),"",IF(M64<YEAR($B$51),12,IF(M64>YEAR($B$51),"")))))) | N65: =IF(YEAR(Assumptions!D22)=N64,IF(MONTH(Assumptions!D8)=12,12-MONTH(Assumptions!D22)+1,IF(MONTH(Assumptions!D22)<MONTH(Assumptions!D8),(MONTH(Assumptions!D8)-MONTH(Assumptions!D22))+1,IF(MONTH(Assumptions!D22)=MONTH(Assumptions!D8),1,""))),IF(AND(M65="",YEAR(Assumptions!D22)+1=N64),((MONTH(N63)+12)-MONTH(Assumptions!D22))+1,IF(YEAR($B$51)=N64,$B$58-SUM($B$65:M65),IF(N64<YEAR(Assumptions!D22),"",IF(N64<YEAR($B$51),12,IF(N64>YEAR($B$51),"")))))) | O65: =IF(YEAR(Assumptions!D22)=O64,IF(MONTH(Assumptions!D8)=12,12-MONTH(Assumptions!D22)+1,IF(MONTH(Assumptions!D22)<MONTH(Assumptions!D8),(MONTH(Assumptions!D8)-MONTH(Assumptions!D22))+1,IF(MONTH(Assumptions!D22)=MONTH(Assumptions!D8),1,""))),IF(AND(N65="",YEAR(Assumptions!D22)+1=O64),((MONTH(O63)+12)-MONTH(Assumptions!D22))+1,IF(YEAR($B$51)=O64,$B$58-SUM($B$65:N65),IF(O64<YEAR(Assumptions!D22),"",IF(O64<YEAR($B$51),12,IF(O64>YEAR($B$51),"")))))) | P65: =IF(YEAR(Assumptions!D22)=P64,IF(MONTH(Assumptions!D8)=12,12-MONTH(Assumptions!D22)+1,IF(MONTH(Assumptions!D22)<MONTH(Assumptions!D8),(MONTH(Assumptions!D8)-MONTH(Assumptions!D22))+1,IF(MONTH(Assumptions!D22)=MONTH(Assumptions!D8),1,""))),IF(AND(O65="",YEAR(Assumptions!D22)+1=P64),((MONTH(P63)+12)-MONTH(Assumptions!D22))+1,IF(YEAR($B$51)=P64,$B$58-SUM($B$65:O65),IF(P64<YEAR(Assumptions!D22),"",IF(P64<YEAR($B$51),12,IF(P64>YEAR($B$51),""))))))
A66: Loan | B66: =IF(YEAR(Assumptions!D32)=B64,IF(MONTH(Assumptions!D8)=12,MONTH(Assumptions!D32),IF(MONTH(Assumptions!D32)<MONTH(Assumptions!D8),12-((MONTH(Assumptions!D8)-MONTH(Assumptions!D32))),IF(MONTH(Assumptions!D32)=MONTH(Assumptions!D8),1,IF(MONTH(Assumptions!D32)>MONTH(Assumptions!D8),IF(YEAR(Assumptions!D32)+1=B64,(MONTH(Assumptions!D32)-MONTH(B62))+1,""),"")))),IF(YEAR(Assumptions!D32)+1=B64,(MONTH(Assumptions!D32)-MONTH(B62))+1,"")) | C66: =IF(B66="",IF(YEAR(Assumptions!D32)=C64,IF(MONTH(Assumptions!D8)=12,MONTH(Assumptions!D32),IF(MONTH(Assumptions!D32)<MONTH(Assumptions!D8),12-((MONTH(Assumptions!D8)-MONTH(Assumptions!D32))),IF(MONTH(Assumptions!D32)=MONTH(Assumptions!D8),1,IF(MONTH(Assumptions!D32)>MONTH(Assumptions!D8),IF(YEAR(Assumptions!D32)+1=C64,(MONTH(Assumptions!D32)-MONTH(C62))+1,""),"")))),IF(YEAR(Assumptions!D32)+1=C64,(MONTH(Assumptions!D32)-MONTH(C62))+1,"")),"") | D66: =IF(C66="",IF(YEAR(Assumptions!D32)=D64,IF(MONTH(Assumptions!D8)=12,MONTH(Assumptions!D32),IF(MONTH(Assumptions!D32)<MONTH(Assumptions!D8),12-((MONTH(Assumptions!D8)-MONTH(Assumptions!D32))),IF(MONTH(Assumptions!D32)=MONTH(Assumptions!D8),1,IF(MONTH(Assumptions!D32)>MONTH(Assumptions!D8),IF(YEAR(Assumptions!D32)+1=D64,(MONTH(Assumptions!D32)-MONTH(D62))+1,""),"")))),IF(YEAR(Assumptions!D32)+1=D64,(MONTH(Assumptions!D32)-MONTH(D62))+1,"")),"") | E66: =IF(D66="",IF(YEAR(Assumptions!D32)=E64,IF(MONTH(Assumptions!D8)=12,MONTH(Assumptions!D32),IF(MONTH(Assumptions!D32)<MONTH(Assumptions!D8),12-((MONTH(Assumptions!D8)-MONTH(Assumptions!D32))),IF(MONTH(Assumptions!D32)=MONTH(Assumptions!D8),1,IF(MONTH(Assumptions!D32)>MONTH(Assumptions!D8),IF(YEAR(Assumptions!D32)+1=E64,(MONTH(Assumptions!D32)-MONTH(E62))+1,""),"")))),IF(YEAR(Assumptions!D32)+1=E64,(MONTH(Assumptions!D32)-MONTH(E62))+1,"")),"") | F66: =IF(E66="",IF(YEAR(Assumptions!D32)=F64,IF(MONTH(Assumptions!D8)=12,MONTH(Assumptions!D32),IF(MONTH(Assumptions!D32)<MONTH(Assumptions!D8),12-((MONTH(Assumptions!D8)-MONTH(Assumptions!D32))),IF(MONTH(Assumptions!D32)=MONTH(Assumptions!D8),1,IF(MONTH(Assumptions!D32)>MONTH(Assumptions!D8),IF(YEAR(Assumptions!D32)+1=F64,(MONTH(Assumptions!D32)-MONTH(F62))+1,""),"")))),IF(YEAR(Assumptions!D32)+1=F64,(MONTH(Assumptions!D32)-MONTH(F62))+1,"")),"") | G66: =IF(F66="",IF(YEAR(Assumptions!D32)=G64,IF(MONTH(Assumptions!D8)=12,MONTH(Assumptions!D32),IF(MONTH(Assumptions!D32)<MONTH(Assumptions!D8),12-((MONTH(Assumptions!D8)-MONTH(Assumptions!D32))),IF(MONTH(Assumptions!D32)=MONTH(Assumptions!D8),1,IF(MONTH(Assumptions!D32)>MONTH(Assumptions!D8),IF(YEAR(Assumptions!D32)+1=G64,(MONTH(Assumptions!D32)-MONTH(G62))+1,""),"")))),IF(YEAR(Assumptions!D32)+1=G64,(MONTH(Assumptions!D32)-MONTH(G62))+1,"")),"") -> 1 | H66: =IF(G66="",IF(YEAR(Assumptions!D32)=H64,IF(MONTH(Assumptions!D8)=12,MONTH(Assumptions!D32),IF(MONTH(Assumptions!D32)<MONTH(Assumptions!D8),12-((MONTH(Assumptions!D8)-MONTH(Assumptions!D32))),IF(MONTH(Assumptions!D32)=MONTH(Assumptions!D8),1,IF(MONTH(Assumptions!D32)>MONTH(Assumptions!D8),IF(YEAR(Assumptions!D32)+1=H64,(MONTH(Assumptions!D32)-MONTH(H62))+1,""),"")))),IF(YEAR(Assumptions!D32)+1=H64,(MONTH(Assumptions!D32)-MONTH(H62))+1,"")),"") | I66: =IF(H66="",IF(YEAR(Assumptions!D32)=I64,IF(MONTH(Assumptions!D8)=12,MONTH(Assumptions!D32),IF(MONTH(Assumptions!D32)<MONTH(Assumptions!D8),12-((MONTH(Assumptions!D8)-MONTH(Assumptions!D32))),IF(MONTH(Assumptions!D32)=MONTH(Assumptions!D8),1,IF(MONTH(Assumptions!D32)>MONTH(Assumptions!D8),IF(YEAR(Assumptions!D32)+1=I64,(MONTH(Assumptions!D32)-MONTH(I62))+1,""),"")))),IF(YEAR(Assumptions!D32)+1=I64,(MONTH(Assumptions!D32)-MONTH(I62))+1,"")),"") | J66: =IF(I66="",IF(YEAR(Assumptions!D32)=J64,IF(MONTH(Assumptions!D8)=12,MONTH(Assumptions!D32),IF(MONTH(Assumptions!D32)<MONTH(Assumptions!D8),12-((MONTH(Assumptions!D8)-MONTH(Assumptions!D32))),IF(MONTH(Assumptions!D32)=MONTH(Assumptions!D8),1,IF(MONTH(Assumptions!D32)>MONTH(Assumptions!D8),IF(YEAR(Assumptions!D32)+1=J64,(MONTH(Assumptions!D32)-MONTH(J62))+1,""),"")))),IF(YEAR(Assumptions!D32)+1=J64,(MONTH(Assumptions!D32)-MONTH(J62))+1,"")),"") | K66: =IF(J66="",IF(YEAR(Assumptions!D32)=K64,IF(MONTH(Assumptions!D8)=12,MONTH(Assumptions!D32),IF(MONTH(Assumptions!D32)<MONTH(Assumptions!D8),12-((MONTH(Assumptions!D8)-MONTH(Assumptions!D32))),IF(MONTH(Assumptions!D32)=MONTH(Assumptions!D8),1,IF(MONTH(Assumptions!D32)>MONTH(Assumptions!D8),IF(YEAR(Assumptions!D32)+1=K64,(MONTH(Assumptions!D32)-MONTH(K62))+1,""),"")))),IF(YEAR(Assumptions!D32)+1=K64,(MONTH(Assumptions!D32)-MONTH(K62))+1,"")),"") | L66: =IF(K66="",IF(YEAR(Assumptions!D32)=L64,IF(MONTH(Assumptions!D8)=12,MONTH(Assumptions!D32),IF(MONTH(Assumptions!D32)<MONTH(Assumptions!D8),12-((MONTH(Assumptions!D8)-MONTH(Assumptions!D32))),IF(MONTH(Assumptions!D32)=MONTH(Assumptions!D8),1,IF(MONTH(Assumptions!D32)>MONTH(Assumptions!D8),IF(YEAR(Assumptions!D32)+1=L64,(MONTH(Assumptions!D32)-MONTH(L62))+1,""),"")))),IF(YEAR(Assumptions!D32)+1=L64,(MONTH(Assumptions!D32)-MONTH(L62))+1,"")),"") | M66: =IF(L66="",IF(YEAR(Assumptions!D32)=M64,IF(MONTH(Assumptions!D8)=12,MONTH(Assumptions!D32),IF(MONTH(Assumptions!D32)<MONTH(Assumptions!D8),12-((MONTH(Assumptions!D8)-MONTH(Assumptions!D32))),IF(MONTH(Assumptions!D32)=MONTH(Assumptions!D8),1,IF(MONTH(Assumptions!D32)>MONTH(Assumptions!D8),IF(YEAR(Assumptions!D32)+1=M64,(MONTH(Assumptions!D32)-MONTH(M62))+1,""),"")))),IF(YEAR(Assumptions!D32)+1=M64,(MONTH(Assumptions!D32)-MONTH(M62))+1,"")),"") | N66: =IF(M66="",IF(YEAR(Assumptions!D32)=N64,IF(MONTH(Assumptions!D8)=12,MONTH(Assumptions!D32),IF(MONTH(Assumptions!D32)<MONTH(Assumptions!D8),12-((MONTH(Assumptions!D8)-MONTH(Assumptions!D32))),IF(MONTH(Assumptions!D32)=MONTH(Assumptions!D8),1,IF(MONTH(Assumptions!D32)>MONTH(Assumptions!D8),IF(YEAR(Assumptions!D32)+1=N64,(MONTH(Assumptions!D32)-MONTH(N62))+1,""),"")))),IF(YEAR(Assumptions!D32)+1=N64,(MONTH(Assumptions!D32)-MONTH(N62))+1,"")),"") | O66: =IF(N66="",IF(YEAR(Assumptions!D32)=O64,IF(MONTH(Assumptions!D8)=12,MONTH(Assumptions!D32),IF(MONTH(Assumptions!D32)<MONTH(Assumptions!D8),12-((MONTH(Assumptions!D8)-MONTH(Assumptions!D32))),IF(MONTH(Assumptions!D32)=MONTH(Assumptions!D8),1,IF(MONTH(Assumptions!D32)>MONTH(Assumptions!D8),IF(YEAR(Assumptions!D32)+1=O64,(MONTH(Assumptions!D32)-MONTH(O62))+1,""),"")))),IF(YEAR(Assumptions!D32)+1=O64,(MONTH(Assumptions!D32)-MONTH(O62))+1,"")),"") | P66: =IF(O66="",IF(YEAR(Assumptions!D32)=P64,IF(MONTH(Assumptions!D8)=12,MONTH(Assumptions!D32),IF(MONTH(Assumptions!D32)<MONTH(Assumptions!D8),12-((MONTH(Assumptions!D8)-MONTH(Assumptions!D32))),IF(MONTH(Assumptions!D32)=MONTH(Assumptions!D8),1,IF(MONTH(Assumptions!D32)>MONTH(Assumptions!D8),IF(YEAR(Assumptions!D32)+1=P64,(MONTH(Assumptions!D32)-MONTH(P62))+1,""),"")))),IF(YEAR(Assumptions!D32)+1=P64,(MONTH(Assumptions!D32)-MONTH(P62))+1,"")),"")
A67: SA Fee | B67: =IF(YEAR(Assumptions!D22)=B64,IF(MONTH(Assumptions!D8)=12,1,IF(MONTH(Assumptions!D22)<MONTH(B62),1,"")),IF(A67="",IF(B64=YEAR(Assumptions!D22)+1,1,""),"")) | C67: =IF(YEAR(Assumptions!D22)=C64,IF(MONTH(Assumptions!D8)=12,1,IF(MONTH(Assumptions!D22)<MONTH(C62),1,"")),IF(B67="",IF(C64=YEAR(Assumptions!D22)+1,1,""),"")) -> 1 | D67: =IF(YEAR(Assumptions!D22)=D64,IF(MONTH(Assumptions!D8)=12,1,IF(MONTH(Assumptions!D22)<MONTH(D62),1,"")),IF(C67="",IF(D64=YEAR(Assumptions!D22)+1,1,""),"")) | E67: =IF(YEAR(Assumptions!D22)=E64,IF(MONTH(Assumptions!D8)=12,1,IF(MONTH(Assumptions!D22)<MONTH(E62),1,"")),IF(D67="",IF(E64=YEAR(Assumptions!D22)+1,1,""),"")) | F67: =IF(YEAR(Assumptions!D22)=F64,IF(MONTH(Assumptions!D8)=12,1,IF(MONTH(Assumptions!D22)<MONTH(F62),1,"")),IF(E67="",IF(F64=YEAR(Assumptions!D22)+1,1,""),"")) | G67: =IF(YEAR(Assumptions!D22)=G64,IF(MONTH(Assumptions!D8)=12,1,IF(MONTH(Assumptions!D22)<MONTH(G62),1,"")),IF(F67="",IF(G64=YEAR(Assumptions!D22)+1,1,""),"")) | H67: =IF(YEAR(Assumptions!D22)=H64,IF(MONTH(Assumptions!D8)=12,1,IF(MONTH(Assumptions!D22)<MONTH(H62),1,"")),IF(G67="",IF(H64=YEAR(Assumptions!D22)+1,1,""),"")) | I67: =IF(YEAR(Assumptions!D22)=I64,IF(MONTH(Assumptions!D8)=12,1,IF(MONTH(Assumptions!D22)<MONTH(I62),1,"")),IF(H67="",IF(I64=YEAR(Assumptions!D22)+1,1,""),"")) | J67: =IF(YEAR(Assumptions!D22)=J64,IF(MONTH(Assumptions!D8)=12,1,IF(MONTH(Assumptions!D22)<MONTH(J62),1,"")),IF(I67="",IF(J64=YEAR(Assumptions!D22)+1,1,""),"")) | K67: =IF(YEAR(Assumptions!D22)=K64,IF(MONTH(Assumptions!D8)=12,1,IF(MONTH(Assumptions!D22)<MONTH(K62),1,"")),IF(J67="",IF(K64=YEAR(Assumptions!D22)+1,1,""),"")) | L67: =IF(YEAR(Assumptions!D22)=L64,IF(MONTH(Assumptions!D8)=12,1,IF(MONTH(Assumptions!D22)<MONTH(L62),1,"")),IF(K67="",IF(L64=YEAR(Assumptions!D22)+1,1,""),"")) | M67: =IF(YEAR(Assumptions!D22)=M64,IF(MONTH(Assumptions!D8)=12,1,IF(MONTH(Assumptions!D22)<MONTH(M62),1,"")),IF(L67="",IF(M64=YEAR(Assumptions!D22)+1,1,""),"")) | N67: =IF(YEAR(Assumptions!D22)=N64,IF(MONTH(Assumptions!D8)=12,1,IF(MONTH(Assumptions!D22)<MONTH(N62),1,"")),IF(M67="",IF(N64=YEAR(Assumptions!D22)+1,1,""),"")) | O67: =IF(YEAR(Assumptions!D22)=O64,IF(MONTH(Assumptions!D8)=12,1,IF(MONTH(Assumptions!D22)<MONTH(O62),1,"")),IF(N67="",IF(O64=YEAR(Assumptions!D22)+1,1,""),"")) | P67: =IF(YEAR(Assumptions!D22)=P64,IF(MONTH(Assumptions!D8)=12,1,IF(MONTH(Assumptions!D22)<MONTH(P62),1,"")),IF(O67="",IF(P64=YEAR(Assumptions!D22)+1,1,""),""))
A68: Loan Proceed | B68: =IF(YEAR(Assumptions!D32)=B64,IF(MONTH(Assumptions!D8)=12,1,IF(MONTH(Assumptions!D32)<MONTH(B62),1,"")),IF(A68="",IF(B64=YEAR(Assumptions!D32)+1,1,""),"")) | C68: =IF(YEAR(Assumptions!D32)=C64,IF(MONTH(Assumptions!D8)=12,1,IF(MONTH(Assumptions!D32)<MONTH(C62),1,"")),IF(B68="",IF(C64=YEAR(Assumptions!D32)+1,1,""),"")) | D68: =IF(YEAR(Assumptions!D32)=D64,IF(MONTH(Assumptions!D8)=12,1,IF(MONTH(Assumptions!D32)<MONTH(D62),1,"")),IF(C68="",IF(D64=YEAR(Assumptions!D32)+1,1,""),"")) | E68: =IF(YEAR(Assumptions!D32)=E64,IF(MONTH(Assumptions!D8)=12,1,IF(MONTH(Assumptions!D32)<MONTH(E62),1,"")),IF(D68="",IF(E64=YEAR(Assumptions!D32)+1,1,""),"")) | F68: =IF(YEAR(Assumptions!D32)=F64,IF(MONTH(Assumptions!D8)=12,1,IF(MONTH(Assumptions!D32)<MONTH(F62),1,"")),IF(E68="",IF(F64=YEAR(Assumptions!D32)+1,1,""),"")) | G68: =IF(YEAR(Assumptions!D32)=G64,IF(MONTH(Assumptions!D8)=12,1,IF(MONTH(Assumptions!D32)<MONTH(G62),1,"")),IF(F68="",IF(G64=YEAR(Assumptions!D32)+1,1,""),"")) -> 1 | H68: =IF(YEAR(Assumptions!D32)=H64,IF(MONTH(Assumptions!D8)=12,1,IF(MONTH(Assumptions!D32)<MONTH(H62),1,"")),IF(G68="",IF(H64=YEAR(Assumptions!D32)+1,1,""),"")) | I68: =IF(YEAR(Assumptions!D32)=I64,IF(MONTH(Assumptions!D8)=12,1,IF(MONTH(Assumptions!D32)<MONTH(I62),1,"")),IF(H68="",IF(I64=YEAR(Assumptions!D32)+1,1,""),"")) | J68: =IF(YEAR(Assumptions!D32)=J64,IF(MONTH(Assumptions!D8)=12,1,IF(MONTH(Assumptions!D32)<MONTH(J62),1,"")),IF(I68="",IF(J64=YEAR(Assumptions!D32)+1,1,""),"")) | K68: =IF(YEAR(Assumptions!D32)=K64,IF(MONTH(Assumptions!D8)=12,1,IF(MONTH(Assumptions!D32)<MONTH(K62),1,"")),IF(J68="",IF(K64=YEAR(Assumptions!D32)+1,1,""),"")) | L68: =IF(YEAR(Assumptions!D32)=L64,IF(MONTH(Assumptions!D8)=12,1,IF(MONTH(Assumptions!D32)<MONTH(L62),1,"")),IF(K68="",IF(L64=YEAR(Assumptions!D32)+1,1,""),"")) | M68: =IF(YEAR(Assumptions!D32)=M64,IF(MONTH(Assumptions!D8)=12,1,IF(MONTH(Assumptions!D32)<MONTH(M62),1,"")),IF(L68="",IF(M64=YEAR(Assumptions!D32)+1,1,""),"")) | N68: =IF(YEAR(Assumptions!D32)=N64,IF(MONTH(Assumptions!D8)=12,1,IF(MONTH(Assumptions!D32)<MONTH(N62),1,"")),IF(M68="",IF(N64=YEAR(Assumptions!D32)+1,1,""),"")) | O68: =IF(YEAR(Assumptions!D32)=O64,IF(MONTH(Assumptions!D8)=12,1,IF(MONTH(Assumptions!D32)<MONTH(O62),1,"")),IF(N68="",IF(O64=YEAR(Assumptions!D32)+1,1,""),"")) | P68: =IF(YEAR(Assumptions!D32)=P64,IF(MONTH(Assumptions!D8)=12,1,IF(MONTH(Assumptions!D32)<MONTH(P62),1,"")),IF(O68="",IF(P64=YEAR(Assumptions!D32)+1,1,""),""))
F71: Assessments for Option 4
B73: =DATE(C76+1,B76,26) -> 45286
B76: =MONTH(Assumptions!E23)-MONTH(Assumptions!D8) -> 0 | C76: =YEAR(Assumptions!E23) -> 2023 | D76: =MONTH(Assumptions!E23) -> 12 | E76: =DAY(Assumptions!E23) -> 30 | G76: =IF(B87="",1,B87) -> 0
B80: =Assumptions!E24*12 -> 120
A82: Loan Clac | B82: =IF((MONTH(B85)-MONTH(Assumptions!$E$32))+1=12,0,(MONTH(B85)-MONTH(Assumptions!$E$32))+1) -> 0 | C82: =IF((MONTH(C85)-MONTH(Assumptions!$E$32))+1=12,0,(MONTH(C85)-MONTH(Assumptions!$E$32))+1) -> 0 | D82: =IF((MONTH(D85)-MONTH(Assumptions!$E$32))+1=12,0,(MONTH(D85)-MONTH(Assumptions!$E$32))+1) -> 0 | E82: =IF((MONTH(E85)-MONTH(Assumptions!$E$32))+1=12,0,(MONTH(E85)-MONTH(Assumptions!$E$32))+1) -> 0 | F82: =IF((MONTH(F85)-MONTH(Assumptions!$E$32))+1=12,0,(MONTH(F85)-MONTH(Assumptions!$E$32))+1) -> 0 | G82: =IF((MONTH(G85)-MONTH(Assumptions!$E$32))+1=12,0,(MONTH(G85)-MONTH(Assumptions!$E$32))+1) -> 0 | H82: =IF((MONTH(H85)-MONTH(Assumptions!$E$32))+1=12,0,(MONTH(H85)-MONTH(Assumptions!$E$32))+1) -> 0 | I82: =IF((MONTH(I85)-MONTH(Assumptions!$E$32))+1=12,0,(MONTH(I85)-MONTH(Assumptions!$E$32))+1) -> 0 | ... P82: =IF((MONTH(P85)-MONTH(Assumptions!$E$32))+1=12,0,(MONTH(P85)-MONTH(Assumptions!$E$32))+1) -> 0
A83: SA Calc | B83: =IF((MONTH(B85)-MONTH(Assumptions!$F$22))+1=12,0,(MONTH(B85)-MONTH(Assumptions!$F$22))+1) -> 0 | C83: =IF((MONTH(C85)-MONTH(Assumptions!$F$22))+1=12,0,(MONTH(C85)-MONTH(Assumptions!$F$22))+1) -> 0 | D83: =IF((MONTH(D85)-MONTH(Assumptions!$F$22))+1=12,0,(MONTH(D85)-MONTH(Assumptions!$F$22))+1) -> 0 | E83: =IF((MONTH(E85)-MONTH(Assumptions!$F$22))+1=12,0,(MONTH(E85)-MONTH(Assumptions!$F$22))+1) -> 0 | F83: =IF((MONTH(F85)-MONTH(Assumptions!$F$22))+1=12,0,(MONTH(F85)-MONTH(Assumptions!$F$22))+1) -> 0 | G83: =IF((MONTH(G85)-MONTH(Assumptions!$F$22))+1=12,0,(MONTH(G85)-MONTH(Assumptions!$F$22))+1) -> 0 | H83: =IF((MONTH(H85)-MONTH(Assumptions!$F$22))+1=12,0,(MONTH(H85)-MONTH(Assumptions!$F$22))+1) -> 0 | I83: =IF((MONTH(I85)-MONTH(Assumptions!$F$22))+1=12,0,(MONTH(I85)-MONTH(Assumptions!$F$22))+1) -> 0 | ... P83: =IF((MONTH(P85)-MONTH(Assumptions!$F$22))+1=12,0,(MONTH(P85)-MONTH(Assumptions!$F$22))+1) -> 0
A84: Beg | B84: =DATE(B86,IF(MONTH(Assumptions!$D$8)=12,1,MONTH(Assumptions!$D$8)+1),1) -> 41275 | C84: =DATE(C86,IF(MONTH(Assumptions!$D$8)=12,1,MONTH(Assumptions!$D$8)+1),1) -> 41640 | D84: =DATE(D86,IF(MONTH(Assumptions!$D$8)=12,1,MONTH(Assumptions!$D$8)+1),1) -> 42005 | E84: =DATE(E86,IF(MONTH(Assumptions!$D$8)=12,1,MONTH(Assumptions!$D$8)+1),1) -> 42370 | F84: =DATE(F86,IF(MONTH(Assumptions!$D$8)=12,1,MONTH(Assumptions!$D$8)+1),1) -> 42736 | G84: =DATE(G86,IF(MONTH(Assumptions!$D$8)=12,1,MONTH(Assumptions!$D$8)+1),1) -> 43101 | H84: =DATE(H86,IF(MONTH(Assumptions!$D$8)=12,1,MONTH(Assumptions!$D$8)+1),1) -> 43466 | I84: =DATE(I86,IF(MONTH(Assumptions!$D$8)=12,1,MONTH(Assumptions!$D$8)+1),1) -> 43831 | ... P84: =DATE(P86,IF(MONTH(Assumptions!$D$8)=12,1,MONTH(Assumptions!$D$8)+1),1) -> 46388
A85: End | B85: =DATE(IF(MONTH(Assumptions!$D$8)=12,B86,B86+1),MONTH(Assumptions!$D$8),DAY(Assumptions!$D$8)) -> 41639 | C85: =DATE(IF(MONTH(Assumptions!$D$8)=12,C86,C86+1),MONTH(Assumptions!$D$8),DAY(Assumptions!$D$8)) -> 42004 | D85: =DATE(IF(MONTH(Assumptions!$D$8)=12,D86,D86+1),MONTH(Assumptions!$D$8),DAY(Assumptions!$D$8)) -> 42369 | E85: =DATE(IF(MONTH(Assumptions!$D$8)=12,E86,E86+1),MONTH(Assumptions!$D$8),DAY(Assumptions!$D$8)) -> 42735 | F85: =DATE(IF(MONTH(Assumptions!$D$8)=12,F86,F86+1),MONTH(Assumptions!$D$8),DAY(Assumptions!$D$8)) -> 43100 | G85: =DATE(IF(MONTH(Assumptions!$D$8)=12,G86,G86+1),MONTH(Assumptions!$D$8),DAY(Assumptions!$D$8)) -> 43465 | H85: =DATE(IF(MONTH(Assumptions!$D$8)=12,H86,H86+1),MONTH(Assumptions!$D$8),DAY(Assumptions!$D$8)) -> 43830 | I85: =DATE(IF(MONTH(Assumptions!$D$8)=12,I86,I86+1),MONTH(Assumptions!$D$8),DAY(Assumptions!$D$8)) -> 44196 | ... P85: =DATE(IF(MONTH(Assumptions!$D$8)=12,P86,P86+1),MONTH(Assumptions!$D$8),DAY(Assumptions!$D$8)) -> 46752
B86: =Assumptions!$D$7 -> 2013 | C86: =+B86+1 -> 2014 | D86: =+C86+1 -> 2015 | E86: =+D86+1 -> 2016 | F86: =+E86+1 -> 2017 | G86: =+F86+1 -> 2018 | H86: =+G86+1 -> 2019 | I86: =+H86+1 -> 2020 | J86: =+I86+1 -> 2021 | ... P86: =+O86+1 -> 2027
A87: SA Month | B87: =IF(YEAR(Assumptions!$E$22)=B86,IF(MONTH(Assumptions!$D$8)=12,12-MONTH(Assumptions!$E$22)+1,IF(MONTH(Assumptions!$E$22)<MONTH(Assumptions!$D$8),(MONTH(Assumptions!$D$8)-MONTH(Assumptions!$E$22))+1,IF(MONTH(Assumptions!$E$22)=MONTH(Assumptions!$D$8),1,""))),IF(AND(A87="",YEAR(Assumptions!$E$22)+1=B86),((MONTH(B85)+12)-MONTH(Assumptions!$E$22))+1,IF(YEAR($B$73)=B86,$B$80-SUM(A$87:$A87),IF(B86<YEAR(Assumptions!$E$22),0,IF(B86<YEAR($B$73),12,IF(B86>YEAR($B$73),0)))))) -> 0 | C87: =IF(YEAR(Assumptions!$E$22)=C86,IF(MONTH(Assumptions!$D$8)=12,12-MONTH(Assumptions!$E$22)+1,IF(MONTH(Assumptions!$E$22)<MONTH(Assumptions!$D$8),(MONTH(Assumptions!$D$8)-MONTH(Assumptions!$E$22))+1,IF(MONTH(Assumptions!$E$22)=MONTH(Assumptions!$D$8),1,""))),IF(AND(B87="",YEAR(Assumptions!$E$22)+1=C86),((MONTH(C85)+12)-MONTH(Assumptions!$E$22))+1,IF(YEAR($B$73)=C86,$B$80-SUM(B$87:$B87),IF(C86<YEAR(Assumptions!$E$22),"",IF(C86<YEAR($B$73),12,IF(C86>YEAR($B$73),"")))))) -> 12 | D87: =IF(YEAR(Assumptions!$E$22)=D86,IF(MONTH(Assumptions!$D$8)=12,12-MONTH(Assumptions!$E$22)+1,IF(MONTH(Assumptions!$E$22)<MONTH(Assumptions!$D$8),(MONTH(Assumptions!$D$8)-MONTH(Assumptions!$E$22))+1,IF(MONTH(Assumptions!$E$22)=MONTH(Assumptions!$D$8),1,""))),IF(AND(C87="",YEAR(Assumptions!$E$22)+1=D86),((MONTH(D85)+12)-MONTH(Assumptions!$E$22))+1,IF(YEAR($B$73)=D86,$B$80-SUM($B$87:C87),IF(D86<YEAR(Assumptions!$E$22),"",IF(D86<YEAR($B$73),12,IF(D86>YEAR($B$73),"")))))) -> 12 | E87: =IF(YEAR(Assumptions!$E$22)=E86,IF(MONTH(Assumptions!$D$8)=12,12-MONTH(Assumptions!$E$22)+1,IF(MONTH(Assumptions!$E$22)<MONTH(Assumptions!$D$8),(MONTH(Assumptions!$D$8)-MONTH(Assumptions!$E$22))+1,IF(MONTH(Assumptions!$E$22)=MONTH(Assumptions!$D$8),1,""))),IF(AND(D87="",YEAR(Assumptions!$E$22)+1=E86),((MONTH(E85)+12)-MONTH(Assumptions!$E$22))+1,IF(YEAR($B$73)=E86,$B$80-SUM($B$87:D87),IF(E86<YEAR(Assumptions!$E$22),"",IF(E86<YEAR($B$73),12,IF(E86>YEAR($B$73),"")))))) -> 12 | F87: =IF(YEAR(Assumptions!$E$22)=F86,IF(MONTH(Assumptions!$D$8)=12,12-MONTH(Assumptions!$E$22)+1,IF(MONTH(Assumptions!$E$22)<MONTH(Assumptions!$D$8),(MONTH(Assumptions!$D$8)-MONTH(Assumptions!$E$22))+1,IF(MONTH(Assumptions!$E$22)=MONTH(Assumptions!$D$8),1,""))),IF(AND(E87="",YEAR(Assumptions!$E$22)+1=F86),((MONTH(F85)+12)-MONTH(Assumptions!$E$22))+1,IF(YEAR($B$73)=F86,$B$80-SUM($B$87:E87),IF(F86<YEAR(Assumptions!$E$22),"",IF(F86<YEAR($B$73),12,IF(F86>YEAR($B$73),"")))))) -> 12 | G87: =IF(YEAR(Assumptions!$E$22)=G86,IF(MONTH(Assumptions!$D$8)=12,12-MONTH(Assumptions!$E$22)+1,IF(MONTH(Assumptions!$E$22)<MONTH(Assumptions!$D$8),(MONTH(Assumptions!$D$8)-MONTH(Assumptions!$E$22))+1,IF(MONTH(Assumptions!$E$22)=MONTH(Assumptions!$D$8),1,""))),IF(AND(F87="",YEAR(Assumptions!$E$22)+1=G86),((MONTH(G85)+12)-MONTH(Assumptions!$E$22))+1,IF(YEAR($B$73)=G86,$B$80-SUM($B$87:F87),IF(G86<YEAR(Assumptions!$E$22),"",IF(G86<YEAR($B$73),12,IF(G86>YEAR($B$73),"")))))) -> 12 | H87: =IF(YEAR(Assumptions!$E$22)=H86,IF(MONTH(Assumptions!$D$8)=12,12-MONTH(Assumptions!$E$22)+1,IF(MONTH(Assumptions!$E$22)<MONTH(Assumptions!$D$8),(MONTH(Assumptions!$D$8)-MONTH(Assumptions!$E$22))+1,IF(MONTH(Assumptions!$E$22)=MONTH(Assumptions!$D$8),1,""))),IF(AND(G87="",YEAR(Assumptions!$E$22)+1=H86),((MONTH(H85)+12)-MONTH(Assumptions!$E$22))+1,IF(YEAR($B$73)=H86,$B$80-SUM($B$87:G87),IF(H86<YEAR(Assumptions!$E$22),"",IF(H86<YEAR($B$73),12,IF(H86>YEAR($B$73),"")))))) -> 12 | I87: =IF(YEAR(Assumptions!$E$22)=I86,IF(MONTH(Assumptions!$D$8)=12,12-MONTH(Assumptions!$E$22)+1,IF(MONTH(Assumptions!$E$22)<MONTH(Assumptions!$D$8),(MONTH(Assumptions!$D$8)-MONTH(Assumptions!$E$22))+1,IF(MONTH(Assumptions!$E$22)=MONTH(Assumptions!$D$8),1,""))),IF(AND(H87="",YEAR(Assumptions!$E$22)+1=I86),((MONTH(I85)+12)-MONTH(Assumptions!$E$22))+1,IF(YEAR($B$73)=I86,$B$80-SUM($B$87:H87),IF(I86<YEAR(Assumptions!$E$22),"",IF(I86<YEAR($B$73),12,IF(I86>YEAR($B$73),"")))))) -> 12 | J87: =IF(YEAR(Assumptions!$E$22)=J86,IF(MONTH(Assumptions!$D$8)=12,12-MONTH(Assumptions!$E$22)+1,IF(MONTH(Assumptions!$E$22)<MONTH(Assumptions!$D$8),(MONTH(Assumptions!$D$8)-MONTH(Assumptions!$E$22))+1,IF(MONTH(Assumptions!$E$22)=MONTH(Assumptions!$D$8),1,""))),IF(AND(I87="",YEAR(Assumptions!$E$22)+1=J86),((MONTH(J85)+12)-MONTH(Assumptions!$E$22))+1,IF(YEAR($B$73)=J86,$B$80-SUM($B$87:I87),IF(J86<YEAR(Assumptions!$E$22),"",IF(J86<YEAR($B$73),12,IF(J86>YEAR($B$73),"")))))) -> 12 | K87: =IF(YEAR(Assumptions!$E$22)=K86,IF(MONTH(Assumptions!$D$8)=12,12-MONTH(Assumptions!$E$22)+1,IF(MONTH(Assumptions!$E$22)<MONTH(Assumptions!$D$8),(MONTH(Assumptions!$D$8)-MONTH(Assumptions!$E$22))+1,IF(MONTH(Assumptions!$E$22)=MONTH(Assumptions!$D$8),1,""))),IF(AND(J87="",YEAR(Assumptions!$E$22)+1=K86),((MONTH(K85)+12)-MONTH(Assumptions!$E$22))+1,IF(YEAR($B$73)=K86,$B$80-SUM($B$87:J87),IF(K86<YEAR(Assumptions!$E$22),"",IF(K86<YEAR($B$73),12,IF(K86>YEAR($B$73),"")))))) -> 12 | ... P87: =IF(YEAR(Assumptions!$E$22)=P86,IF(MONTH(Assumptions!$D$8)=12,12-MONTH(Assumptions!$E$22)+1,IF(MONTH(Assumptions!$E$22)<MONTH(Assumptions!$D$8),(MONTH(Assumptions!$D$8)-MONTH(Assumptions!$E$22))+1,IF(MONTH(Assumptions!$E$22)=MONTH(Assumptions!$D$8),1,""))),IF(AND(O87="",YEAR(Assumptions!$E$22)+1=P86),((MONTH(P85)+12)-MONTH(Assumptions!$E$22))+1,IF(YEAR($B$73)=P86,$B$80-SUM($B$87:O87),IF(P86<YEAR(Assumptions!$E$22),"",IF(P86<YEAR($B$73),12,IF(P86>YEAR($B$73),""))))))
A88: Loan | B88: =IF(YEAR(Assumptions!$E$32)=B86,IF(MONTH(Assumptions!$D$8)=12,MONTH(Assumptions!$E$32),IF(MONTH(Assumptions!$E$32)<MONTH(Assumptions!$D$8),12-((MONTH(Assumptions!$D$8)-MONTH(Assumptions!$E$32))),IF(MONTH(Assumptions!$E$32)=MONTH(Assumptions!$D$8),1,IF(MONTH(Assumptions!$E$32)>MONTH(Assumptions!$D$8),IF(YEAR(Assumptions!$E$32)+1=B86,(MONTH(Assumptions!$E$32)-MONTH(B84))+1,""),"")))),IF(YEAR(Assumptions!$E$32)+1=B86,(MONTH(Assumptions!$E$32)-MONTH(B84))+1,"")) | C88: =IF(B88="",IF(YEAR(Assumptions!$E$32)=C86,IF(MONTH(Assumptions!$D$8)=12,MONTH(Assumptions!$E$32),IF(MONTH(Assumptions!$E$32)<MONTH(Assumptions!$D$8),12-((MONTH(Assumptions!$D$8)-MONTH(Assumptions!$E$32))),IF(MONTH(Assumptions!$E$32)=MONTH(Assumptions!$D$8),1,IF(MONTH(Assumptions!$E$32)>MONTH(Assumptions!$D$8),IF(YEAR(Assumptions!$E$32)+1=C86,(MONTH(Assumptions!$E$32)-MONTH(C84))+1,""),"")))),IF(YEAR(Assumptions!$E$32)+1=C86,(MONTH(Assumptions!$E$32)-MONTH(C84))+1,"")),"") | D88: =IF(C88="",IF(YEAR(Assumptions!$E$32)=D86,IF(MONTH(Assumptions!$D$8)=12,MONTH(Assumptions!$E$32),IF(MONTH(Assumptions!$E$32)<MONTH(Assumptions!$D$8),12-((MONTH(Assumptions!$D$8)-MONTH(Assumptions!$E$32))),IF(MONTH(Assumptions!$E$32)=MONTH(Assumptions!$D$8),1,IF(MONTH(Assumptions!$E$32)>MONTH(Assumptions!$D$8),IF(YEAR(Assumptions!$E$32)+1=D86,(MONTH(Assumptions!$E$32)-MONTH(D84))+1,""),"")))),IF(YEAR(Assumptions!$E$32)+1=D86,(MONTH(Assumptions!$E$32)-MONTH(D84))+1,"")),"") | E88: =IF(D88="",IF(YEAR(Assumptions!$E$32)=E86,IF(MONTH(Assumptions!$D$8)=12,MONTH(Assumptions!$E$32),IF(MONTH(Assumptions!$E$32)<MONTH(Assumptions!$D$8),12-((MONTH(Assumptions!$D$8)-MONTH(Assumptions!$E$32))),IF(MONTH(Assumptions!$E$32)=MONTH(Assumptions!$D$8),1,IF(MONTH(Assumptions!$E$32)>MONTH(Assumptions!$D$8),IF(YEAR(Assumptions!$E$32)+1=E86,(MONTH(Assumptions!$E$32)-MONTH(E84))+1,""),"")))),IF(YEAR(Assumptions!$E$32)+1=E86,(MONTH(Assumptions!$E$32)-MONTH(E84))+1,"")),"") | F88: =IF(E88="",IF(YEAR(Assumptions!$E$32)=F86,IF(MONTH(Assumptions!$D$8)=12,MONTH(Assumptions!$E$32),IF(MONTH(Assumptions!$E$32)<MONTH(Assumptions!$D$8),12-((MONTH(Assumptions!$D$8)-MONTH(Assumptions!$E$32))),IF(MONTH(Assumptions!$E$32)=MONTH(Assumptions!$D$8),1,IF(MONTH(Assumptions!$E$32)>MONTH(Assumptions!$D$8),IF(YEAR(Assumptions!$E$32)+1=F86,(MONTH(Assumptions!$E$32)-MONTH(F84))+1,""),"")))),IF(YEAR(Assumptions!$E$32)+1=F86,(MONTH(Assumptions!$E$32)-MONTH(F84))+1,"")),"") | G88: =IF(F88="",IF(YEAR(Assumptions!$E$32)=G86,IF(MONTH(Assumptions!$D$8)=12,MONTH(Assumptions!$E$32),IF(MONTH(Assumptions!$E$32)<MONTH(Assumptions!$D$8),12-((MONTH(Assumptions!$D$8)-MONTH(Assumptions!$E$32))),IF(MONTH(Assumptions!$E$32)=MONTH(Assumptions!$D$8),1,IF(MONTH(Assumptions!$E$32)>MONTH(Assumptions!$D$8),IF(YEAR(Assumptions!$E$32)+1=G86,(MONTH(Assumptions!$E$32)-MONTH(G84))+1,""),"")))),IF(YEAR(Assumptions!$E$32)+1=G86,(MONTH(Assumptions!$E$32)-MONTH(G84))+1,"")),"") -> 1 | H88: =IF(G88="",IF(YEAR(Assumptions!$E$32)=H86,IF(MONTH(Assumptions!$D$8)=12,MONTH(Assumptions!$E$32),IF(MONTH(Assumptions!$E$32)<MONTH(Assumptions!$D$8),12-((MONTH(Assumptions!$D$8)-MONTH(Assumptions!$E$32))),IF(MONTH(Assumptions!$E$32)=MONTH(Assumptions!$D$8),1,IF(MONTH(Assumptions!$E$32)>MONTH(Assumptions!$D$8),IF(YEAR(Assumptions!$E$32)+1=H86,(MONTH(Assumptions!$E$32)-MONTH(H84))+1,""),"")))),IF(YEAR(Assumptions!$E$32)+1=H86,(MONTH(Assumptions!$E$32)-MONTH(H84))+1,"")),"") | I88: =IF(H88="",IF(YEAR(Assumptions!$E$32)=I86,IF(MONTH(Assumptions!$D$8)=12,MONTH(Assumptions!$E$32),IF(MONTH(Assumptions!$E$32)<MONTH(Assumptions!$D$8),12-((MONTH(Assumptions!$D$8)-MONTH(Assumptions!$E$32))),IF(MONTH(Assumptions!$E$32)=MONTH(Assumptions!$D$8),1,IF(MONTH(Assumptions!$E$32)>MONTH(Assumptions!$D$8),IF(YEAR(Assumptions!$E$32)+1=I86,(MONTH(Assumptions!$E$32)-MONTH(I84))+1,""),"")))),IF(YEAR(Assumptions!$E$32)+1=I86,(MONTH(Assumptions!$E$32)-MONTH(I84))+1,"")),"") | J88: =IF(I88="",IF(YEAR(Assumptions!$E$32)=J86,IF(MONTH(Assumptions!$D$8)=12,MONTH(Assumptions!$E$32),IF(MONTH(Assumptions!$E$32)<MONTH(Assumptions!$D$8),12-((MONTH(Assumptions!$D$8)-MONTH(Assumptions!$E$32))),IF(MONTH(Assumptions!$E$32)=MONTH(Assumptions!$D$8),1,IF(MONTH(Assumptions!$E$32)>MONTH(Assumptions!$D$8),IF(YEAR(Assumptions!$E$32)+1=J86,(MONTH(Assumptions!$E$32)-MONTH(J84))+1,""),"")))),IF(YEAR(Assumptions!$E$32)+1=J86,(MONTH(Assumptions!$E$32)-MONTH(J84))+1,"")),"") | ... P88: =IF(O88="",IF(YEAR(Assumptions!$E$32)=P86,IF(MONTH(Assumptions!$D$8)=12,MONTH(Assumptions!$E$32),IF(MONTH(Assumptions!$E$32)<MONTH(Assumptions!$D$8),12-((MONTH(Assumptions!$D$8)-MONTH(Assumptions!$E$32))),IF(MONTH(Assumptions!$E$32)=MONTH(Assumptions!$D$8),1,IF(MONTH(Assumptions!$E$32)>MONTH(Assumptions!$D$8),IF(YEAR(Assumptions!$E$32)+1=P86,(MONTH(Assumptions!$E$32)-MONTH(P84))+1,""),"")))),IF(YEAR(Assumptions!$E$32)+1=P86,(MONTH(Assumptions!$E$32)-MONTH(P84))+1,"")),"")
A89: SA Fee | B89: =IF(YEAR(Assumptions!$E$22)=B86,IF(MONTH(Assumptions!$D$8)=12,1,IF(MONTH(Assumptions!$E$22)<MONTH(B84),1,"")),IF(A89="",IF(B86=YEAR(Assumptions!$E$22)+1,1,""),"")) | C89: =IF(YEAR(Assumptions!$E$22)=C86,IF(MONTH(Assumptions!$D$8)=12,1,IF(MONTH(Assumptions!$E$22)<MONTH(C84),1,"")),IF(B89="",IF(C86=YEAR(Assumptions!$E$22)+1,1,""),"")) -> 1 | D89: =IF(YEAR(Assumptions!$E$22)=D86,IF(MONTH(Assumptions!$D$8)=12,1,IF(MONTH(Assumptions!$E$22)<MONTH(D84),1,"")),IF(C89="",IF(D86=YEAR(Assumptions!$E$22)+1,1,""),"")) | E89: =IF(YEAR(Assumptions!$E$22)=E86,IF(MONTH(Assumptions!$D$8)=12,1,IF(MONTH(Assumptions!$E$22)<MONTH(E84),1,"")),IF(D89="",IF(E86=YEAR(Assumptions!$E$22)+1,1,""),"")) | F89: =IF(YEAR(Assumptions!$E$22)=F86,IF(MONTH(Assumptions!$D$8)=12,1,IF(MONTH(Assumptions!$E$22)<MONTH(F84),1,"")),IF(E89="",IF(F86=YEAR(Assumptions!$E$22)+1,1,""),"")) | G89: =IF(YEAR(Assumptions!$E$22)=G86,IF(MONTH(Assumptions!$D$8)=12,1,IF(MONTH(Assumptions!$E$22)<MONTH(G84),1,"")),IF(F89="",IF(G86=YEAR(Assumptions!$E$22)+1,1,""),"")) | H89: =IF(YEAR(Assumptions!$E$22)=H86,IF(MONTH(Assumptions!$D$8)=12,1,IF(MONTH(Assumptions!$E$22)<MONTH(H84),1,"")),IF(G89="",IF(H86=YEAR(Assumptions!$E$22)+1,1,""),"")) | I89: =IF(YEAR(Assumptions!$E$22)=I86,IF(MONTH(Assumptions!$D$8)=12,1,IF(MONTH(Assumptions!$E$22)<MONTH(I84),1,"")),IF(H89="",IF(I86=YEAR(Assumptions!$E$22)+1,1,""),"")) | ... P89: =IF(YEAR(Assumptions!$E$22)=P86,IF(MONTH(Assumptions!$D$8)=12,1,IF(MONTH(Assumptions!$E$22)<MONTH(P84),1,"")),IF(O89="",IF(P86=YEAR(Assumptions!$E$22)+1,1,""),""))
A90: Loan Proceed | B90: =IF(YEAR(Assumptions!$E$32)=B86,IF(MONTH(Assumptions!$D$8)=12,1,IF(MONTH(Assumptions!$E$32)<MONTH(B84),1,"")),IF(A90="",IF(B86=YEAR(Assumptions!$E$32)+1,1,""),"")) | C90: =IF(YEAR(Assumptions!$E$32)=C86,IF(MONTH(Assumptions!$D$8)=12,1,IF(MONTH(Assumptions!$E$32)<MONTH(C84),1,"")),IF(B90="",IF(C86=YEAR(Assumptions!$E$32)+1,1,""),"")) | D90: =IF(YEAR(Assumptions!$E$32)=D86,IF(MONTH(Assumptions!$D$8)=12,1,IF(MONTH(Assumptions!$E$32)<MONTH(D84),1,"")),IF(C90="",IF(D86=YEAR(Assumptions!$E$32)+1,1,""),"")) | E90: =IF(YEAR(Assumptions!$E$32)=E86,IF(MONTH(Assumptions!$D$8)=12,1,IF(MONTH(Assumptions!$E$32)<MONTH(E84),1,"")),IF(D90="",IF(E86=YEAR(Assumptions!$E$32)+1,1,""),"")) | F90: =IF(YEAR(Assumptions!$E$32)=F86,IF(MONTH(Assumptions!$D$8)=12,1,IF(MONTH(Assumptions!$E$32)<MONTH(F84),1,"")),IF(E90="",IF(F86=YEAR(Assumptions!$E$32)+1,1,""),"")) | G90: =IF(YEAR(Assumptions!$E$32)=G86,IF(MONTH(Assumptions!$D$8)=12,1,IF(MONTH(Assumptions!$E$32)<MONTH(G84),1,"")),IF(F90="",IF(G86=YEAR(Assumptions!$E$32)+1,1,""),"")) -> 1 | H90: =IF(YEAR(Assumptions!$E$32)=H86,IF(MONTH(Assumptions!$D$8)=12,1,IF(MONTH(Assumptions!$E$32)<MONTH(H84),1,"")),IF(G90="",IF(H86=YEAR(Assumptions!$E$32)+1,1,""),"")) | I90: =IF(YEAR(Assumptions!$E$32)=I86,IF(MONTH(Assumptions!$D$8)=12,1,IF(MONTH(Assumptions!$E$32)<MONTH(I84),1,"")),IF(H90="",IF(I86=YEAR(Assumptions!$E$32)+1,1,""),"")) | ... P90: =IF(YEAR(Assumptions!$E$32)=P86,IF(MONTH(Assumptions!$D$8)=12,1,IF(MONTH(Assumptions!$E$32)<MONTH(P84),1,"")),IF(O90="",IF(P86=YEAR(Assumptions!$E$32)+1,1,""),""))
F93: Assessments for Option 5
B95: =DATE(C98+1,B98,26) -> 26
B98: =MONTH(Assumptions!F23)-MONTH(Assumptions!$D$8) -> -11 | C98: =YEAR(Assumptions!F23) -> 1900 | D98: =MONTH(Assumptions!F23) -> 1 | E98: =DAY(Assumptions!F23) -> 0 | G98: =IF(B109="",1,B109) -> 0
B102: =Assumptions!F24*12 -> 0
A104: Loan Clac | B104: =IF((MONTH(B107)-MONTH(Assumptions!$E$32))+1=12,0,(MONTH(B107)-MONTH(Assumptions!$E$32))+1) -> 0 | C104: =IF((MONTH(C107)-MONTH(Assumptions!$E$32))+1=12,0,(MONTH(C107)-MONTH(Assumptions!$E$32))+1) -> 0 | D104: =IF((MONTH(D107)-MONTH(Assumptions!$E$32))+1=12,0,(MONTH(D107)-MONTH(Assumptions!$E$32))+1) -> 0 | E104: =IF((MONTH(E107)-MONTH(Assumptions!$E$32))+1=12,0,(MONTH(E107)-MONTH(Assumptions!$E$32))+1) -> 0 | F104: =IF((MONTH(F107)-MONTH(Assumptions!$E$32))+1=12,0,(MONTH(F107)-MONTH(Assumptions!$E$32))+1) -> 0 | G104: =IF((MONTH(G107)-MONTH(Assumptions!$E$32))+1=12,0,(MONTH(G107)-MONTH(Assumptions!$E$32))+1) -> 0 | H104: =IF((MONTH(H107)-MONTH(Assumptions!$E$32))+1=12,0,(MONTH(H107)-MONTH(Assumptions!$E$32))+1) -> 0 | I104: =IF((MONTH(I107)-MONTH(Assumptions!$E$32))+1=12,0,(MONTH(I107)-MONTH(Assumptions!$E$32))+1) -> 0 | ... P104: =IF((MONTH(P107)-MONTH(Assumptions!$E$32))+1=12,0,(MONTH(P107)-MONTH(Assumptions!$E$32))+1) -> 0
A105: SA Calc | B105: =IF((MONTH(B107)-MONTH(Assumptions!$F$22))+1=12,0,(MONTH(B107)-MONTH(Assumptions!$F$22))+1) -> 0 | C105: =IF((MONTH(C107)-MONTH(Assumptions!$F$22))+1=12,0,(MONTH(C107)-MONTH(Assumptions!$F$22))+1) -> 0 | D105: =IF((MONTH(D107)-MONTH(Assumptions!$F$22))+1=12,0,(MONTH(D107)-MONTH(Assumptions!$F$22))+1) -> 0 | E105: =IF((MONTH(E107)-MONTH(Assumptions!$F$22))+1=12,0,(MONTH(E107)-MONTH(Assumptions!$F$22))+1) -> 0 | F105: =IF((MONTH(F107)-MONTH(Assumptions!$F$22))+1=12,0,(MONTH(F107)-MONTH(Assumptions!$F$22))+1) -> 0 | G105: =IF((MONTH(G107)-MONTH(Assumptions!$F$22))+1=12,0,(MONTH(G107)-MONTH(Assumptions!$F$22))+1) -> 0 | H105: =IF((MONTH(H107)-MONTH(Assumptions!$F$22))+1=12,0,(MONTH(H107)-MONTH(Assumptions!$F$22))+1) -> 0 | I105: =IF((MONTH(I107)-MONTH(Assumptions!$F$22))+1=12,0,(MONTH(I107)-MONTH(Assumptions!$F$22))+1) -> 0 | ... P105: =IF((MONTH(P107)-MONTH(Assumptions!$F$22))+1=12,0,(MONTH(P107)-MONTH(Assumptions!$F$22))+1) -> 0
A106: Beg | B106: =DATE(B108,IF(MONTH(Assumptions!$D$8)=12,1,MONTH(Assumptions!$D$8)+1),1) -> 41275 | C106: =DATE(C108,IF(MONTH(Assumptions!$D$8)=12,1,MONTH(Assumptions!$D$8)+1),1) -> 41640 | D106: =DATE(D108,IF(MONTH(Assumptions!$D$8)=12,1,MONTH(Assumptions!$D$8)+1),1) -> 42005 | E106: =DATE(E108,IF(MONTH(Assumptions!$D$8)=12,1,MONTH(Assumptions!$D$8)+1),1) -> 42370 | F106: =DATE(F108,IF(MONTH(Assumptions!$D$8)=12,1,MONTH(Assumptions!$D$8)+1),1) -> 42736 | G106: =DATE(G108,IF(MONTH(Assumptions!$D$8)=12,1,MONTH(Assumptions!$D$8)+1),1) -> 43101 | H106: =DATE(H108,IF(MONTH(Assumptions!$D$8)=12,1,MONTH(Assumptions!$D$8)+1),1) -> 43466 | I106: =DATE(I108,IF(MONTH(Assumptions!$D$8)=12,1,MONTH(Assumptions!$D$8)+1),1) -> 43831 | ... P106: =DATE(P108,IF(MONTH(Assumptions!$D$8)=12,1,MONTH(Assumptions!$D$8)+1),1) -> 46388
A107: End | B107: =DATE(IF(MONTH(Assumptions!$D$8)=12,B108,B108+1),MONTH(Assumptions!$D$8),DAY(Assumptions!$D$8)) -> 41639 | C107: =DATE(IF(MONTH(Assumptions!$D$8)=12,C108,C108+1),MONTH(Assumptions!$D$8),DAY(Assumptions!$D$8)) -> 42004 | D107: =DATE(IF(MONTH(Assumptions!$D$8)=12,D108,D108+1),MONTH(Assumptions!$D$8),DAY(Assumptions!$D$8)) -> 42369 | E107: =DATE(IF(MONTH(Assumptions!$D$8)=12,E108,E108+1),MONTH(Assumptions!$D$8),DAY(Assumptions!$D$8)) -> 42735 | F107: =DATE(IF(MONTH(Assumptions!$D$8)=12,F108,F108+1),MONTH(Assumptions!$D$8),DAY(Assumptions!$D$8)) -> 43100 | G107: =DATE(IF(MONTH(Assumptions!$D$8)=12,G108,G108+1),MONTH(Assumptions!$D$8),DAY(Assumptions!$D$8)) -> 43465 | H107: =DATE(IF(MONTH(Assumptions!$D$8)=12,H108,H108+1),MONTH(Assumptions!$D$8),DAY(Assumptions!$D$8)) -> 43830 | I107: =DATE(IF(MONTH(Assumptions!$D$8)=12,I108,I108+1),MONTH(Assumptions!$D$8),DAY(Assumptions!$D$8)) -> 44196 | ... P107: =DATE(IF(MONTH(Assumptions!$D$8)=12,P108,P108+1),MONTH(Assumptions!$D$8),DAY(Assumptions!$D$8)) -> 46752
B108: =Assumptions!$D$7 -> 2013 | C108: =+B108+1 -> 2014 | D108: =+C108+1 -> 2015 | E108: =+D108+1 -> 2016 | F108: =+E108+1 -> 2017 | G108: =+F108+1 -> 2018 | H108: =+G108+1 -> 2019 | I108: =+H108+1 -> 2020 | J108: =+I108+1 -> 2021 | ... P108: =+O108+1 -> 2027
A109: SA Month | B109: =IF(YEAR(Assumptions!$F$22)=B108,IF(MONTH(Assumptions!$D$8)=12,12-MONTH(Assumptions!$F$22)+1,IF(MONTH(Assumptions!$F$22)<MONTH(Assumptions!$D$8),(MONTH(Assumptions!$D$8)-MONTH(Assumptions!$F$22))+1,IF(MONTH(Assumptions!$F$22)=MONTH(Assumptions!$D$8),1,""))),IF(AND(A109="",YEAR(Assumptions!$F$22)+1=B108),((MONTH(B107)+12)-MONTH(Assumptions!$F$22))+1,IF(YEAR($B$95)=B108,$B$108-SUM(A$109:$A109),IF(B108<YEAR(Assumptions!$F$22),0,IF(B108<YEAR($B$95),12,IF(B108>YEAR($B$95),0)))))) -> 0 | C109: =IF(YEAR(Assumptions!$F$22)=C108,IF(MONTH(Assumptions!$D$8)=12,12-MONTH(Assumptions!$F$22)+1,IF(MONTH(Assumptions!$F$22)<MONTH(Assumptions!$D$8),(MONTH(Assumptions!$D$8)-MONTH(Assumptions!$F$22))+1,IF(MONTH(Assumptions!$F$22)=MONTH(Assumptions!$D$8),1,""))),IF(AND(B109="",YEAR(Assumptions!$F$22)+1=C108),((MONTH(C107)+12)-MONTH(Assumptions!$F$22))+1,IF(YEAR($B$95)=C108,$B$102-SUM(B109:B109),IF(C108<YEAR(Assumptions!$F$22),"",IF(C108<YEAR($B$95),12,IF(C108>YEAR($B$95),"")))))) | D109: =IF(YEAR(Assumptions!$F$22)=D108,IF(MONTH(Assumptions!$D$8)=12,12-MONTH(Assumptions!$F$22)+1,IF(MONTH(Assumptions!$F$22)<MONTH(Assumptions!$D$8),(MONTH(Assumptions!$D$8)-MONTH(Assumptions!$F$22))+1,IF(MONTH(Assumptions!$F$22)=MONTH(Assumptions!$D$8),1,""))),IF(AND(C109="",YEAR(Assumptions!$F$22)+1=D108),((MONTH(D107)+12)-MONTH(Assumptions!$F$22))+1,IF(YEAR($B$95)=D108,$B$102-SUM($B$109:C$109),IF(D108<YEAR(Assumptions!$F$22),"",IF(D108<YEAR($B$95),12,IF(D108>YEAR($B$95),"")))))) | E109: =IF(YEAR(Assumptions!$F$22)=E108,IF(MONTH(Assumptions!$D$8)=12,12-MONTH(Assumptions!$F$22)+1,IF(MONTH(Assumptions!$F$22)<MONTH(Assumptions!$D$8),(MONTH(Assumptions!$D$8)-MONTH(Assumptions!$F$22))+1,IF(MONTH(Assumptions!$F$22)=MONTH(Assumptions!$D$8),1,""))),IF(AND(D109="",YEAR(Assumptions!$F$22)+1=E108),((MONTH(E107)+12)-MONTH(Assumptions!$F$22))+1,IF(YEAR($B$95)=E108,$B$102-SUM($B$109:D$109),IF(E108<YEAR(Assumptions!$F$22),"",IF(E108<YEAR($B$95),12,IF(E108>YEAR($B$95),"")))))) | F109: =IF(YEAR(Assumptions!$F$22)=F108,IF(MONTH(Assumptions!$D$8)=12,12-MONTH(Assumptions!$F$22)+1,IF(MONTH(Assumptions!$F$22)<MONTH(Assumptions!$D$8),(MONTH(Assumptions!$D$8)-MONTH(Assumptions!$F$22))+1,IF(MONTH(Assumptions!$F$22)=MONTH(Assumptions!$D$8),1,""))),IF(AND(E109="",YEAR(Assumptions!$F$22)+1=F108),((MONTH(F107)+12)-MONTH(Assumptions!$F$22))+1,IF(YEAR($B$95)=F108,$B$102-SUM($B$109:E$109),IF(F108<YEAR(Assumptions!$F$22),"",IF(F108<YEAR($B$95),12,IF(F108>YEAR($B$95),"")))))) | G109: =IF(YEAR(Assumptions!$F$22)=G108,IF(MONTH(Assumptions!$D$8)=12,12-MONTH(Assumptions!$F$22)+1,IF(MONTH(Assumptions!$F$22)<MONTH(Assumptions!$D$8),(MONTH(Assumptions!$D$8)-MONTH(Assumptions!$F$22))+1,IF(MONTH(Assumptions!$F$22)=MONTH(Assumptions!$D$8),1,""))),IF(AND(F109="",YEAR(Assumptions!$F$22)+1=G108),((MONTH(G107)+12)-MONTH(Assumptions!$F$22))+1,IF(YEAR($B$95)=G108,$B$102-SUM($B$109:F$109),IF(G108<YEAR(Assumptions!$F$22),"",IF(G108<YEAR($B$95),12,IF(G108>YEAR($B$95),"")))))) | H109: =IF(YEAR(Assumptions!$F$22)=H108,IF(MONTH(Assumptions!$D$8)=12,12-MONTH(Assumptions!$F$22)+1,IF(MONTH(Assumptions!$F$22)<MONTH(Assumptions!$D$8),(MONTH(Assumptions!$D$8)-MONTH(Assumptions!$F$22))+1,IF(MONTH(Assumptions!$F$22)=MONTH(Assumptions!$D$8),1,""))),IF(AND(G109="",YEAR(Assumptions!$F$22)+1=H108),((MONTH(H107)+12)-MONTH(Assumptions!$F$22))+1,IF(YEAR($B$95)=H108,$B$102-SUM($B$109:G$109),IF(H108<YEAR(Assumptions!$F$22),"",IF(H108<YEAR($B$95),12,IF(H108>YEAR($B$95),"")))))) | I109: =IF(YEAR(Assumptions!$F$22)=I108,IF(MONTH(Assumptions!$D$8)=12,12-MONTH(Assumptions!$F$22)+1,IF(MONTH(Assumptions!$F$22)<MONTH(Assumptions!$D$8),(MONTH(Assumptions!$D$8)-MONTH(Assumptions!$F$22))+1,IF(MONTH(Assumptions!$F$22)=MONTH(Assumptions!$D$8),1,""))),IF(AND(H109="",YEAR(Assumptions!$F$22)+1=I108),((MONTH(I107)+12)-MONTH(Assumptions!$F$22))+1,IF(YEAR($B$95)=I108,$B$102-SUM($B$109:H$109),IF(I108<YEAR(Assumptions!$F$22),"",IF(I108<YEAR($B$95),12,IF(I108>YEAR($B$95),"")))))) | J109: =IF(YEAR(Assumptions!$F$22)=J108,IF(MONTH(Assumptions!$D$8)=12,12-MONTH(Assumptions!$F$22)+1,IF(MONTH(Assumptions!$F$22)<MONTH(Assumptions!$D$8),(MONTH(Assumptions!$D$8)-MONTH(Assumptions!$F$22))+1,IF(MONTH(Assumptions!$F$22)=MONTH(Assumptions!$D$8),1,""))),IF(AND(I109="",YEAR(Assumptions!$F$22)+1=J108),((MONTH(J107)+12)-MONTH(Assumptions!$F$22))+1,IF(YEAR($B$95)=J108,$B$102-SUM($B$109:I$109),IF(J108<YEAR(Assumptions!$F$22),"",IF(J108<YEAR($B$95),12,IF(J108>YEAR($B$95),"")))))) | K109: =IF(YEAR(Assumptions!$F$22)=K108,IF(MONTH(Assumptions!$D$8)=12,12-MONTH(Assumptions!$F$22)+1,IF(MONTH(Assumptions!$F$22)<MONTH(Assumptions!$D$8),(MONTH(Assumptions!$D$8)-MONTH(Assumptions!$F$22))+1,IF(MONTH(Assumptions!$F$22)=MONTH(Assumptions!$D$8),1,""))),IF(AND(J109="",YEAR(Assumptions!$F$22)+1=K108),((MONTH(K107)+12)-MONTH(Assumptions!$F$22))+1,IF(YEAR($B$95)=K108,$B$102-SUM($B$109:J$109),IF(K108<YEAR(Assumptions!$F$22),"",IF(K108<YEAR($B$95),12,IF(K108>YEAR($B$95),"")))))) | ... P109: =IF(YEAR(Assumptions!$F$22)=P108,IF(MONTH(Assumptions!$D$8)=12,12-MONTH(Assumptions!$F$22)+1,IF(MONTH(Assumptions!$F$22)<MONTH(Assumptions!$D$8),(MONTH(Assumptions!$D$8)-MONTH(Assumptions!$F$22))+1,IF(MONTH(Assumptions!$F$22)=MONTH(Assumptions!$D$8),1,""))),IF(AND(O109="",YEAR(Assumptions!$F$22)+1=P108),((MONTH(P107)+12)-MONTH(Assumptions!$F$22))+1,IF(YEAR($B$95)=P108,$B$102-SUM($B$109:O$109),IF(P108<YEAR(Assumptions!$F$22),"",IF(P108<YEAR($B$95),12,IF(P108>YEAR($B$95),""))))))
A110: Loan | B110: =IF(YEAR(Assumptions!$F$32)=B108,IF(MONTH(Assumptions!$D$8)=12,MONTH(Assumptions!$F$32),IF(MONTH(Assumptions!$F$32)<MONTH(Assumptions!$D$8),12-((MONTH(Assumptions!$D$8)-MONTH(Assumptions!$F$32))),IF(MONTH(Assumptions!$F$32)=MONTH(Assumptions!$D$8),1,IF(MONTH(Assumptions!$F$32)>MONTH(Assumptions!$D$8),IF(YEAR(Assumptions!$F$32)+1=B108,(MONTH(Assumptions!$F$32)-MONTH(B106))+1,""),"")))),IF(YEAR(Assumptions!$F$32)+1=B108,(MONTH(Assumptions!$F$32)-MONTH(B106))+1,"")) | C110: =IF(B110="",IF(YEAR(Assumptions!$F$32)=C108,IF(MONTH(Assumptions!$D$8)=12,MONTH(Assumptions!$F$32),IF(MONTH(Assumptions!$F$32)<MONTH(Assumptions!$D$8),12-((MONTH(Assumptions!$D$8)-MONTH(Assumptions!$F$32))),IF(MONTH(Assumptions!$F$32)=MONTH(Assumptions!$D$8),1,IF(MONTH(Assumptions!$F$32)>MONTH(Assumptions!$D$8),IF(YEAR(Assumptions!$F$32)+1=C108,(MONTH(Assumptions!$F$32)-MONTH(C106))+1,""),"")))),IF(YEAR(Assumptions!$F$32)+1=C108,(MONTH(Assumptions!$F$32)-MONTH(C106))+1,"")),"") | D110: =IF(C110="",IF(YEAR(Assumptions!$F$32)=D108,IF(MONTH(Assumptions!$D$8)=12,MONTH(Assumptions!$F$32),IF(MONTH(Assumptions!$F$32)<MONTH(Assumptions!$D$8),12-((MONTH(Assumptions!$D$8)-MONTH(Assumptions!$F$32))),IF(MONTH(Assumptions!$F$32)=MONTH(Assumptions!$D$8),1,IF(MONTH(Assumptions!$F$32)>MONTH(Assumptions!$D$8),IF(YEAR(Assumptions!$F$32)+1=D108,(MONTH(Assumptions!$F$32)-MONTH(D106))+1,""),"")))),IF(YEAR(Assumptions!$F$32)+1=D108,(MONTH(Assumptions!$F$32)-MONTH(D106))+1,"")),"") | E110: =IF(D110="",IF(YEAR(Assumptions!$F$32)=E108,IF(MONTH(Assumptions!$D$8)=12,MONTH(Assumptions!$F$32),IF(MONTH(Assumptions!$F$32)<MONTH(Assumptions!$D$8),12-((MONTH(Assumptions!$D$8)-MONTH(Assumptions!$F$32))),IF(MONTH(Assumptions!$F$32)=MONTH(Assumptions!$D$8),1,IF(MONTH(Assumptions!$F$32)>MONTH(Assumptions!$D$8),IF(YEAR(Assumptions!$F$32)+1=E108,(MONTH(Assumptions!$F$32)-MONTH(E106))+1,""),"")))),IF(YEAR(Assumptions!$F$32)+1=E108,(MONTH(Assumptions!$F$32)-MONTH(E106))+1,"")),"") | F110: =IF(E110="",IF(YEAR(Assumptions!$F$32)=F108,IF(MONTH(Assumptions!$D$8)=12,MONTH(Assumptions!$F$32),IF(MONTH(Assumptions!$F$32)<MONTH(Assumptions!$D$8),12-((MONTH(Assumptions!$D$8)-MONTH(Assumptions!$F$32))),IF(MONTH(Assumptions!$F$32)=MONTH(Assumptions!$D$8),1,IF(MONTH(Assumptions!$F$32)>MONTH(Assumptions!$D$8),IF(YEAR(Assumptions!$F$32)+1=F108,(MONTH(Assumptions!$F$32)-MONTH(F106))+1,""),"")))),IF(YEAR(Assumptions!$F$32)+1=F108,(MONTH(Assumptions!$F$32)-MONTH(F106))+1,"")),"") | G110: =IF(F110="",IF(YEAR(Assumptions!$F$32)=G108,IF(MONTH(Assumptions!$D$8)=12,MONTH(Assumptions!$F$32),IF(MONTH(Assumptions!$F$32)<MONTH(Assumptions!$D$8),12-((MONTH(Assumptions!$D$8)-MONTH(Assumptions!$F$32))),IF(MONTH(Assumptions!$F$32)=MONTH(Assumptions!$D$8),1,IF(MONTH(Assumptions!$F$32)>MONTH(Assumptions!$D$8),IF(YEAR(Assumptions!$F$32)+1=G108,(MONTH(Assumptions!$F$32)-MONTH(G106))+1,""),"")))),IF(YEAR(Assumptions!$F$32)+1=G108,(MONTH(Assumptions!$F$32)-MONTH(G106))+1,"")),"") | H110: =IF(G110="",IF(YEAR(Assumptions!$F$32)=H108,IF(MONTH(Assumptions!$D$8)=12,MONTH(Assumptions!$F$32),IF(MONTH(Assumptions!$F$32)<MONTH(Assumptions!$D$8),12-((MONTH(Assumptions!$D$8)-MONTH(Assumptions!$F$32))),IF(MONTH(Assumptions!$F$32)=MONTH(Assumptions!$D$8),1,IF(MONTH(Assumptions!$F$32)>MONTH(Assumptions!$D$8),IF(YEAR(Assumptions!$F$32)+1=H108,(MONTH(Assumptions!$F$32)-MONTH(H106))+1,""),"")))),IF(YEAR(Assumptions!$F$32)+1=H108,(MONTH(Assumptions!$F$32)-MONTH(H106))+1,"")),"") | I110: =IF(H110="",IF(YEAR(Assumptions!$F$32)=I108,IF(MONTH(Assumptions!$D$8)=12,MONTH(Assumptions!$F$32),IF(MONTH(Assumptions!$F$32)<MONTH(Assumptions!$D$8),12-((MONTH(Assumptions!$D$8)-MONTH(Assumptions!$F$32))),IF(MONTH(Assumptions!$F$32)=MONTH(Assumptions!$D$8),1,IF(MONTH(Assumptions!$F$32)>MONTH(Assumptions!$D$8),IF(YEAR(Assumptions!$F$32)+1=I108,(MONTH(Assumptions!$F$32)-MONTH(I106))+1,""),"")))),IF(YEAR(Assumptions!$F$32)+1=I108,(MONTH(Assumptions!$F$32)-MONTH(I106))+1,"")),"") | J110: =IF(I110="",IF(YEAR(Assumptions!$F$32)=J108,IF(MONTH(Assumptions!$D$8)=12,MONTH(Assumptions!$F$32),IF(MONTH(Assumptions!$F$32)<MONTH(Assumptions!$D$8),12-((MONTH(Assumptions!$D$8)-MONTH(Assumptions!$F$32))),IF(MONTH(Assumptions!$F$32)=MONTH(Assumptions!$D$8),1,IF(MONTH(Assumptions!$F$32)>MONTH(Assumptions!$D$8),IF(YEAR(Assumptions!$F$32)+1=J108,(MONTH(Assumptions!$F$32)-MONTH(J106))+1,""),"")))),IF(YEAR(Assumptions!$F$32)+1=J108,(MONTH(Assumptions!$F$32)-MONTH(J106))+1,"")),"") | ... P110: =IF(O110="",IF(YEAR(Assumptions!$F$32)=P108,IF(MONTH(Assumptions!$D$8)=12,MONTH(Assumptions!$F$32),IF(MONTH(Assumptions!$F$32)<MONTH(Assumptions!$D$8),12-((MONTH(Assumptions!$D$8)-MONTH(Assumptions!$F$32))),IF(MONTH(Assumptions!$F$32)=MONTH(Assumptions!$D$8),1,IF(MONTH(Assumptions!$F$32)>MONTH(Assumptions!$D$8),IF(YEAR(Assumptions!$F$32)+1=P108,(MONTH(Assumptions!$F$32)-MONTH(P106))+1,""),"")))),IF(YEAR(Assumptions!$F$32)+1=P108,(MONTH(Assumptions!$F$32)-MONTH(P106))+1,"")),"")
A111: SA Fee | B111: =IF(YEAR(Assumptions!$F$22)=B108,IF(MONTH(Assumptions!$D$8)=12,1,IF(MONTH(Assumptions!$F$22)<MONTH(B106),1,"")),IF(A111="",IF(B108=YEAR(Assumptions!$F$22)+1,1,""),"")) | C111: =IF(YEAR(Assumptions!$F$22)=C108,IF(MONTH(Assumptions!$D$8)=12,1,IF(MONTH(Assumptions!$F$22)<MONTH(C106),1,"")),IF(B111="",IF(C108=YEAR(Assumptions!$F$22)+1,1,""),"")) | D111: =IF(YEAR(Assumptions!$F$22)=D108,IF(MONTH(Assumptions!$D$8)=12,1,IF(MONTH(Assumptions!$F$22)<MONTH(D106),1,"")),IF(C111="",IF(D108=YEAR(Assumptions!$F$22)+1,1,""),"")) | E111: =IF(YEAR(Assumptions!$F$22)=E108,IF(MONTH(Assumptions!$D$8)=12,1,IF(MONTH(Assumptions!$F$22)<MONTH(E106),1,"")),IF(D111="",IF(E108=YEAR(Assumptions!$F$22)+1,1,""),"")) | F111: =IF(YEAR(Assumptions!$F$22)=F108,IF(MONTH(Assumptions!$D$8)=12,1,IF(MONTH(Assumptions!$F$22)<MONTH(F106),1,"")),IF(E111="",IF(F108=YEAR(Assumptions!$F$22)+1,1,""),"")) | G111: =IF(YEAR(Assumptions!$F$22)=G108,IF(MONTH(Assumptions!$D$8)=12,1,IF(MONTH(Assumptions!$F$22)<MONTH(G106),1,"")),IF(F111="",IF(G108=YEAR(Assumptions!$F$22)+1,1,""),"")) | H111: =IF(YEAR(Assumptions!$F$22)=H108,IF(MONTH(Assumptions!$D$8)=12,1,IF(MONTH(Assumptions!$F$22)<MONTH(H106),1,"")),IF(G111="",IF(H108=YEAR(Assumptions!$F$22)+1,1,""),"")) | I111: =IF(YEAR(Assumptions!$F$22)=I108,IF(MONTH(Assumptions!$D$8)=12,1,IF(MONTH(Assumptions!$F$22)<MONTH(I106),1,"")),IF(H111="",IF(I108=YEAR(Assumptions!$F$22)+1,1,""),"")) | ... P111: =IF(YEAR(Assumptions!$F$22)=P108,IF(MONTH(Assumptions!$D$8)=12,1,IF(MONTH(Assumptions!$F$22)<MONTH(P106),1,"")),IF(O111="",IF(P108=YEAR(Assumptions!$F$22)+1,1,""),""))
A112: Loan Proceed | B112: =IF(YEAR(Assumptions!$F$32)=B108,IF(MONTH(Assumptions!$D$8)=12,1,IF(MONTH(Assumptions!$F$32)<MONTH(B106),1,"")),IF(A112="",IF(B108=YEAR(Assumptions!$F$32)+1,1,""),"")) | C112: =IF(YEAR(Assumptions!$F$32)=C108,IF(MONTH(Assumptions!$D$8)=12,1,IF(MONTH(Assumptions!$F$32)<MONTH(C106),1,"")),IF(B112="",IF(C108=YEAR(Assumptions!$F$32)+1,1,""),"")) | D112: =IF(YEAR(Assumptions!$F$32)=D108,IF(MONTH(Assumptions!$D$8)=12,1,IF(MONTH(Assumptions!$F$32)<MONTH(D106),1,"")),IF(C112="",IF(D108=YEAR(Assumptions!$F$32)+1,1,""),"")) | E112: =IF(YEAR(Assumptions!$F$32)=E108,IF(MONTH(Assumptions!$D$8)=12,1,IF(MONTH(Assumptions!$F$32)<MONTH(E106),1,"")),IF(D112="",IF(E108=YEAR(Assumptions!$F$32)+1,1,""),"")) | F112: =IF(YEAR(Assumptions!$F$32)=F108,IF(MONTH(Assumptions!$D$8)=12,1,IF(MONTH(Assumptions!$F$32)<MONTH(F106),1,"")),IF(E112="",IF(F108=YEAR(Assumptions!$F$32)+1,1,""),"")) | G112: =IF(YEAR(Assumptions!$F$32)=G108,IF(MONTH(Assumptions!$D$8)=12,1,IF(MONTH(Assumptions!$F$32)<MONTH(G106),1,"")),IF(F112="",IF(G108=YEAR(Assumptions!$F$32)+1,1,""),"")) | H112: =IF(YEAR(Assumptions!$F$32)=H108,IF(MONTH(Assumptions!$D$8)=12,1,IF(MONTH(Assumptions!$F$32)<MONTH(H106),1,"")),IF(G112="",IF(H108=YEAR(Assumptions!$F$32)+1,1,""),"")) | I112: =IF(YEAR(Assumptions!$F$32)=I108,IF(MONTH(Assumptions!$D$8)=12,1,IF(MONTH(Assumptions!$F$32)<MONTH(I106),1,"")),IF(H112="",IF(I108=YEAR(Assumptions!$F$32)+1,1,""),"")) | ... P112: =IF(YEAR(Assumptions!$F$32)=P108,IF(MONTH(Assumptions!$D$8)=12,1,IF(MONTH(Assumptions!$F$32)<MONTH(P106),1,"")),IF(O112="",IF(P108=YEAR(Assumptions!$F$32)+1,1,""),""))
F115: Assessments for Option 6
B117: =DATE(C120+1,B120,26) -> 26
B120: =MONTH(Assumptions!G23)-MONTH(Assumptions!$D$8) -> -11 | C120: =YEAR(Assumptions!G23) -> 1900 | D120: =MONTH(Assumptions!G23) -> 1 | E120: =DAY(Assumptions!G23) -> 0 | G120: =IF(B131="",1,B131) -> 0
B124: =Assumptions!G24*12 -> 0
A126: Loan Clac | B126: =IF((MONTH(B129)-MONTH(Assumptions!$E$32))+1=12,0,(MONTH(B129)-MONTH(Assumptions!$E$32))+1) -> 0 | C126: =IF((MONTH(C129)-MONTH(Assumptions!$E$32))+1=12,0,(MONTH(C129)-MONTH(Assumptions!$E$32))+1) -> 0 | D126: =IF((MONTH(D129)-MONTH(Assumptions!$E$32))+1=12,0,(MONTH(D129)-MONTH(Assumptions!$E$32))+1) -> 0 | E126: =IF((MONTH(E129)-MONTH(Assumptions!$E$32))+1=12,0,(MONTH(E129)-MONTH(Assumptions!$E$32))+1) -> 0 | F126: =IF((MONTH(F129)-MONTH(Assumptions!$E$32))+1=12,0,(MONTH(F129)-MONTH(Assumptions!$E$32))+1) -> 0 | G126: =IF((MONTH(G129)-MONTH(Assumptions!$E$32))+1=12,0,(MONTH(G129)-MONTH(Assumptions!$E$32))+1) -> 0 | H126: =IF((MONTH(H129)-MONTH(Assumptions!$E$32))+1=12,0,(MONTH(H129)-MONTH(Assumptions!$E$32))+1) -> 0 | I126: =IF((MONTH(I129)-MONTH(Assumptions!$E$32))+1=12,0,(MONTH(I129)-MONTH(Assumptions!$E$32))+1) -> 0 | ... P126: =IF((MONTH(P129)-MONTH(Assumptions!$E$32))+1=12,0,(MONTH(P129)-MONTH(Assumptions!$E$32))+1) -> 0
A127: SA Calc | B127: =IF((MONTH(B129)-MONTH(Assumptions!$G$22))+1=12,0,(MONTH(B129)-MONTH(Assumptions!$G$22))+1) -> 0 | C127: =IF((MONTH(C129)-MONTH(Assumptions!$G$22))+1=12,0,(MONTH(C129)-MONTH(Assumptions!$G$22))+1) -> 0 | D127: =IF((MONTH(D129)-MONTH(Assumptions!$G$22))+1=12,0,(MONTH(D129)-MONTH(Assumptions!$G$22))+1) -> 0 | E127: =IF((MONTH(E129)-MONTH(Assumptions!$G$22))+1=12,0,(MONTH(E129)-MONTH(Assumptions!$G$22))+1) -> 0 | F127: =IF((MONTH(F129)-MONTH(Assumptions!$G$22))+1=12,0,(MONTH(F129)-MONTH(Assumptions!$G$22))+1) -> 0 | G127: =IF((MONTH(G129)-MONTH(Assumptions!$G$22))+1=12,0,(MONTH(G129)-MONTH(Assumptions!$G$22))+1) -> 0 | H127: =IF((MONTH(H129)-MONTH(Assumptions!$G$22))+1=12,0,(MONTH(H129)-MONTH(Assumptions!$G$22))+1) -> 0 | I127: =IF((MONTH(I129)-MONTH(Assumptions!$G$22))+1=12,0,(MONTH(I129)-MONTH(Assumptions!$G$22))+1) -> 0 | ... P127: =IF((MONTH(P129)-MONTH(Assumptions!$G$22))+1=12,0,(MONTH(P129)-MONTH(Assumptions!$G$22))+1) -> 0
A128: Beg | B128: =DATE(B130,IF(MONTH(Assumptions!$D$8)=12,1,MONTH(Assumptions!$D$8)+1),1) -> 41275 | C128: =DATE(C130,IF(MONTH(Assumptions!$D$8)=12,1,MONTH(Assumptions!$D$8)+1),1) -> 41640 | D128: =DATE(D130,IF(MONTH(Assumptions!$D$8)=12,1,MONTH(Assumptions!$D$8)+1),1) -> 42005 | E128: =DATE(E130,IF(MONTH(Assumptions!$D$8)=12,1,MONTH(Assumptions!$D$8)+1),1) -> 42370 | F128: =DATE(F130,IF(MONTH(Assumptions!$D$8)=12,1,MONTH(Assumptions!$D$8)+1),1) -> 42736 | G128: =DATE(G130,IF(MONTH(Assumptions!$D$8)=12,1,MONTH(Assumptions!$D$8)+1),1) -> 43101 | H128: =DATE(H130,IF(MONTH(Assumptions!$D$8)=12,1,MONTH(Assumptions!$D$8)+1),1) -> 43466 | I128: =DATE(I130,IF(MONTH(Assumptions!$D$8)=12,1,MONTH(Assumptions!$D$8)+1),1) -> 43831 | ... P128: =DATE(P130,IF(MONTH(Assumptions!$D$8)=12,1,MONTH(Assumptions!$D$8)+1),1) -> 46388
A129: End | B129: =DATE(IF(MONTH(Assumptions!$D$8)=12,B130,B130+1),MONTH(Assumptions!$D$8),DAY(Assumptions!$D$8)) -> 41639 | C129: =DATE(IF(MONTH(Assumptions!$D$8)=12,C130,C130+1),MONTH(Assumptions!$D$8),DAY(Assumptions!$D$8)) -> 42004 | D129: =DATE(IF(MONTH(Assumptions!$D$8)=12,D130,D130+1),MONTH(Assumptions!$D$8),DAY(Assumptions!$D$8)) -> 42369 | E129: =DATE(IF(MONTH(Assumptions!$D$8)=12,E130,E130+1),MONTH(Assumptions!$D$8),DAY(Assumptions!$D$8)) -> 42735 | F129: =DATE(IF(MONTH(Assumptions!$D$8)=12,F130,F130+1),MONTH(Assumptions!$D$8),DAY(Assumptions!$D$8)) -> 43100 | G129: =DATE(IF(MONTH(Assumptions!$D$8)=12,G130,G130+1),MONTH(Assumptions!$D$8),DAY(Assumptions!$D$8)) -> 43465 | H129: =DATE(IF(MONTH(Assumptions!$D$8)=12,H130,H130+1),MONTH(Assumptions!$D$8),DAY(Assumptions!$D$8)) -> 43830 | I129: =DATE(IF(MONTH(Assumptions!$D$8)=12,I130,I130+1),MONTH(Assumptions!$D$8),DAY(Assumptions!$D$8)) -> 44196 | ... P129: =DATE(IF(MONTH(Assumptions!$D$8)=12,P130,P130+1),MONTH(Assumptions!$D$8),DAY(Assumptions!$D$8)) -> 46752
B130: =Assumptions!$D$7 -> 2013 | C130: =+B130+1 -> 2014 | D130: =+C130+1 -> 2015 | E130: =+D130+1 -> 2016 | F130: =+E130+1 -> 2017 | G130: =+F130+1 -> 2018 | H130: =+G130+1 -> 2019 | I130: =+H130+1 -> 2020 | J130: =+I130+1 -> 2021 | ... P130: =+O130+1 -> 2027
A131: SA Month | B131: =IF(YEAR(Assumptions!$G$22)=B130,IF(MONTH(Assumptions!$D$8)=12,12-MONTH(Assumptions!$G$22)+1,IF(MONTH(Assumptions!$G$22)<MONTH(Assumptions!$D$8),(MONTH(Assumptions!$D$8)-MONTH(Assumptions!$G$22))+1,IF(MONTH(Assumptions!$G$22)=MONTH(Assumptions!$D$8),1,""))),IF(AND(A131="",YEAR(Assumptions!$G$22)+1=B130),((MONTH(B129)+12)-MONTH(Assumptions!$G$22))+1,IF(YEAR($B$117)=B130,$B$124-SUM(A$131:$A131),IF(B130<YEAR(Assumptions!$G$22),0,IF(B130<YEAR($B$117),12,IF(B130>YEAR($B$117),0)))))) -> 0 | C131: =IF(YEAR(Assumptions!$G$22)=C130,IF(MONTH(Assumptions!$D$8)=12,12-MONTH(Assumptions!$G$22)+1,IF(MONTH(Assumptions!$G$22)<MONTH(Assumptions!$D$8),(MONTH(Assumptions!$D$8)-MONTH(Assumptions!$G$22))+1,IF(MONTH(Assumptions!$G$22)=MONTH(Assumptions!$D$8),1,""))),IF(AND(B131="",YEAR(Assumptions!$G$22)+1=C130),((MONTH(C129)+12)-MONTH(Assumptions!$G$22))+1,IF(YEAR($B$117)=C130,$B$124-SUM(B131:B131),IF(C130<YEAR(Assumptions!$G$22),"",IF(C130<YEAR($B$117),12,IF(C130>YEAR($B$117),"")))))) | D131: =IF(YEAR(Assumptions!$G$22)=D130,IF(MONTH(Assumptions!$D$8)=12,12-MONTH(Assumptions!$G$22)+1,IF(MONTH(Assumptions!$G$22)<MONTH(Assumptions!$D$8),(MONTH(Assumptions!$D$8)-MONTH(Assumptions!$G$22))+1,IF(MONTH(Assumptions!$G$22)=MONTH(Assumptions!$D$8),1,""))),IF(AND(C131="",YEAR(Assumptions!$G$22)+1=D130),((MONTH(D129)+12)-MONTH(Assumptions!$G$22))+1,IF(YEAR($B$117)=D130,$B$124-SUM($B$131:C131),IF(D130<YEAR(Assumptions!$G$22),"",IF(D130<YEAR($B$117),12,IF(D130>YEAR($B$117),"")))))) | E131: =IF(YEAR(Assumptions!$G$22)=E130,IF(MONTH(Assumptions!$D$8)=12,12-MONTH(Assumptions!$G$22)+1,IF(MONTH(Assumptions!$G$22)<MONTH(Assumptions!$D$8),(MONTH(Assumptions!$D$8)-MONTH(Assumptions!$G$22))+1,IF(MONTH(Assumptions!$G$22)=MONTH(Assumptions!$D$8),1,""))),IF(AND(D131="",YEAR(Assumptions!$G$22)+1=E130),((MONTH(E129)+12)-MONTH(Assumptions!$G$22))+1,IF(YEAR($B$117)=E130,$B$124-SUM($B$131:D131),IF(E130<YEAR(Assumptions!$G$22),"",IF(E130<YEAR($B$117),12,IF(E130>YEAR($B$117),"")))))) | F131: =IF(YEAR(Assumptions!$G$22)=F130,IF(MONTH(Assumptions!$D$8)=12,12-MONTH(Assumptions!$G$22)+1,IF(MONTH(Assumptions!$G$22)<MONTH(Assumptions!$D$8),(MONTH(Assumptions!$D$8)-MONTH(Assumptions!$G$22))+1,IF(MONTH(Assumptions!$G$22)=MONTH(Assumptions!$D$8),1,""))),IF(AND(E131="",YEAR(Assumptions!$G$22)+1=F130),((MONTH(F129)+12)-MONTH(Assumptions!$G$22))+1,IF(YEAR($B$117)=F130,$B$124-SUM($B$131:E131),IF(F130<YEAR(Assumptions!$G$22),"",IF(F130<YEAR($B$117),12,IF(F130>YEAR($B$117),"")))))) | G131: =IF(YEAR(Assumptions!$G$22)=G130,IF(MONTH(Assumptions!$D$8)=12,12-MONTH(Assumptions!$G$22)+1,IF(MONTH(Assumptions!$G$22)<MONTH(Assumptions!$D$8),(MONTH(Assumptions!$D$8)-MONTH(Assumptions!$G$22))+1,IF(MONTH(Assumptions!$G$22)=MONTH(Assumptions!$D$8),1,""))),IF(AND(F131="",YEAR(Assumptions!$G$22)+1=G130),((MONTH(G129)+12)-MONTH(Assumptions!$G$22))+1,IF(YEAR($B$117)=G130,$B$124-SUM($B$131:F131),IF(G130<YEAR(Assumptions!$G$22),"",IF(G130<YEAR($B$117),12,IF(G130>YEAR($B$117),"")))))) | H131: =IF(YEAR(Assumptions!$G$22)=H130,IF(MONTH(Assumptions!$D$8)=12,12-MONTH(Assumptions!$G$22)+1,IF(MONTH(Assumptions!$G$22)<MONTH(Assumptions!$D$8),(MONTH(Assumptions!$D$8)-MONTH(Assumptions!$G$22))+1,IF(MONTH(Assumptions!$G$22)=MONTH(Assumptions!$D$8),1,""))),IF(AND(G131="",YEAR(Assumptions!$G$22)+1=H130),((MONTH(H129)+12)-MONTH(Assumptions!$G$22))+1,IF(YEAR($B$117)=H130,$B$124-SUM($B$131:G131),IF(H130<YEAR(Assumptions!$G$22),"",IF(H130<YEAR($B$117),12,IF(H130>YEAR($B$117),"")))))) | I131: =IF(YEAR(Assumptions!$G$22)=I130,IF(MONTH(Assumptions!$D$8)=12,12-MONTH(Assumptions!$G$22)+1,IF(MONTH(Assumptions!$G$22)<MONTH(Assumptions!$D$8),(MONTH(Assumptions!$D$8)-MONTH(Assumptions!$G$22))+1,IF(MONTH(Assumptions!$G$22)=MONTH(Assumptions!$D$8),1,""))),IF(AND(H131="",YEAR(Assumptions!$G$22)+1=I130),((MONTH(I129)+12)-MONTH(Assumptions!$G$22))+1,IF(YEAR($B$117)=I130,$B$124-SUM($B$131:H131),IF(I130<YEAR(Assumptions!$G$22),"",IF(I130<YEAR($B$117),12,IF(I130>YEAR($B$117),"")))))) | J131: =IF(YEAR(Assumptions!$G$22)=J130,IF(MONTH(Assumptions!$D$8)=12,12-MONTH(Assumptions!$G$22)+1,IF(MONTH(Assumptions!$G$22)<MONTH(Assumptions!$D$8),(MONTH(Assumptions!$D$8)-MONTH(Assumptions!$G$22))+1,IF(MONTH(Assumptions!$G$22)=MONTH(Assumptions!$D$8),1,""))),IF(AND(I131="",YEAR(Assumptions!$G$22)+1=J130),((MONTH(J129)+12)-MONTH(Assumptions!$G$22))+1,IF(YEAR($B$117)=J130,$B$124-SUM($B$131:I131),IF(J130<YEAR(Assumptions!$G$22),"",IF(J130<YEAR($B$117),12,IF(J130>YEAR($B$117),"")))))) | K131: =IF(YEAR(Assumptions!$G$22)=K130,IF(MONTH(Assumptions!$D$8)=12,12-MONTH(Assumptions!$G$22)+1,IF(MONTH(Assumptions!$G$22)<MONTH(Assumptions!$D$8),(MONTH(Assumptions!$D$8)-MONTH(Assumptions!$G$22))+1,IF(MONTH(Assumptions!$G$22)=MONTH(Assumptions!$D$8),1,""))),IF(AND(J131="",YEAR(Assumptions!$G$22)+1=K130),((MONTH(K129)+12)-MONTH(Assumptions!$G$22))+1,IF(YEAR($B$117)=K130,$B$124-SUM($B$131:J131),IF(K130<YEAR(Assumptions!$G$22),"",IF(K130<YEAR($B$117),12,IF(K130>YEAR($B$117),"")))))) | ... P131: =IF(YEAR(Assumptions!$G$22)=P130,IF(MONTH(Assumptions!$D$8)=12,12-MONTH(Assumptions!$G$22)+1,IF(MONTH(Assumptions!$G$22)<MONTH(Assumptions!$D$8),(MONTH(Assumptions!$D$8)-MONTH(Assumptions!$G$22))+1,IF(MONTH(Assumptions!$G$22)=MONTH(Assumptions!$D$8),1,""))),IF(AND(O131="",YEAR(Assumptions!$G$22)+1=P130),((MONTH(P129)+12)-MONTH(Assumptions!$G$22))+1,IF(YEAR($B$117)=P130,$B$124-SUM($B$131:O131),IF(P130<YEAR(Assumptions!$G$22),"",IF(P130<YEAR($B$117),12,IF(P130>YEAR($B$117),""))))))
A132: Loan | B132: =IF(YEAR(Assumptions!$G$32)=B130,IF(MONTH(Assumptions!$D$8)=12,MONTH(Assumptions!$G$32),IF(MONTH(Assumptions!$G$32)<MONTH(Assumptions!$D$8),12-((MONTH(Assumptions!$D$8)-MONTH(Assumptions!$G$32))),IF(MONTH(Assumptions!$G$32)=MONTH(Assumptions!$D$8),1,IF(MONTH(Assumptions!$G$32)>MONTH(Assumptions!$D$8),IF(YEAR(Assumptions!$G$32)+1=B130,(MONTH(Assumptions!$G$32)-MONTH(B128))+1,""),"")))),IF(YEAR(Assumptions!$G$32)+1=B130,(MONTH(Assumptions!$G$32)-MONTH(B128))+1,"")) | C132: =IF(B132="",IF(YEAR(Assumptions!$G$32)=C130,IF(MONTH(Assumptions!$D$8)=12,MONTH(Assumptions!$G$32),IF(MONTH(Assumptions!$G$32)<MONTH(Assumptions!$D$8),12-((MONTH(Assumptions!$D$8)-MONTH(Assumptions!$G$32))),IF(MONTH(Assumptions!$G$32)=MONTH(Assumptions!$D$8),1,IF(MONTH(Assumptions!$G$32)>MONTH(Assumptions!$D$8),IF(YEAR(Assumptions!$G$32)+1=C130,(MONTH(Assumptions!$G$32)-MONTH(C128))+1,""),"")))),IF(YEAR(Assumptions!$G$32)+1=C130,(MONTH(Assumptions!$G$32)-MONTH(C128))+1,"")),"") | D132: =IF(C132="",IF(YEAR(Assumptions!$G$32)=D130,IF(MONTH(Assumptions!$D$8)=12,MONTH(Assumptions!$G$32),IF(MONTH(Assumptions!$G$32)<MONTH(Assumptions!$D$8),12-((MONTH(Assumptions!$D$8)-MONTH(Assumptions!$G$32))),IF(MONTH(Assumptions!$G$32)=MONTH(Assumptions!$D$8),1,IF(MONTH(Assumptions!$G$32)>MONTH(Assumptions!$D$8),IF(YEAR(Assumptions!$G$32)+1=D130,(MONTH(Assumptions!$G$32)-MONTH(D128))+1,""),"")))),IF(YEAR(Assumptions!$G$32)+1=D130,(MONTH(Assumptions!$G$32)-MONTH(D128))+1,"")),"") | E132: =IF(D132="",IF(YEAR(Assumptions!$G$32)=E130,IF(MONTH(Assumptions!$D$8)=12,MONTH(Assumptions!$G$32),IF(MONTH(Assumptions!$G$32)<MONTH(Assumptions!$D$8),12-((MONTH(Assumptions!$D$8)-MONTH(Assumptions!$G$32))),IF(MONTH(Assumptions!$G$32)=MONTH(Assumptions!$D$8),1,IF(MONTH(Assumptions!$G$32)>MONTH(Assumptions!$D$8),IF(YEAR(Assumptions!$G$32)+1=E130,(MONTH(Assumptions!$G$32)-MONTH(E128))+1,""),"")))),IF(YEAR(Assumptions!$G$32)+1=E130,(MONTH(Assumptions!$G$32)-MONTH(E128))+1,"")),"") | F132: =IF(E132="",IF(YEAR(Assumptions!$G$32)=F130,IF(MONTH(Assumptions!$D$8)=12,MONTH(Assumptions!$G$32),IF(MONTH(Assumptions!$G$32)<MONTH(Assumptions!$D$8),12-((MONTH(Assumptions!$D$8)-MONTH(Assumptions!$G$32))),IF(MONTH(Assumptions!$G$32)=MONTH(Assumptions!$D$8),1,IF(MONTH(Assumptions!$G$32)>MONTH(Assumptions!$D$8),IF(YEAR(Assumptions!$G$32)+1=F130,(MONTH(Assumptions!$G$32)-MONTH(F128))+1,""),"")))),IF(YEAR(Assumptions!$G$32)+1=F130,(MONTH(Assumptions!$G$32)-MONTH(F128))+1,"")),"") | G132: =IF(F132="",IF(YEAR(Assumptions!$G$32)=G130,IF(MONTH(Assumptions!$D$8)=12,MONTH(Assumptions!$G$32),IF(MONTH(Assumptions!$G$32)<MONTH(Assumptions!$D$8),12-((MONTH(Assumptions!$D$8)-MONTH(Assumptions!$G$32))),IF(MONTH(Assumptions!$G$32)=MONTH(Assumptions!$D$8),1,IF(MONTH(Assumptions!$G$32)>MONTH(Assumptions!$D$8),IF(YEAR(Assumptions!$G$32)+1=G130,(MONTH(Assumptions!$G$32)-MONTH(G128))+1,""),"")))),IF(YEAR(Assumptions!$G$32)+1=G130,(MONTH(Assumptions!$G$32)-MONTH(G128))+1,"")),"") | H132: =IF(G132="",IF(YEAR(Assumptions!$G$32)=H130,IF(MONTH(Assumptions!$D$8)=12,MONTH(Assumptions!$G$32),IF(MONTH(Assumptions!$G$32)<MONTH(Assumptions!$D$8),12-((MONTH(Assumptions!$D$8)-MONTH(Assumptions!$G$32))),IF(MONTH(Assumptions!$G$32)=MONTH(Assumptions!$D$8),1,IF(MONTH(Assumptions!$G$32)>MONTH(Assumptions!$D$8),IF(YEAR(Assumptions!$G$32)+1=H130,(MONTH(Assumptions!$G$32)-MONTH(H128))+1,""),"")))),IF(YEAR(Assumptions!$G$32)+1=H130,(MONTH(Assumptions!$G$32)-MONTH(H128))+1,"")),"") | I132: =IF(H132="",IF(YEAR(Assumptions!$G$32)=I130,IF(MONTH(Assumptions!$D$8)=12,MONTH(Assumptions!$G$32),IF(MONTH(Assumptions!$G$32)<MONTH(Assumptions!$D$8),12-((MONTH(Assumptions!$D$8)-MONTH(Assumptions!$G$32))),IF(MONTH(Assumptions!$G$32)=MONTH(Assumptions!$D$8),1,IF(MONTH(Assumptions!$G$32)>MONTH(Assumptions!$D$8),IF(YEAR(Assumptions!$G$32)+1=I130,(MONTH(Assumptions!$G$32)-MONTH(I128))+1,""),"")))),IF(YEAR(Assumptions!$G$32)+1=I130,(MONTH(Assumptions!$G$32)-MONTH(I128))+1,"")),"") | J132: =IF(I132="",IF(YEAR(Assumptions!$G$32)=J130,IF(MONTH(Assumptions!$D$8)=12,MONTH(Assumptions!$G$32),IF(MONTH(Assumptions!$G$32)<MONTH(Assumptions!$D$8),12-((MONTH(Assumptions!$D$8)-MONTH(Assumptions!$G$32))),IF(MONTH(Assumptions!$G$32)=MONTH(Assumptions!$D$8),1,IF(MONTH(Assumptions!$G$32)>MONTH(Assumptions!$D$8),IF(YEAR(Assumptions!$G$32)+1=J130,(MONTH(Assumptions!$G$32)-MONTH(J128))+1,""),"")))),IF(YEAR(Assumptions!$G$32)+1=J130,(MONTH(Assumptions!$G$32)-MONTH(J128))+1,"")),"") | ... P132: =IF(O132="",IF(YEAR(Assumptions!$G$32)=P130,IF(MONTH(Assumptions!$D$8)=12,MONTH(Assumptions!$G$32),IF(MONTH(Assumptions!$G$32)<MONTH(Assumptions!$D$8),12-((MONTH(Assumptions!$D$8)-MONTH(Assumptions!$G$32))),IF(MONTH(Assumptions!$G$32)=MONTH(Assumptions!$D$8),1,IF(MONTH(Assumptions!$G$32)>MONTH(Assumptions!$D$8),IF(YEAR(Assumptions!$G$32)+1=P130,(MONTH(Assumptions!$G$32)-MONTH(P128))+1,""),"")))),IF(YEAR(Assumptions!$G$32)+1=P130,(MONTH(Assumptions!$G$32)-MONTH(P128))+1,"")),"")
A133: SA Fee | B133: =IF(YEAR(Assumptions!$G$22)=B130,IF(MONTH(Assumptions!$D$8)=12,1,IF(MONTH(Assumptions!$G$22)<MONTH(B128),1,"")),IF(A133="",IF(B130=YEAR(Assumptions!$G$22)+1,1,""),"")) | C133: =IF(YEAR(Assumptions!$G$22)=C130,IF(MONTH(Assumptions!$D$8)=12,1,IF(MONTH(Assumptions!$G$22)<MONTH(C128),1,"")),IF(B133="",IF(C130=YEAR(Assumptions!$G$22)+1,1,""),"")) | D133: =IF(YEAR(Assumptions!$G$22)=D130,IF(MONTH(Assumptions!$D$8)=12,1,IF(MONTH(Assumptions!$G$22)<MONTH(D128),1,"")),IF(C133="",IF(D130=YEAR(Assumptions!$G$22)+1,1,""),"")) | E133: =IF(YEAR(Assumptions!$G$22)=E130,IF(MONTH(Assumptions!$D$8)=12,1,IF(MONTH(Assumptions!$G$22)<MONTH(E128),1,"")),IF(D133="",IF(E130=YEAR(Assumptions!$G$22)+1,1,""),"")) | F133: =IF(YEAR(Assumptions!$G$22)=F130,IF(MONTH(Assumptions!$D$8)=12,1,IF(MONTH(Assumptions!$G$22)<MONTH(F128),1,"")),IF(E133="",IF(F130=YEAR(Assumptions!$G$22)+1,1,""),"")) | G133: =IF(YEAR(Assumptions!$G$22)=G130,IF(MONTH(Assumptions!$D$8)=12,1,IF(MONTH(Assumptions!$G$22)<MONTH(G128),1,"")),IF(F133="",IF(G130=YEAR(Assumptions!$G$22)+1,1,""),"")) | H133: =IF(YEAR(Assumptions!$G$22)=H130,IF(MONTH(Assumptions!$D$8)=12,1,IF(MONTH(Assumptions!$G$22)<MONTH(H128),1,"")),IF(G133="",IF(H130=YEAR(Assumptions!$G$22)+1,1,""),"")) | I133: =IF(YEAR(Assumptions!$G$22)=I130,IF(MONTH(Assumptions!$D$8)=12,1,IF(MONTH(Assumptions!$G$22)<MONTH(I128),1,"")),IF(H133="",IF(I130=YEAR(Assumptions!$G$22)+1,1,""),"")) | ... P133: =IF(YEAR(Assumptions!$G$22)=P130,IF(MONTH(Assumptions!$D$8)=12,1,IF(MONTH(Assumptions!$G$22)<MONTH(P128),1,"")),IF(O133="",IF(P130=YEAR(Assumptions!$G$22)+1,1,""),""))
A134: Loan Proceed | B134: =IF(YEAR(Assumptions!$G$32)=B130,IF(MONTH(Assumptions!$D$8)=12,1,IF(MONTH(Assumptions!$G$32)<MONTH(B128),1,"")),IF(A134="",IF(B130=YEAR(Assumptions!$G$32)+1,1,""),"")) | C134: =IF(YEAR(Assumptions!$G$32)=C130,IF(MONTH(Assumptions!$D$8)=12,1,IF(MONTH(Assumptions!$G$32)<MONTH(C128),1,"")),IF(B134="",IF(C130=YEAR(Assumptions!$G$32)+1,1,""),"")) | D134: =IF(YEAR(Assumptions!$G$32)=D130,IF(MONTH(Assumptions!$D$8)=12,1,IF(MONTH(Assumptions!$G$32)<MONTH(D128),1,"")),IF(C134="",IF(D130=YEAR(Assumptions!$G$32)+1,1,""),"")) | E134: =IF(YEAR(Assumptions!$G$32)=E130,IF(MONTH(Assumptions!$D$8)=12,1,IF(MONTH(Assumptions!$G$32)<MONTH(E128),1,"")),IF(D134="",IF(E130=YEAR(Assumptions!$G$32)+1,1,""),"")) | F134: =IF(YEAR(Assumptions!$G$32)=F130,IF(MONTH(Assumptions!$D$8)=12,1,IF(MONTH(Assumptions!$G$32)<MONTH(F128),1,"")),IF(E134="",IF(F130=YEAR(Assumptions!$G$32)+1,1,""),"")) | G134: =IF(YEAR(Assumptions!$G$32)=G130,IF(MONTH(Assumptions!$D$8)=12,1,IF(MONTH(Assumptions!$G$32)<MONTH(G128),1,"")),IF(F134="",IF(G130=YEAR(Assumptions!$G$32)+1,1,""),"")) | H134: =IF(YEAR(Assumptions!$G$32)=H130,IF(MONTH(Assumptions!$D$8)=12,1,IF(MONTH(Assumptions!$G$32)<MONTH(H128),1,"")),IF(G134="",IF(H130=YEAR(Assumptions!$G$32)+1,1,""),"")) | I134: =IF(YEAR(Assumptions!$G$32)=I130,IF(MONTH(Assumptions!$D$8)=12,1,IF(MONTH(Assumptions!$G$32)<MONTH(I128),1,"")),IF(H134="",IF(I130=YEAR(Assumptions!$G$32)+1,1,""),"")) | ... P134: =IF(YEAR(Assumptions!$G$32)=P130,IF(MONTH(Assumptions!$D$8)=12,1,IF(MONTH(Assumptions!$G$32)<MONTH(P128),1,"")),IF(O134="",IF(P130=YEAR(Assumptions!$G$32)+1,1,""),""))

Sheet Assumptions
A1: Special Assessment Assumptions
A3: General Information | I3: Available Reserve Cash Balance
K4: Option 1 | L4: Option 2 | M4: Option 3 | N4: Option 4 | O4: Option 5 | P4: Option 6
A5: Property Name: | D5: Dana Point | J5: =+D7 -> 2013 | K5: =+'Option 1'!D$252 -> 290817.53 | L5: =+'Option 2'!D$252 -> 290817.53 | M5: =+'Option 3'!D$252 -> 290817.53 | N5: =+'Option 4'!D$252 -> 290817.53 | O5: =+'Option 5'!D$252 -> 290817.53 | P5: =+'Option 6'!D$252 -> 290817.53
A6: Property #: | D6: 554 | J6: =+J5+1 -> 2014 | K6: =+'Option 1'!E252 -> 479775.62 | L6: =+'Option 2'!E252 -> 462904.84 | M6: =+'Option 3'!E$252 -> 519821.09 | N6: =+'Option 4'!E$252 -> 608294.9 | O6: =+'Option 5'!E$252 -> 462904.84 | P6: =+'Option 6'!E$252 -> 462904.84
A7: Current Year (YYYY) | D7: 2013 | J7: =+J6+1 -> 2015 | K7: =+'Option 1'!F252 -> 653028.4 | L7: =+'Option 2'!F252 -> 618612.01 | M7: =+'Option 3'!F$252 -> 785408.69 | N7: =+'Option 4'!F$252 -> 952149.16 | O7: =+'Option 5'!F$252 -> 618612.01 | P7: =+'Option 6'!F$252 -> 618612.01
A8: Fiscal Year End | D8: 41639 | J8: =+J7+1 -> 2016 | K8: =+'Option 1'!G252 -> -388424.37 | L8: =+'Option 2'!G252 -> -441255.22 | M8: =+'Option 3'!G$252 -> -162645.34 | N8: =+'Option 4'!G$252 -> 72553.541 | O8: =+'Option 5'!G$252 -> -441255.22 | P8: =+'Option 6'!G$252 -> -441255.22
A9: Current Yr Operating Budget | D9: 1743474 | J9: =+J8+1 -> 2017 | K9: =+'Option 1'!H252 -> -1484659.5 | L9: =+'Option 2'!H252 -> -1556982.1 | M9: =+'Option 3'!H$252 -> -1163488.8 | N9: =+'Option 4'!H$252 -> -869396 | O9: =+'Option 5'!H$252 -> -1556982.1 | P9: =+'Option 6'!H$252 -> -1556982.1
A10: Current Yr Contribution to Reserves | D10: 485174 | J10: =+J9+1 -> 2018 | K10: =+'Option 1'!I252 -> -2967044.7 | L10: =+'Option 2'!I252 -> -1560163.6 | M10: =+'Option 3'!I$252 -> -1847521.6 | N10: =+'Option 4'!I$252 -> -1204007 | O10: =+'Option 5'!I$252 -> -3060163.6 | P10: =+'Option 6'!I$252 -> -3060163.6
A11: Operating Budget less Contribution | D11: =+D9-D10 -> 1258300 | J11: =+J10+1 -> 2019 | K11: =+'Option 1'!J252 -> -3074184.2 | L11: =+'Option 2'!J252 -> -1863044.2 | M11: =+'Option 3'!J$252 -> -2001643.8 | N11: =+'Option 4'!J$252 -> -1382233.2 | O11: =+'Option 5'!J$252 -> -3189654.5 | P11: =+'Option 6'!J$252 -> -3189654.5
J12: =+J11+1 -> 2020 | K12: =+'Option 1'!K252 -> -3921497.1 | L12: =+'Option 2'!K252 -> -2906501.4 | M12: =+'Option 3'!K$252 -> -2892572.8 | N12: =+'Option 4'!K$252 -> -2307750.9 | O12: =+'Option 5'!K$252 -> -4061153.5 | P12: =+'Option 6'!K$252 -> -4061153.5
A13: # of Units or Shares: | D13: 499 | J13: =+J12+1 -> 2021 | K13: =+'Option 1'!L252 -> -3891890.1 | L13: =+'Option 2'!L252 -> -3075433.2 | M13: =+'Option 3'!L$252 -> -2903568.2 | N13: =+'Option 4'!L$252 -> -2364865.7 | O13: =+'Option 5'!L$252 -> -4057881.6 | P13: =+'Option 6'!L$252 -> -4057881.6
J14: =+J13+1 -> 2022 | K14: =+'Option 1'!M252 -> -4397561.4 | L14: =+'Option 2'!M252 -> -3784125 | M14: =+'Option 3'!M$252 -> -3447146.9 | N14: =+'Option 4'!M$252 -> -2967356.7 | O14: =+'Option 5'!M$252 -> -4592394 | P14: =+'Option 6'!M$252 -> -4592394
A15: Beginning Reserve Cash Account: | D15: 623745 | J15: =+J14+1 -> 2023 | K15: =+'Option 1'!N252 -> -4258101.8 | L15: =+'Option 2'!N252 -> -3854395.8 | M15: =+'Option 3'!N$252 -> -3187061.4 | N15: =+'Option 4'!N$252 -> -2713574.3 | O15: =+'Option 5'!N$252 -> -4484688.6 | P15: =+'Option 6'!N$252 -> -4484688.6
A16: As of Date: | D16: 41486 | J16: =+J15+1 -> 2024 | K16: =+'Option 1'!O252 -> -3836706.1 | L16: =+'Option 2'!O252 -> -3653877.4 | M16: =+'Option 3'!O$252 -> -2734786.5 | N16: =+'Option 4'!O$252 -> -2734510.2 | O16: =+'Option 5'!O$252 -> -4097295.1 | P16: =+'Option 6'!O$252 -> -4097295.1
A18: Special Assessment Assumptions | I18: Avg Unit's Assessment per Option
B19: Current Situation - No loan extention | C19: Loan and No Special Assessment | D19: Loan and Special Assessment | E19: Reduce Oper Assessment, but a larger Special Assessment
B20: Option 1 | C20: Option 2 | D20: Option 3 | E20: Option 4 | F20: Option 5 | G20: Option 6 | K20: Option 1 | L20: Option 2 | M20: Option 3 | N20: Option 4 | O20: Option 5 | P20: Option 6 | R20: No | S20: 1 | T20: 2 | U20: 3 | V20: 4 | W20: 5 | X20: 6
A21: Special Amount | D21: 1000000 | E21: 5000000 | I21: Monthly Special Assessment | K21: =-IF(B$21=0,0,PMT(B$25/12,B$24*12,B$21)/$D$13) -> 0 | L21: =-IF(C$21=0,0,PMT(C$25/12,C$24*12,C$21)/$D$13) -> 0 | M21: =-IF(D$21=0,0,PMT(D$25/12,D$24*12,D$21)/$D$13) -> 21.255614 | N21: =-IF(E$21=0,0,PMT(E$25/12,E$24*12,E$21)/$D$13) -> 106.27807 | O21: =-IF(F$21=0,0,PMT(F$25/12,F$24*12,F$21)/$D$13) -> 0 | P21: =-IF(G$21=0,0,PMT(G$25/12,G$24*12,G$21)/$D$13) -> 0 | R21: =+D9 -> 1743474 | S21: =+$R21+SUM('Option 1'!$D$12:$D$13) -> 1743474 | T21: =+$R21+SUM('Option 2'!$D$12:$D$13) -> 1743474 | U21: =+$R21+SUM('Option 3'!$D$12:$D$13) -> 1743474 | V21: =+$R21+SUM('Option 4'!$D$12:$D$13) -> 1743474 | W21: =+$R21+SUM('Option 5'!$D$12:$D$13) -> 1743474 | X21: =+$R21+SUM('Option 6'!$D$12:$D$13) -> 1743474
A22: Date of Projected SA | D22: 41640 | E22: 41640 | I22: Reduction of the Operating Assessment | N22: =-359344/D13/12 -> -60.010688 | R22: =+R21*(1+#REF!) -> #REF! | S22: =+$R22+SUM('Option 1'!$E$12:$E$13) -> #REF! | T22: =+$R22+SUM('Option 2'!$E$12:$E$13) -> #REF! | U22: =+$R22+SUM('Option 3'!$E$12:$E$13) -> #REF! | V22: =+$R22+SUM('Option 4'!$E$12:$E$13) -> #REF! | W22: =+$R22+SUM('Option 5'!$E$12:$E$13) -> #REF! | X22: =+$R22+SUM('Option 6'!$E$12:$E$13) -> #REF!
A23: End Date of Specials | B23: =+B22+(365*B24) -> 0 | C23: =+C22+(365*C24) -> 0 | D23: =+D22+(365*D24) -> 45290 | E23: =+E22+(365*E24) -> 45290 | F23: =+F22+(365*F24) -> 0 | G23: =+G22+(365*G24) -> 0 | R23: =+R22*(1+#REF!) -> #REF! | S23: =+$R23+SUM('Option 1'!$F$12:$F$13) -> #REF! | T23: =+$R23+SUM('Option 2'!$F$12:$F$13) -> #REF! | U23: =+$R23+SUM('Option 3'!$F$12:$F$13) -> #REF! | V23: =+$R23+SUM('Option 4'!$F$12:$F$13) -> #REF! | W23: =+$R23+SUM('Option 5'!$F$12:$F$13) -> #REF! | X23: =+$R23+SUM('Option 6'!$F$12:$F$13) -> #REF!
A24: SA term (yrs) | D24: 10 | E24: 10 | J24: Interest Rate on Reserve $$ | K24: Oper Exp Increase | L24: Delinq % | R24: =+R23*(1+#REF!) -> #REF! | S24: =+$R24+SUM('Option 1'!$G$12:$G$13) -> #REF! | T24: =+$R24+SUM('Option 2'!$G$12:$G$13) -> #REF! | U24: =+$R24+SUM('Option 3'!$G$12:$G$13) -> #REF! | V24: =+$R24+SUM('Option 4'!$G$12:$G$13) -> #REF! | W24: =+$R24+SUM('Option 5'!$G$12:$G$13) -> #REF! | X24: =+$R24+SUM('Option 6'!$G$12:$G$13) -> #REF!
A25: SA Interest Charged | D25: 0.05 | E25: 0.05 | I25: =+J5 -> 2013 | J25: 0.0025 | K25: 0.03 | L25: 0.1 | R25: =+R24*(1+#REF!) -> #REF! | S25: =+$R25+SUM('Option 1'!$H$12:$H$13) -> #REF! | T25: =+$R25+SUM('Option 2'!$H$12:$H$13) -> #REF! | U25: =+$R25+SUM('Option 3'!$H$12:$H$13) -> #REF! | V25: =+$R25+SUM('Option 4'!$H$12:$H$13) -> #REF! | W25: =+$R25+SUM('Option 5'!$H$12:$H$13) -> #REF! | X25: =+$R25+SUM('Option 6'!$H$12:$H$13) -> #REF!
A26: Amount charged Interest | B26: =+B21 -> 0 | C26: =+C21 -> 0 | D26: =+D21 -> 1000000 | E26: =+E21 -> 5000000 | F26: =+F21 -> 0 | G26: =+G21 -> 0 | I26: =+I25+1 -> 2014 | J26: 0.005 | K26: 0.03 | L26: 0.1 | R26: =+R25*(1+#REF!) -> #REF! | S26: =+$R26+SUM('Option 1'!$I$12:$I$13) -> #REF! | T26: =+$R26+SUM('Option 2'!$I$12:$I$13) -> #REF! | U26: =+$R26+SUM('Option 3'!$I$12:$I$13) -> #REF! | V26: =+$R26+SUM('Option 4'!$I$12:$I$13) -> #REF! | W26: =+$R26+SUM('Option 5'!$I$12:$I$13) -> #REF! | X26: =+$R26+SUM('Option 6'!$I$12:$I$13) -> #REF!
I27: =+I26+1 -> 2015 | J27: =+J26+0.005 -> 0.01 | K27: 0.03 | L27: 0.1 | R27: =+R26*(1+#REF!) -> #REF! | S27: =+$R27+SUM('Option 1'!$J$12:$J$13) -> #REF! | T27: =+$R27+SUM('Option 2'!$J$12:$J$13) -> #REF! | U27: =+$R27+SUM('Option 3'!$J$12:$J$13) -> #REF! | V27: =+$R27+SUM('Option 4'!$J$12:$J$13) -> #REF! | W27: =+$R27+SUM('Option 5'!$J$12:$J$13) -> #REF! | X27: =+$R27+SUM('Option 6'!$J$12:$J$13) -> #REF!
A28: Loan Assumptions | I28: =+I27+1 -> 2016 | J28: =+J27+0.005 -> 0.015 | K28: 0.03 | L28: 0.1 | R28: =+R27*(1+#REF!) -> #REF! | S28: =+$R28+SUM('Option 1'!$K$12:$K$13) -> #REF! | T28: =+$R28+SUM('Option 2'!$K$12:$K$13) -> #REF! | U28: =+$R28+SUM('Option 3'!$K$12:$K$13) -> #REF! | V28: =+$R28+SUM('Option 4'!$K$12:$K$13) -> #REF! | W28: =+$R28+SUM('Option 5'!$K$12:$K$13) -> #REF! | X28: =+$R28+SUM('Option 6'!$K$12:$K$13) -> #REF!
B29: Option 1 | C29: Option 2 | D29: Option 3 | E29: Option 4 | F29: Option 5 | G29: Option 6 | I29: =+I28+1 -> 2017 | J29: =+J28+0.005 -> 0.02 | K29: 0.03 | L29: 0.1 | R29: =+R28*(1+#REF!) -> #REF! | S29: =+$R29+SUM('Option 1'!$L$12:$L$13) -> #REF! | T29: =+$R29+SUM('Option 2'!$L$12:$L$13) -> #REF! | U29: =+$R29+SUM('Option 3'!$L$12:$L$13) -> #REF! | V29: =+$R29+SUM('Option 4'!$L$12:$L$13) -> #REF! | W29: =+$R29+SUM('Option 5'!$L$12:$L$13) -> #REF! | X29: =+$R29+SUM('Option 6'!$L$12:$L$13) -> #REF!
A30: Loan Amount | C30: 1500000 | D30: 700000 | E30: 1000000 | I30: =+I29+1 -> 2018 | J30: =+J29+0.005 -> 0.025 | K30: 0.03 | L30: 0.1 | R30: =+R29*(1+#REF!) -> #REF! | S30: =+$R30+SUM('Option 1'!$M$12:$M$13) -> #REF! | T30: =+$R30+SUM('Option 2'!$M$12:$M$13) -> #REF! | U30: =+$R30+SUM('Option 3'!$M$12:$M$13) -> #REF! | V30: =+$R30+SUM('Option 4'!$M$12:$M$13) -> #REF! | W30: =+$R30+SUM('Option 5'!$M$12:$M$13) -> #REF! | X30: =+$R30+SUM('Option 6'!$M$12:$M$13) -> #REF!
A31: Loan % of SA | I31: =+I30+1 -> 2019 | J31: =+J30+0.005 -> 0.03 | K31: 0.03 | L31: 0.1 | R31: =+R30*(1+#REF!) -> #REF! | S31: =+$R31+SUM('Option 1'!$N$12:$N$13) -> #REF! | T31: =+$R31+SUM('Option 2'!$N$12:$N$13) -> #REF! | U31: =+$R31+SUM('Option 3'!$N$12:$N$13) -> #REF! | V31: =+$R31+SUM('Option 4'!$N$12:$N$13) -> #REF! | W31: =+$R31+SUM('Option 5'!$N$12:$N$13) -> #REF! | X31: =+$R31+SUM('Option 6'!$N$12:$N$13) -> #REF!
A32: Date of Projected Loan | C32: 43101 | D32: 43101 | E32: 43101 | I32: =+I31+1 -> 2020 | J32: =+J31+0.005 -> 0.035 | K32: 0.03 | L32: 0.1 | R32: =+R31*(1+#REF!) -> #REF! | S32: =+$R32+SUM('Option 1'!$O$12:$O$13) -> #REF! | T32: =+$R32+SUM('Option 2'!$O$12:$O$13) -> #REF! | U32: =+$R32+SUM('Option 3'!$O$12:$O$13) -> #REF! | V32: =+$R32+SUM('Option 4'!$O$12:$O$13) -> #REF! | W32: =+$R32+SUM('Option 5'!$O$12:$O$13) -> #REF! | X32: =+$R32+SUM('Option 6'!$O$12:$O$13) -> #REF!
A33: Projected Loan Interst Rate | C33: 0.08 | D33: 0.08 | E33: 0.08 | I33: =+I32+1 -> 2021 | J33: =+J32+0.005 -> 0.04 | K33: 0.03 | L33: 0.1
I34: =+I33+1 -> 2022 | J34: =+J33+0.005 -> 0.045 | K34: 0.03 | L34: 0.1
A35: End Date of Loan | B35: =+B32+(365*B36) -> 0 | C35: =+C32+(365*C36) -> 46751 | D35: =+D32+(365*D36) -> 44926 | E35: =+E32+(365*E36) -> 44926 | F35: =+F32+(365*F36) -> 0 | G35: =+G32+(365*G36) -> 0 | I35: =+I34+1 -> 2023 | J35: =+J34+0.005 -> 0.05 | K35: 0.03 | L35: 0.1
A36: Loan term (yrs) | C36: 10 | D36: 5 | E36: 5 | I36: =+I35+1 -> 2024 | J36: =+J35 -> 0.05 | K36: 0.03 | L36: 0.1

Sheet Option 1
B1: =Assumptions!D5&" - Reserve & Special Assessment Analysis Option 1" -> Dana Point - Reserve & Special Assessment Analysis Option 1
B2: =+Assumptions!D7&" Reserve Study 10-Year Projection" -> 2013 Reserve Study 10-Year Projection
C4: Special Assessment | D4: =Assumptions!B21 -> 0
E5: =IF(YEAR(Assumptions!$D8)<YEAR(Assumptions!B22),0,1) -> 1 | F5: =+E5+1 -> 2 | G5: =+F5+1 -> 3 | H5: =+G5+1 -> 4 | I5: =+H5+1 -> 5 | J5: =+I5+1 -> 6 | K5: =+J5+1 -> 7 | L5: =+K5+1 -> 8 | M5: =+L5+1 -> 9 | ... O5: =+N5+1 -> 11
D6: =IF(YEAR(Assumptions!B22)>LEFT(D9,4)*1,0,1) -> 1 | E6: =+D7+1 -> 1389 | F6: =+E7+1 -> 1 | G6: =+F7+1 -> 1 | H6: =+G7+1 -> 1 | I6: =+H7+1 -> 1 | J6: =+I7+1 -> 1 | K6: =+J7+1 -> 1 | L6: =+K7+1 -> 1 | ... O6: =+N7+1 -> 1
D7: =IF(D6=0,0,ROUND(((IF(YEAR(Assumptions!D8)<YEAR(Assumptions!B22),(Assumptions!D8+365)-Assumptions!B22,Assumptions!D8-Assumptions!B22))/30),0)) -> 1388 | E7: =IF(D7=0,ROUND(((IF(YEAR(Assumptions!D8)<YEAR(Assumptions!B22),(Assumptions!D8+365)-Assumptions!B22,Assumptions!D8-Assumptions!B22))/30),0),IF(Assumptions!$B$24*12>D7+12,D7+12,Assumptions!$B$24*12)) -> 0 | F7: =IF(Assumptions!$B$24*12>E7+12,E7+12,Assumptions!$B$24*12) -> 0 | G7: =IF(Assumptions!$B$24*12>F7+12,F7+12,Assumptions!$B$24*12) -> 0 | H7: =IF(Assumptions!$B$24*12>G7+12,G7+12,Assumptions!$B$24*12) -> 0 | I7: =IF(Assumptions!$B$24*12>H7+12,H7+12,Assumptions!$B$24*12) -> 0 | J7: =IF(Assumptions!$B$24*12>I7+12,I7+12,Assumptions!$B$24*12) -> 0 | K7: =IF(Assumptions!$B$24*12>J7+12,J7+12,Assumptions!$B$24*12) -> 0 | L7: =IF(Assumptions!$B$24*12>K7+12,K7+12,Assumptions!$B$24*12) -> 0 | M7: =IF(Assumptions!$B$24*12>L7+12,L7+12,Assumptions!$B$24*12) -> 0 | ... O7: =IF(Assumptions!$B$24*12>N7+12,N7+12,Assumptions!$B$24*12) -> 0
A9: INCOME | B9: GL | C9: Name | D9: =Assumptions!D7&" Budget" -> 2013 Budget | E9: =+Assumptions!D7+1 -> 2014 | F9: =+E9+1 -> 2015 | G9: =+F9+1 -> 2016 | H9: =+G9+1 -> 2017 | I9: =+H9+1 -> 2018 | J9: =+I9+1 -> 2019 | K9: =+J9+1 -> 2020 | L9: =+K9+1 -> 2021 | M9: =+L9+1 -> 2022 | ... O9: =+N9+1 -> 2024 | P9: TOTAL
B10: 9001 | C10: Budgeted Operating Funds to Reserves | D10: =ROUND((+Assumptions!D10/12*Calc!$G$9),0) -> 202156 | E10: 516600 | F10: =+E10*(1+Assumptions!K27) -> 532098 | G10: =+F10*(1+Assumptions!K28) -> 548060.94 | H10: =+G10*(1+Assumptions!K29) -> 564502.77 | I10: =+H10*(1+Assumptions!K30) -> 581437.85 | J10: =+I10*(1+Assumptions!K31) -> 598880.99 | K10: =+J10*(1+Assumptions!K32) -> 616847.42 | L10: =+K10*(1+Assumptions!K33) -> 635352.84 | M10: =+L10*(1+Assumptions!K34) -> 654413.42 | N10: =+M10*(1+Assumptions!K35) -> 674045.83 | O10: =+N10*(1+Assumptions!K36) -> 694267.2 | P10: =SUM(D10:O10) -> 6818663.3
B11: 9005 | C11: Budgeted Operating Funds to Reserves | D11: =140650/12*5 -> 58604.167 | E11: 152001 | F11: =+E11*1.03 -> 156561.03 | G11: =+F11*1.03 -> 161257.86 | H11: =+G11*1.03 -> 166095.6 | I11: =+H11*1.03 -> 171078.46 | J11: =+I11*1.03 -> 176210.82 | K11: =+J11*1.03 -> 181497.14 | L11: =+K11*1.03 -> 186942.06 | M11: =+L11*1.03 -> 192550.32 | ... O11: =+N11*1.03 -> 204276.63 | P11: =SUM(D11:O11) -> 2005401.9
B12: 9031 | C12: Special Assessment - Principal | D12: =IF(Assumptions!$B$25=0,IF(ISERROR(-CUMPRINC(0.00000000001/12,Assumptions!$B$24*12,$D$4,D6,D7,0)),0,(-CUMPRINC(0.00000000001/12,Assumptions!$B$24*12,$D$4,D6,D7,0))),IF(ISERROR(-CUMPRINC(Assumptions!$B$25/12,Assumptions!$B$24*12,$D$4,D6,D7,0)),0,(-CUMPRINC(Assumptions!$B$25/12,Assumptions!$B$24*12,$D$4,D6,D7,0)))) -> 0 | E12: =IF(Assumptions!$B$25=0,IF(ISERROR(-CUMPRINC(0.00000000001/12,Assumptions!$B$24*12,$D$4,E6,E7,0)),0,(-CUMPRINC(0.00000000001/12,Assumptions!$B$24*12,$D$4,E6,E7,0))),IF(ISERROR(-CUMPRINC(Assumptions!$B$25/12,Assumptions!$B$24*12,$D$4,E6,E7,0)),0,(-CUMPRINC(Assumptions!$B$25/12,Assumptions!$B$24*12,$D$4,E6,E7,0)))) -> 0 | F12: =IF(Assumptions!$B$25=0,IF(ISERROR(-CUMPRINC(0.00000000001/12,Assumptions!$B$24*12,$D$4,F6,F7,0)),0,(-CUMPRINC(0.00000000001/12,Assumptions!$B$24*12,$D$4,F6,F7,0))),IF(ISERROR(-CUMPRINC(Assumptions!$B$25/12,Assumptions!$B$24*12,$D$4,F6,F7,0)),0,(-CUMPRINC(Assumptions!$B$25/12,Assumptions!$B$24*12,$D$4,F6,F7,0)))) -> 0 | G12: =IF(Assumptions!$B$25=0,IF(ISERROR(-CUMPRINC(0.00000000001/12,Assumptions!$B$24*12,$D$4,G6,G7,0)),0,(-CUMPRINC(0.00000000001/12,Assumptions!$B$24*12,$D$4,G6,G7,0))),IF(ISERROR(-CUMPRINC(Assumptions!$B$25/12,Assumptions!$B$24*12,$D$4,G6,G7,0)),0,(-CUMPRINC(Assumptions!$B$25/12,Assumptions!$B$24*12,$D$4,G6,G7,0)))) -> 0 | H12: =IF(Assumptions!$B$25=0,IF(ISERROR(-CUMPRINC(0.00000000001/12,Assumptions!$B$24*12,$D$4,H6,H7,0)),0,(-CUMPRINC(0.00000000001/12,Assumptions!$B$24*12,$D$4,H6,H7,0))),IF(ISERROR(-CUMPRINC(Assumptions!$B$25/12,Assumptions!$B$24*12,$D$4,H6,H7,0)),0,(-CUMPRINC(Assumptions!$B$25/12,Assumptions!$B$24*12,$D$4,H6,H7,0)))) -> 0 | I12: =IF(Assumptions!$B$25=0,IF(ISERROR(-CUMPRINC(0.00000000001/12,Assumptions!$B$24*12,$D$4,I6,I7,0)),0,(-CUMPRINC(0.00000000001/12,Assumptions!$B$24*12,$D$4,I6,I7,0))),IF(ISERROR(-CUMPRINC(Assumptions!$B$25/12,Assumptions!$B$24*12,$D$4,I6,I7,0)),0,(-CUMPRINC(Assumptions!$B$25/12,Assumptions!$B$24*12,$D$4,I6,I7,0)))) -> 0 | J12: =IF(Assumptions!$B$25=0,IF(ISERROR(-CUMPRINC(0.00000000001/12,Assumptions!$B$24*12,$D$4,J6,J7,0)),0,(-CUMPRINC(0.00000000001/12,Assumptions!$B$24*12,$D$4,J6,J7,0))),IF(ISERROR(-CUMPRINC(Assumptions!$B$25/12,Assumptions!$B$24*12,$D$4,J6,J7,0)),0,(-CUMPRINC(Assumptions!$B$25/12,Assumptions!$B$24*12,$D$4,J6,J7,0)))) -> 0 | K12: =IF(Assumptions!$B$25=0,IF(ISERROR(-CUMPRINC(0.00000000001/12,Assumptions!$B$24*12,$D$4,K6,K7,0)),0,(-CUMPRINC(0.00000000001/12,Assumptions!$B$24*12,$D$4,K6,K7,0))),IF(ISERROR(-CUMPRINC(Assumptions!$B$25/12,Assumptions!$B$24*12,$D$4,K6,K7,0)),0,(-CUMPRINC(Assumptions!$B$25/12,Assumptions!$B$24*12,$D$4,K6,K7,0)))) -> 0 | ... O12: =IF(Assumptions!$B$25=0,IF(ISERROR(-CUMPRINC(0.00000000001/12,Assumptions!$B$24*12,$D$4,O6,O7,0)),0,(-CUMPRINC(0.00000000001/12,Assumptions!$B$24*12,$D$4,O6,O7,0))),IF(ISERROR(-CUMPRINC(Assumptions!$B$25/12,Assumptions!$B$24*12,$D$4,O6,O7,0)),0,(-CUMPRINC(Assumptions!$B$25/12,Assumptions!$B$24*12,$D$4,O6,O7,0)))) -> 0 | P12: =SUM(D12:O12) -> 0
B13: 9032 | C13: Special Assessment - Interest | D13: =IF(Assumptions!$B$25=0,IF(ISERROR(-CUMIPMT(0.00000000001/12,Assumptions!$B$24*12,$D$4,D6,D7,0)),0,-CUMIPMT(0.00000000001/12,Assumptions!$B$24*12,$D$4,D6,D7,0)),IF(ISERROR(-CUMIPMT(Assumptions!$B$25/12,Assumptions!$B$24*12,$D$4,D6,D7,0)),0,-CUMIPMT(Assumptions!$B$25/12,Assumptions!$B$24*12,$D$4,D6,D7,0))) -> 0 | E13: =IF(Assumptions!$B$25=0,IF(ISERROR(-CUMIPMT(0.00000000001/12,Assumptions!$B$24*12,$D$4,E6,E7,0)),0,-CUMIPMT(0.00000000001/12,Assumptions!$B$24*12,$D$4,E6,E7,0)),IF(ISERROR(-CUMIPMT(Assumptions!$B$25/12,Assumptions!$B$24*12,$D$4,E6,E7,0)),0,-CUMIPMT(Assumptions!$B$25/12,Assumptions!$B$24*12,$D$4,E6,E7,0))) -> 0 | F13: =IF(Assumptions!$B$25=0,IF(ISERROR(-CUMIPMT(0.00000000001/12,Assumptions!$B$24*12,$D$4,F6,F7,0)),0,-CUMIPMT(0.00000000001/12,Assumptions!$B$24*12,$D$4,F6,F7,0)),IF(ISERROR(-CUMIPMT(Assumptions!$B$25/12,Assumptions!$B$24*12,$D$4,F6,F7,0)),0,-CUMIPMT(Assumptions!$B$25/12,Assumptions!$B$24*12,$D$4,F6,F7,0))) -> 0 | G13: =IF(Assumptions!$B$25=0,IF(ISERROR(-CUMIPMT(0.00000000001/12,Assumptions!$B$24*12,$D$4,G6,G7,0)),0,-CUMIPMT(0.00000000001/12,Assumptions!$B$24*12,$D$4,G6,G7,0)),IF(ISERROR(-CUMIPMT(Assumptions!$B$25/12,Assumptions!$B$24*12,$D$4,G6,G7,0)),0,-CUMIPMT(Assumptions!$B$25/12,Assumptions!$B$24*12,$D$4,G6,G7,0))) -> 0 | H13: =IF(Assumptions!$B$25=0,IF(ISERROR(-CUMIPMT(0.00000000001/12,Assumptions!$B$24*12,$D$4,H6,H7,0)),0,-CUMIPMT(0.00000000001/12,Assumptions!$B$24*12,$D$4,H6,H7,0)),IF(ISERROR(-CUMIPMT(Assumptions!$B$25/12,Assumptions!$B$24*12,$D$4,H6,H7,0)),0,-CUMIPMT(Assumptions!$B$25/12,Assumptions!$B$24*12,$D$4,H6,H7,0))) -> 0 | I13: =IF(Assumptions!$B$25=0,IF(ISERROR(-CUMIPMT(0.00000000001/12,Assumptions!$B$24*12,$D$4,I6,I7,0)),0,-CUMIPMT(0.00000000001/12,Assumptions!$B$24*12,$D$4,I6,I7,0)),IF(ISERROR(-CUMIPMT(Assumptions!$B$25/12,Assumptions!$B$24*12,$D$4,I6,I7,0)),0,-CUMIPMT(Assumptions!$B$25/12,Assumptions!$B$24*12,$D$4,I6,I7,0))) -> 0 | J13: =IF(Assumptions!$B$25=0,IF(ISERROR(-CUMIPMT(0.00000000001/12,Assumptions!$B$24*12,$D$4,J6,J7,0)),0,-CUMIPMT(0.00000000001/12,Assumptions!$B$24*12,$D$4,J6,J7,0)),IF(ISERROR(-CUMIPMT(Assumptions!$B$25/12,Assumptions!$B$24*12,$D$4,J6,J7,0)),0,-CUMIPMT(Assumptions!$B$25/12,Assumptions!$B$24*12,$D$4,J6,J7,0))) -> 0 | K13: =IF(Assumptions!$B$25=0,IF(ISERROR(-CUMIPMT(0.00000000001/12,Assumptions!$B$24*12,$D$4,K6,K7,0)),0,-CUMIPMT(0.00000000001/12,Assumptions!$B$24*12,$D$4,K6,K7,0)),IF(ISERROR(-CUMIPMT(Assumptions!$B$25/12,Assumptions!$B$24*12,$D$4,K6,K7,0)),0,-CUMIPMT(Assumptions!$B$25/12,Assumptions!$B$24*12,$D$4,K6,K7,0))) -> 0 | ... O13: =IF(Assumptions!$B$25=0,IF(ISERROR(-CUMIPMT(0.00000000001/12,Assumptions!$B$24*12,$D$4,O6,O7,0)),0,-CUMIPMT(0.00000000001/12,Assumptions!$B$24*12,$D$4,O6,O7,0)),IF(ISERROR(-CUMIPMT(Assumptions!$B$25/12,Assumptions!$B$24*12,$D$4,O6,O7,0)),0,-CUMIPMT(Assumptions!$B$25/12,Assumptions!$B$24*12,$D$4,O6,O7,0))) -> 0 | P13: =SUM(D13:O13) -> 0
B14: 9033 | C14: Allowance for Deliquency & Foreclosure | D14: =-SUM(D12:D13)*Assumptions!L25 -> 0 | E14: =-SUM(E12:E13)*Assumptions!L26 -> 0 | F14: =-SUM(F12:F13)*Assumptions!L27 -> 0 | G14: =-SUM(G12:G13)*Assumptions!L28 -> 0 | H14: =-SUM(H12:H13)*Assumptions!L29 -> 0 | I14: =-SUM(I12:I13)*Assumptions!L30 -> 0 | J14: =-SUM(J12:J13)*Assumptions!L31 -> 0 | K14: =-SUM(K12:K13)*Assumptions!L32 -> 0 | L14: =-SUM(L12:L13)*Assumptions!L33 -> 0 | M14: =-SUM(M12:M13)*Assumptions!L34 -> 0 | N14: =-SUM(N12:N13)*Assumptions!L35 -> 0 | O14: =-SUM(O12:O13)*Assumptions!L36 -> 0 | P14: =SUM(D14:O14) -> 0
B15: 9041 | C15: Loan Proceeds | D15: =IF(ISERROR(Assumptions!$B$30*Calc!B$23),0,Assumptions!$B$30*Calc!B$23) -> 0 | E15: =IF(ISERROR(Assumptions!$B$30*Calc!C$23),0,Assumptions!$B$30*Calc!C$23) -> 0 | F15: =IF(ISERROR(Assumptions!$B$30*Calc!D$23),0,Assumptions!$B$30*Calc!D$23) -> 0 | G15: =IF(ISERROR(Assumptions!$B$30*Calc!E$23),0,Assumptions!$B$30*Calc!E$23) -> 0 | H15: =IF(ISERROR(Assumptions!$B$30*Calc!F$23),0,Assumptions!$B$30*Calc!F$23) -> 0 | I15: =IF(ISERROR(Assumptions!$B$30*Calc!G$23),0,Assumptions!$B$30*Calc!G$23) -> 0 | J15: =IF(ISERROR(Assumptions!$B$30*Calc!H$23),0,Assumptions!$B$30*Calc!H$23) -> 0 | K15: =IF(ISERROR(Assumptions!$B$30*Calc!I$23),0,Assumptions!$B$30*Calc!I$23) -> 0 | ... O15: =IF(ISERROR(Assumptions!$B$30*Calc!M$23),0,Assumptions!$B$30*Calc!M$23) -> 0 | P15: =SUM(D15:O15) -> 0
B16: 9045 | C16: Reserve Interest Inc | D16: =+D247*Assumptions!J25 -> 1559.3625 | E16: =+D252*Assumptions!J26 -> 1454.0876 | F16: =+E252*Assumptions!J27 -> 4797.7562 | G16: =+F252*Assumptions!J28 -> 9795.426 | H16: =+G252*Assumptions!J29 -> -7768.4874 | I16: =+H252*Assumptions!J30 -> -37116.487 | J16: =+I252*Assumptions!J31 -> -89011.34 | K16: =+J252*Assumptions!J32 -> -107596.45 | L16: =+K252*Assumptions!J33 -> -156859.88 | M16: =+L252*Assumptions!J34 -> -175135.05 | N16: =+M252*Assumptions!J35 -> -219878.07 | O16: =+N252*Assumptions!J36 -> -212905.09 | P16: =SUM(D16:O16) -> -988664.22
C17: Total Income | D17: =SUM(D10:D16) -> 262319.53 | E17: =SUM(E10:E16) -> 670055.09 | F17: =SUM(F10:F16) -> 693456.79 | G17: =SUM(G10:G16) -> 719114.23 | H17: =SUM(H10:H16) -> 722829.88 | I17: =SUM(I10:I16) -> 715399.83 | J17: =SUM(J10:J16) -> 686080.47 | K17: =SUM(K10:K16) -> 690748.11 | ... O17: =SUM(O10:O16) -> 685638.75 | P17: =SUM(D17:O17) -> 7835400.9
D19: =+D5 -> 0 | E19: =+E5 -> 1 | F19: =+F5 -> 2 | G19: =+G5 -> 3 | H19: =+H5 -> 4 | I19: =+I5 -> 5 | J19: =+J5 -> 6 | K19: =+K5 -> 7 | ... O19: =+O5 -> 11
D20: =IF(YEAR(Assumptions!B32)>LEFT(D9,4)*1,0,1) -> 1 | E20: =+D21+1 -> 1389 | F20: =+E21+1 -> 1 | G20: =+F21+1 -> 1 | H20: =+G21+1 -> 1 | I20: =+H21+1 -> 1 | J20: =+I21+1 -> 1 | K20: =+J21+1 -> 1 | L20: =+K21+1 -> 1 | ... O20: =+N21+1 -> 1
D21: =IF(D20=0,0,ROUND(((IF(YEAR(Assumptions!D8)<YEAR(Assumptions!B32),(Assumptions!D8+365)-Assumptions!B32,Assumptions!D8-Assumptions!B32))/30),0)) -> 1388 | E21: =IF(D21=0,ROUND(((IF(YEAR(Assumptions!D8)<YEAR(Assumptions!B32),(Assumptions!D8+365)-Assumptions!B32,Assumptions!D8-Assumptions!B32))/30),0),IF(Assumptions!$B$36*12>D21+12,D21+12,Assumptions!$B$36*12)) -> 0 | F21: =IF(Assumptions!$B$36*12>E21+12,E21+12,Assumptions!$B$36*12) -> 0 | G21: =IF(Assumptions!$B$36*12>F21+12,F21+12,Assumptions!$B$36*12) -> 0 | H21: =IF(Assumptions!$B$36*12>G21+12,G21+12,Assumptions!$B$36*12) -> 0 | I21: =IF(Assumptions!$B$36*12>H21+12,H21+12,Assumptions!$B$36*12) -> 0 | J21: =IF(Assumptions!$B$36*12>I21+12,I21+12,Assumptions!$B$36*12) -> 0 | K21: =IF(Assumptions!$B$36*12>J21+12,J21+12,Assumptions!$B$36*12) -> 0 | L21: =IF(Assumptions!$B$36*12>K21+12,K21+12,Assumptions!$B$36*12) -> 0 | M21: =IF(Assumptions!$B$36*12>L21+12,L21+12,Assumptions!$B$36*12) -> 0 | ... O21: =IF(Assumptions!$B$36*12>N21+12,N21+12,Assumptions!$B$36*12) -> 0
A23: EXPENSES | B23: GL | C23: Name | D23: =+D9 -> 2013 Budget | E23: =+E9 -> 2014 | F23: =+F9 -> 2015 | G23: =+G9 -> 2016 | H23: =+H9 -> 2017 | I23: =+I9 -> 2018 | J23: =+J9 -> 2019 | K23: =+K9 -> 2020 | ... M23: =+M9 -> 2022 | N23: =+M23+1 -> 2023 | O23: =+N23+1 -> 2024 | P23: Total
C24: Sitework Elements | P24: 0
C25: East Entry Street Asphalt Pavement | P25: =IF(SUM(D25:O25)=0,0,SUM(D25:O25)) -> 0
C26: East Entry Street Asphalt Sealcoating | P26: =IF(SUM(D26:O26)=0,0,SUM(D26:O26)) -> 0
C27: West Entry Street Asphalt Pavement | P27: =IF(SUM(D27:O27)=0,0,SUM(D27:O27)) -> 0
C28: West Entry Street Asphalt Sealcoating | P28: =IF(SUM(D28:O28)=0,0,SUM(D28:O28)) -> 0
C29: East, South, & West Central Road Pavement | P29: =IF(SUM(D29:O29)=0,0,SUM(D29:O29)) -> 0
C30: East, South, & West Central Road Sealcoating | P30: =IF(SUM(D30:O30)=0,0,SUM(D30:O30)) -> 0
C31: Asphalt Fire Lane Pavement (Grind and Resurface) | I31: 1023820 | P31: =IF(SUM(D31:O31)=0,0,SUM(D31:O31)) -> 1023820
C32: Asphalt Fire Lane Pavement Sealcoating | K32: 46150 | P32: =IF(SUM(D32:O32)=0,0,SUM(D32:O32)) -> 46150
C33: Asphalt Parking Lot Pavement | E33: 120000 | J33: 384660 | K33: 571410 | L33: 134413 | M33: 457398 | N33: 0 | P33: =IF(SUM(D33:O33)=0,0,SUM(D33:O33)) -> 1667881
C34: Asphalt Parking Lot Sealcoating | P34: =IF(SUM(D34:O34)=0,0,SUM(D34:O34)) -> 0
C35: Ramp Asphalt Pavement (Grind and Resurface) | J35: 50460 | P35: =IF(SUM(D35:O35)=0,0,SUM(D35:O35)) -> 50460
C36: Ramp Asphalt Sealcoating | P36: =IF(SUM(D36:O36)=0,0,SUM(D36:O36)) -> 0
C37: Street Concrete Curbs | P37: =IF(SUM(D37:O37)=0,0,SUM(D37:O37)) -> 0
C38: Parking Lot Concrete Curbs | P38: =IF(SUM(D38:O38)=0,0,SUM(D38:O38)) -> 0
C39: Ramp Concrete Curbs | P39: =IF(SUM(D39:O39)=0,0,SUM(D39:O39)) -> 0
C40: Aggregate 5'-0" Walkway | P40: =IF(SUM(D40:O40)=0,0,SUM(D40:O40)) -> 0
C41: Storm Sewer System | M41: 30445 | P41: =IF(SUM(D41:O41)=0,0,SUM(D41:O41)) -> 30445
C42: Concrete Entry Walk (Clubhouse) | P42: =IF(SUM(D42:O42)=0,0,SUM(D42:O42)) -> 0
C43: Rear Concrete Walks | E43: 27835 | P43: =IF(SUM(D43:O43)=0,0,SUM(D43:O43)) -> 27835
C44: Brick Paver Entry Walks (Bldgs. 1405, 1515, 1605, & 1615) | P44: =IF(SUM(D44:O44)=0,0,SUM(D44:O44)) -> 0
C45: Brick Paver Entry Walks (Bldgs. 1415 & 1505) | P45: =IF(SUM(D45:O45)=0,0,SUM(D45:O45)) -> 0
C46: Stone Paver Walks (Concrete) | P46: =IF(SUM(D46:O46)=0,0,SUM(D46:O46)) -> 0
C47: Concrete Trash Pads | N47: 30456 | P47: =IF(SUM(D47:O47)=0,0,SUM(D47:O47)) -> 30456
C48: Split Rail Fence | P48: =IF(SUM(D48:O48)=0,0,SUM(D48:O48)) -> 0
C49: Chain Link Fence at SW (5') | P49: =IF(SUM(D49:O49)=0,0,SUM(D49:O49)) -> 0
C50: Chain Link Fence (6') | P50: =IF(SUM(D50:O50)=0,0,SUM(D50:O50)) -> 0
C51: Patio Aluminum Fence | P51: =IF(SUM(D51:O51)=0,0,SUM(D51:O51)) -> 0
C52: Concrete Retaining Walls | P52: =IF(SUM(D52:O52)=0,0,SUM(D52:O52)) -> 0
C53: Ramp Trench Drains | N53: 41516 | P53: =IF(SUM(D53:O53)=0,0,SUM(D53:O53)) -> 41516
C54: Patios | P54: =IF(SUM(D54:O54)=0,0,SUM(D54:O54)) -> 0
C55: Entry Monuments | H55: 2076 | P55: =IF(SUM(D55:O55)=0,0,SUM(D55:O55)) -> 2076
C56: Chain Link Fence (6' at 1605 S Line) | P56: =IF(SUM(D56:O56)=0,0,SUM(D56:O56)) -> 0
C57: Waterproofing Elements | P57: =IF(SUM(D57:O57)=0,0,SUM(D57:O57)) -> 0
C58: Metal Fascia (1505 A & B Wings) | P58: =IF(SUM(D58:O58)=0,0,SUM(D58:O58)) -> 0
C59: Shingle Roofing (Clubhouse) | E59: 5175 | P59: =IF(SUM(D59:O59)=0,0,SUM(D59:O59)) -> 5175
C60: Flat Roofing (Clubhouse) | P60: =IF(SUM(D60:O60)=0,0,SUM(D60:O60)) -> 0
C61: Roofing (1415 A Wing) | P61: =IF(SUM(D61:O61)=0,0,SUM(D61:O61)) -> 0
C62: Roofing (1405, 1415, 1505, 1515, 1605 & 1605 Core Bldgs.) | D62: 26826 | P62: =IF(SUM(D62:O62)=0,0,SUM(D62:O62)) -> 26826
C63: Roofing (1605 B Wing) | H63: 14465 | P63: =IF(SUM(D63:O63)=0,0,SUM(D63:O63)) -> 14465
C64: Roofing (1415 C & 1605 A Wings) | G64: 28930 | P64: =IF(SUM(D64:O64)=0,0,SUM(D64:O64)) -> 28930
C65: Roofing (1405 A & B, & 1405 C Wings) | I65: 43395 | P65: =IF(SUM(D65:O65)=0,0,SUM(D65:O65)) -> 43395
C66: Roofing (1515 B, 1515 A & C Wings) | J66: 43395 | P66: =IF(SUM(D66:O66)=0,0,SUM(D66:O66)) -> 43395
C67: Roofing (1515 A & C, 1615 B Wings) | K67: 43395 | P67: =IF(SUM(D67:O67)=0,0,SUM(D67:O67)) -> 43395
C68: Roofing (1505 A & B Wings) | L68: 28930 | P68: =IF(SUM(D68:O68)=0,0,SUM(D68:O68)) -> 28930
C69: Roofing (1415 B & 1605 C Wings) | P69: =IF(SUM(D69:O69)=0,0,SUM(D69:O69)) -> 0
C70: Gutters and Downspouts (Clubhouse) | P70: =IF(SUM(D70:O70)=0,0,SUM(D70:O70)) -> 0
C71: Gutters and Downspouts (Bldg. 1505) | P71: =IF(SUM(D71:O71)=0,0,SUM(D71:O71)) -> 0
C72: Gutters and Downspouts (Bldg. 1405) | P72: =IF(SUM(D72:O72)=0,0,SUM(D72:O72)) -> 0
C73: Gutters and Downspouts (Bldgs. 1415, 1515, 1605, & 1615) | P73: =IF(SUM(D73:O73)=0,0,SUM(D73:O73)) -> 0
C74: Skylights (Clubhouse) | H74: 1910 | P74: =IF(SUM(D74:O74)=0,0,SUM(D74:O74)) -> 1910
C75: Metal Fascia (1515 A & C, & 1615 B Wings) | P75: =IF(SUM(D75:O75)=0,0,SUM(D75:O75)) -> 0
C76: Metal Fascia (1515 B, & 1615 A & C Wings) | O76: 7326 | P76: =IF(SUM(D76:O76)=0,0,SUM(D76:O76)) -> 7326
C77: Metal Fascia (1405 A, B & C Wings) | N77: 7326 | P77: =IF(SUM(D77:O77)=0,0,SUM(D77:O77)) -> 7326
C78: Metal Fascia (1605 B Wing) | M78: 2442 | P78: =IF(SUM(D78:O78)=0,0,SUM(D78:O78)) -> 2442
C79: Metal Fascia (1415 C & 1605 A Wings) | L79: 4884 | P79: =IF(SUM(D79:O79)=0,0,SUM(D79:O79)) -> 4884
C80: Metal Fascia (1415 A Wing) | H80: 2442 | P80: =IF(SUM(D80:O80)=0,0,SUM(D80:O80)) -> 2442
C81: Metal Fascia (1415 B & 1605 C Wings) | P81: =IF(SUM(D81:O81)=0,0,SUM(D81:O81)) -> 0
C82: Brick Waterproofing (Bldgs. 1405, 1415, 1505, & 1515) | I82: 251600 | P82: =IF(SUM(D82:O82)=0,0,SUM(D82:O82)) -> 251600
C83: Brick Waterproofing (Bldg. 1605) | L83: 56240 | P83: =IF(SUM(D83:O83)=0,0,SUM(D83:O83)) -> 56240
C84: Brick Waterproofing (Bldg. 1615) | N84: 56240 | P84: =IF(SUM(D84:O84)=0,0,SUM(D84:O84)) -> 56240
C85: Interior Finishes Elements | P85: =IF(SUM(D85:O85)=0,0,SUM(D85:O85)) -> 0
C86: Wing and Lobby Carpet | G86: 284095 | P86: =IF(SUM(D86:O86)=0,0,SUM(D86:O86)) -> 284095
C87: Core Ceramic Tile | L87: 186440 | P87: =IF(SUM(D87:O87)=0,0,SUM(D87:O87)) -> 186440
C88: Core Wallcovering | G88: 87561 | P88: =IF(SUM(D88:O88)=0,0,SUM(D88:O88)) -> 87561
C89: Interior Window Wall | M89: 69190 | P89: =IF(SUM(D89:O89)=0,0,SUM(D89:O89)) -> 69190
C90: Mirrors | M90: 24907 | P90: =IF(SUM(D90:O90)=0,0,SUM(D90:O90)) -> 24907
C91: Lobby Furniture | P91: =IF(SUM(D91:O91)=0,0,SUM(D91:O91)) -> 0
C92: Artwork | P92: =IF(SUM(D92:O92)=0,0,SUM(D92:O92)) -> 0
C93: Vestibule Flooring | K93: 8303 | P93: =IF(SUM(D93:O93)=0,0,SUM(D93:O93)) -> 8303
C94: Acoustical Tile Ceilings | F94: 57222 | P94: =IF(SUM(D94:O94)=0,0,SUM(D94:O94)) -> 57222
C95: Laundry Room Flooring | D95: 17305 | N95: 17305 | P95: =IF(SUM(D95:O95)=0,0,SUM(D95:O95)) -> 34610
C96: Social Room Carpet | K96: 21075 | P96: =IF(SUM(D96:O96)=0,0,SUM(D96:O96)) -> 21075
C97: Social Room Sliding Doors | P97: =IF(SUM(D97:O97)=0,0,SUM(D97:O97)) -> 0
C98: Social Room Furniture | P98: =IF(SUM(D98:O98)=0,0,SUM(D98:O98)) -> 0
C99: Carpet (Clubhouse) | J99: 6326 | P99: =IF(SUM(D99:O99)=0,0,SUM(D99:O99)) -> 6326
C100: Ceramic Tile (Clubhouse) | P100: =IF(SUM(D100:O100)=0,0,SUM(D100:O100)) -> 0
C101: Toilet Partitions | I101: 2491 | P101: =IF(SUM(D101:O101)=0,0,SUM(D101:O101)) -> 2491
C102: Showers | D102: 5536 | P102: =IF(SUM(D102:O102)=0,0,SUM(D102:O102)) -> 5536
C103: Saunas | H103: 30445 | P103: =IF(SUM(D103:O103)=0,0,SUM(D103:O103)) -> 30445
C104: Plumbing Fixtures | D104: 19500 | F104: 3875 | P104: =IF(SUM(D104:O104)=0,0,SUM(D104:O104)) -> 23375
...

Sheet Option 2
B1: =Assumptions!D5&" - Reserve & Special Assessment Analysis Option 2" -> Dana Point - Reserve & Special Assessment Analysis Option 2
B2: =+Assumptions!D7&" Reserve Study 10-Year Projection" -> 2013 Reserve Study 10-Year Projection
C4: Special Assessment | D4: =Assumptions!C21 -> 0
E5: =IF(YEAR(Assumptions!$D8)<YEAR(Assumptions!C22),0,1) -> 1 | F5: =+E5+1 -> 2 | G5: =+F5+1 -> 3 | H5: =+G5+1 -> 4 | I5: =+H5+1 -> 5 | J5: =+I5+1 -> 6 | K5: =+J5+1 -> 7 | L5: =+K5+1 -> 8 | M5: =+L5+1 -> 9 | ... O5: =+N5+1 -> 11
D6: =IF(YEAR(Assumptions!C22)>LEFT(D9,4)*1,0,1) -> 1 | E6: =+D7+1 -> 1389 | F6: =+E7+1 -> 1 | G6: =+F7+1 -> 1 | H6: =+G7+1 -> 1 | I6: =+H7+1 -> 1 | J6: =+I7+1 -> 1 | K6: =+J7+1 -> 1 | L6: =+K7+1 -> 1 | ... O6: =+N7+1 -> 1
D7: =IF(D6=0,0,ROUND(((IF(YEAR(Assumptions!D8)<YEAR(Assumptions!C22),(Assumptions!D8+365)-Assumptions!C22,Assumptions!D8-Assumptions!C22))/30),0)) -> 1388 | E7: =IF(D7=0,ROUND(((IF(YEAR(Assumptions!D8)<YEAR(Assumptions!C22),(Assumptions!D8+365)-Assumptions!C22,Assumptions!D8-Assumptions!C22))/30),0),IF(Assumptions!$C$24*12>D7+12,D7+12,Assumptions!$C$24*12)) -> 0 | F7: =IF(Assumptions!$C$24*12>E7+12,E7+12,Assumptions!$C$24*12) -> 0 | G7: =IF(Assumptions!$C$24*12>F7+12,F7+12,Assumptions!$C$24*12) -> 0 | H7: =IF(Assumptions!$C$24*12>G7+12,G7+12,Assumptions!$C$24*12) -> 0 | I7: =IF(Assumptions!$C$24*12>H7+12,H7+12,Assumptions!$C$24*12) -> 0 | J7: =IF(Assumptions!$C$24*12>I7+12,I7+12,Assumptions!$C$24*12) -> 0 | K7: =IF(Assumptions!$C$24*12>J7+12,J7+12,Assumptions!$C$24*12) -> 0 | L7: =IF(Assumptions!$C$24*12>K7+12,K7+12,Assumptions!$C$24*12) -> 0 | M7: =IF(Assumptions!$C$24*12>L7+12,L7+12,Assumptions!$C$24*12) -> 0 | ... O7: =IF(Assumptions!$C$24*12>N7+12,N7+12,Assumptions!$C$24*12) -> 0
A9: INCOME | B9: GL | C9: Name | D9: =Assumptions!D7&" Budget" -> 2013 Budget | E9: =+Assumptions!D7+1 -> 2014 | F9: =+E9+1 -> 2015 | G9: =+F9+1 -> 2016 | H9: =+G9+1 -> 2017 | I9: =+H9+1 -> 2018 | J9: =+I9+1 -> 2019 | K9: =+J9+1 -> 2020 | L9: =+K9+1 -> 2021 | M9: =+L9+1 -> 2022 | ... O9: =+N9+1 -> 2024 | P9: TOTAL
B10: 9001 | C10: Budgeted Operating Funds to Reserves | D10: =ROUND((+Assumptions!D10/12*Calc!$G$9),0) -> 202156 | E10: =+(Assumptions!D10)*(1+Assumptions!K26) -> 499729.22 | F10: =+E10*(1+Assumptions!K27) -> 514721.1 | G10: =+F10*(1+Assumptions!K28) -> 530162.73 | H10: =+G10*(1+Assumptions!K29) -> 546067.61 | I10: =+H10*(1+Assumptions!K30) -> 562449.64 | J10: =+I10*(1+Assumptions!K31) -> 579323.13 | K10: =+J10*(1+Assumptions!K32) -> 596702.82 | L10: =+K10*(1+Assumptions!K33) -> 614603.91 | M10: =+L10*(1+Assumptions!K34) -> 633042.02 | N10: =+M10*(1+Assumptions!K35) -> 652033.29 | O10: =+N10*(1+Assumptions!K36) -> 671594.28 | P10: =SUM(D10:O10) -> 6602585.8
B11: 9005 | C11: Budgeted Operating Funds to Reserves | D11: =+'Option 1'!D11 -> 58604.167 | E11: =+'Option 1'!E11 -> 152001 | F11: =+'Option 1'!F11 -> 156561.03 | G11: =+'Option 1'!G11 -> 161257.86 | H11: =+'Option 1'!H11 -> 166095.6 | I11: =+'Option 1'!I11 -> 171078.46 | J11: =+'Option 1'!J11 -> 176210.82 | K11: =+'Option 1'!K11 -> 181497.14 | ... O11: =+'Option 1'!O11 -> 204276.63 | P11: =SUM(D11:O11) -> 2005401.9
B12: 9031 | C12: Special Assessment - Principal | D12: =IF(Assumptions!$C$25=0,IF(ISERROR(-CUMPRINC(0.00000000001/12,Assumptions!$C$24*12,$D$4,D6,D7,0)),0,(-CUMPRINC(0.00000000001/12,Assumptions!$C$24*12,$D$4,D6,D7,0))),IF(ISERROR(-CUMPRINC(Assumptions!$C$25/12,Assumptions!$C$24*12,$D$4,D6,D7,0)),0,(-CUMPRINC(Assumptions!$C$25/12,Assumptions!$C$24*12,$D$4,D6,D7,0)))) -> 0 | E12: =IF(Assumptions!$C$25=0,IF(ISERROR(-CUMPRINC(0.00000000001/12,Assumptions!$C$24*12,$D$4,E6,E7,0)),0,(-CUMPRINC(0.00000000001/12,Assumptions!$C$24*12,$D$4,E6,E7,0))),IF(ISERROR(-CUMPRINC(Assumptions!$C$25/12,Assumptions!$C$24*12,$D$4,E6,E7,0)),0,(-CUMPRINC(Assumptions!$C$25/12,Assumptions!$C$24*12,$D$4,E6,E7,0)))) -> 0 | F12: =IF(Assumptions!$C$25=0,IF(ISERROR(-CUMPRINC(0.00000000001/12,Assumptions!$C$24*12,$D$4,F6,F7,0)),0,(-CUMPRINC(0.00000000001/12,Assumptions!$C$24*12,$D$4,F6,F7,0))),IF(ISERROR(-CUMPRINC(Assumptions!$C$25/12,Assumptions!$C$24*12,$D$4,F6,F7,0)),0,(-CUMPRINC(Assumptions!$C$25/12,Assumptions!$C$24*12,$D$4,F6,F7,0)))) -> 0 | G12: =IF(Assumptions!$C$25=0,IF(ISERROR(-CUMPRINC(0.00000000001/12,Assumptions!$C$24*12,$D$4,G6,G7,0)),0,(-CUMPRINC(0.00000000001/12,Assumptions!$C$24*12,$D$4,G6,G7,0))),IF(ISERROR(-CUMPRINC(Assumptions!$C$25/12,Assumptions!$C$24*12,$D$4,G6,G7,0)),0,(-CUMPRINC(Assumptions!$C$25/12,Assumptions!$C$24*12,$D$4,G6,G7,0)))) -> 0 | H12: =IF(Assumptions!$C$25=0,IF(ISERROR(-CUMPRINC(0.00000000001/12,Assumptions!$C$24*12,$D$4,H6,H7,0)),0,(-CUMPRINC(0.00000000001/12,Assumptions!$C$24*12,$D$4,H6,H7,0))),IF(ISERROR(-CUMPRINC(Assumptions!$C$25/12,Assumptions!$C$24*12,$D$4,H6,H7,0)),0,(-CUMPRINC(Assumptions!$C$25/12,Assumptions!$C$24*12,$D$4,H6,H7,0)))) -> 0 | I12: =IF(Assumptions!$C$25=0,IF(ISERROR(-CUMPRINC(0.00000000001/12,Assumptions!$C$24*12,$D$4,I6,I7,0)),0,(-CUMPRINC(0.00000000001/12,Assumptions!$C$24*12,$D$4,I6,I7,0))),IF(ISERROR(-CUMPRINC(Assumptions!$C$25/12,Assumptions!$C$24*12,$D$4,I6,I7,0)),0,(-CUMPRINC(Assumptions!$C$25/12,Assumptions!$C$24*12,$D$4,I6,I7,0)))) -> 0 | J12: =IF(Assumptions!$C$25=0,IF(ISERROR(-CUMPRINC(0.00000000001/12,Assumptions!$C$24*12,$D$4,J6,J7,0)),0,(-CUMPRINC(0.00000000001/12,Assumptions!$C$24*12,$D$4,J6,J7,0))),IF(ISERROR(-CUMPRINC(Assumptions!$C$25/12,Assumptions!$C$24*12,$D$4,J6,J7,0)),0,(-CUMPRINC(Assumptions!$C$25/12,Assumptions!$C$24*12,$D$4,J6,J7,0)))) -> 0 | K12: =IF(Assumptions!$C$25=0,IF(ISERROR(-CUMPRINC(0.00000000001/12,Assumptions!$C$24*12,$D$4,K6,K7,0)),0,(-CUMPRINC(0.00000000001/12,Assumptions!$C$24*12,$D$4,K6,K7,0))),IF(ISERROR(-CUMPRINC(Assumptions!$C$25/12,Assumptions!$C$24*12,$D$4,K6,K7,0)),0,(-CUMPRINC(Assumptions!$C$25/12,Assumptions!$C$24*12,$D$4,K6,K7,0)))) -> 0 | ... O12: =IF(Assumptions!$C$25=0,IF(ISERROR(-CUMPRINC(0.00000000001/12,Assumptions!$C$24*12,$D$4,O6,O7,0)),0,(-CUMPRINC(0.00000000001/12,Assumptions!$C$24*12,$D$4,O6,O7,0))),IF(ISERROR(-CUMPRINC(Assumptions!$C$25/12,Assumptions!$C$24*12,$D$4,O6,O7,0)),0,(-CUMPRINC(Assumptions!$C$25/12,Assumptions!$C$24*12,$D$4,O6,O7,0)))) -> 0 | P12: =SUM(D12:O12) -> 0
B13: 9032 | C13: Special Assessment - Interest | D13: =IF(Assumptions!$C$25=0,IF(ISERROR(-CUMIPMT(0.00000000001/12,Assumptions!$C$24*12,$D$4,D6,D7,0)),0,-CUMIPMT(0.00000000001/12,Assumptions!$C$24*12,$D$4,D6,D7,0)),IF(ISERROR(-CUMIPMT(Assumptions!$C$25/12,Assumptions!$C$24*12,$D$4,D6,D7,0)),0,-CUMIPMT(Assumptions!$C$25/12,Assumptions!$C$24*12,$D$4,D6,D7,0))) -> 0 | E13: =IF(Assumptions!$C$25=0,IF(ISERROR(-CUMIPMT(0.00000000001/12,Assumptions!$C$24*12,$D$4,E6,E7,0)),0,-CUMIPMT(0.00000000001/12,Assumptions!$C$24*12,$D$4,E6,E7,0)),IF(ISERROR(-CUMIPMT(Assumptions!$C$25/12,Assumptions!$C$24*12,$D$4,E6,E7,0)),0,-CUMIPMT(Assumptions!$C$25/12,Assumptions!$C$24*12,$D$4,E6,E7,0))) -> 0 | F13: =IF(Assumptions!$C$25=0,IF(ISERROR(-CUMIPMT(0.00000000001/12,Assumptions!$C$24*12,$D$4,F6,F7,0)),0,-CUMIPMT(0.00000000001/12,Assumptions!$C$24*12,$D$4,F6,F7,0)),IF(ISERROR(-CUMIPMT(Assumptions!$C$25/12,Assumptions!$C$24*12,$D$4,F6,F7,0)),0,-CUMIPMT(Assumptions!$C$25/12,Assumptions!$C$24*12,$D$4,F6,F7,0))) -> 0 | G13: =IF(Assumptions!$C$25=0,IF(ISERROR(-CUMIPMT(0.00000000001/12,Assumptions!$C$24*12,$D$4,G6,G7,0)),0,-CUMIPMT(0.00000000001/12,Assumptions!$C$24*12,$D$4,G6,G7,0)),IF(ISERROR(-CUMIPMT(Assumptions!$C$25/12,Assumptions!$C$24*12,$D$4,G6,G7,0)),0,-CUMIPMT(Assumptions!$C$25/12,Assumptions!$C$24*12,$D$4,G6,G7,0))) -> 0 | H13: =IF(Assumptions!$C$25=0,IF(ISERROR(-CUMIPMT(0.00000000001/12,Assumptions!$C$24*12,$D$4,H6,H7,0)),0,-CUMIPMT(0.00000000001/12,Assumptions!$C$24*12,$D$4,H6,H7,0)),IF(ISERROR(-CUMIPMT(Assumptions!$C$25/12,Assumptions!$C$24*12,$D$4,H6,H7,0)),0,-CUMIPMT(Assumptions!$C$25/12,Assumptions!$C$24*12,$D$4,H6,H7,0))) -> 0 | I13: =IF(Assumptions!$C$25=0,IF(ISERROR(-CUMIPMT(0.00000000001/12,Assumptions!$C$24*12,$D$4,I6,I7,0)),0,-CUMIPMT(0.00000000001/12,Assumptions!$C$24*12,$D$4,I6,I7,0)),IF(ISERROR(-CUMIPMT(Assumptions!$C$25/12,Assumptions!$C$24*12,$D$4,I6,I7,0)),0,-CUMIPMT(Assumptions!$C$25/12,Assumptions!$C$24*12,$D$4,I6,I7,0))) -> 0 | J13: =IF(Assumptions!$C$25=0,IF(ISERROR(-CUMIPMT(0.00000000001/12,Assumptions!$C$24*12,$D$4,J6,J7,0)),0,-CUMIPMT(0.00000000001/12,Assumptions!$C$24*12,$D$4,J6,J7,0)),IF(ISERROR(-CUMIPMT(Assumptions!$C$25/12,Assumptions!$C$24*12,$D$4,J6,J7,0)),0,-CUMIPMT(Assumptions!$C$25/12,Assumptions!$C$24*12,$D$4,J6,J7,0))) -> 0 | K13: =IF(Assumptions!$C$25=0,IF(ISERROR(-CUMIPMT(0.00000000001/12,Assumptions!$C$24*12,$D$4,K6,K7,0)),0,-CUMIPMT(0.00000000001/12,Assumptions!$C$24*12,$D$4,K6,K7,0)),IF(ISERROR(-CUMIPMT(Assumptions!$C$25/12,Assumptions!$C$24*12,$D$4,K6,K7,0)),0,-CUMIPMT(Assumptions!$C$25/12,Assumptions!$C$24*12,$D$4,K6,K7,0))) -> 0 | ... O13: =IF(Assumptions!$C$25=0,IF(ISERROR(-CUMIPMT(0.00000000001/12,Assumptions!$C$24*12,$D$4,O6,O7,0)),0,-CUMIPMT(0.00000000001/12,Assumptions!$C$24*12,$D$4,O6,O7,0)),IF(ISERROR(-CUMIPMT(Assumptions!$C$25/12,Assumptions!$C$24*12,$D$4,O6,O7,0)),0,-CUMIPMT(Assumptions!$C$25/12,Assumptions!$C$24*12,$D$4,O6,O7,0))) -> 0 | P13: =SUM(D13:O13) -> 0
B14: 9033 | C14: Allowance for Deliquency & Foreclosure | D14: =-SUM(D12:D13)*Assumptions!L25 -> 0 | E14: =-SUM(E12:E13)*Assumptions!L26 -> 0 | F14: =-SUM(F12:F13)*Assumptions!L27 -> 0 | G14: =-SUM(G12:G13)*Assumptions!L28 -> 0 | H14: =-SUM(H12:H13)*Assumptions!L29 -> 0 | I14: =-SUM(I12:I13)*Assumptions!L30 -> 0 | J14: =-SUM(J12:J13)*Assumptions!L31 -> 0 | K14: =-SUM(K12:K13)*Assumptions!L32 -> 0 | L14: =-SUM(L12:L13)*Assumptions!L33 -> 0 | M14: =-SUM(M12:M13)*Assumptions!L34 -> 0 | N14: =-SUM(N12:N13)*Assumptions!L35 -> 0 | O14: =-SUM(O12:O13)*Assumptions!L36 -> 0 | P14: =SUM(D14:O14) -> 0
B15: 9041 | C15: Loan Proceeds | D15: =IF(ISERROR(Assumptions!$C$30*Calc!B$46),0,Assumptions!$C$30*Calc!B$46) -> 0 | E15: =IF(ISERROR(Assumptions!$C$30*Calc!C$46),0,Assumptions!$C$30*Calc!C$46) -> 0 | F15: =IF(ISERROR(Assumptions!$C$30*Calc!D$46),0,Assumptions!$C$30*Calc!D$46) -> 0 | G15: =IF(ISERROR(Assumptions!$C$30*Calc!E$46),0,Assumptions!$C$30*Calc!E$46) -> 0 | H15: =IF(ISERROR(Assumptions!$C$30*Calc!F$46),0,Assumptions!$C$30*Calc!F$46) -> 0 | I15: =IF(ISERROR(Assumptions!$C$30*Calc!G$46),0,Assumptions!$C$30*Calc!G$46) -> 1500000 | J15: =IF(ISERROR(Assumptions!$C$30*Calc!H$46),0,Assumptions!$C$30*Calc!H$46) -> 0 | K15: =IF(ISERROR(Assumptions!$C$30*Calc!I$46),0,Assumptions!$C$30*Calc!I$46) -> 0 | ... O15: =IF(ISERROR(Assumptions!$C$30*Calc!M$46),0,Assumptions!$C$30*Calc!M$46) -> 0 | P15: =SUM(D15:O15) -> 1500000
B16: 9045 | C16: Reserve Interest Inc | D16: =+D247*Assumptions!J25 -> 1559.3625 | E16: =+D252*Assumptions!J26 -> 1454.0876 | F16: =+E252*Assumptions!J27 -> 4629.0484 | G16: =+F252*Assumptions!J28 -> 9279.1802 | H16: =+G252*Assumptions!J29 -> -8825.1044 | I16: =+H252*Assumptions!J30 -> -38924.553 | J16: =+I252*Assumptions!J31 -> -46804.907 | K16: =+J252*Assumptions!J32 -> -65206.547 | L16: =+K252*Assumptions!J33 -> -116260.06 | M16: =+L252*Assumptions!J34 -> -138394.49 | N16: =+M252*Assumptions!J35 -> -189206.25 | O16: =+N252*Assumptions!J36 -> -192719.79 | P16: =SUM(D16:O16) -> -779420.03
C17: Total Income | D17: =SUM(D10:D16) -> 262319.53 | E17: =SUM(E10:E16) -> 653184.31 | F17: =SUM(F10:F16) -> 675911.17 | G17: =SUM(G10:G16) -> 700699.77 | H17: =SUM(H10:H16) -> 703338.1 | I17: =SUM(I10:I16) -> 2194603.6 | J17: =SUM(J10:J16) -> 708729.04 | K17: =SUM(K10:K16) -> 712993.42 | ... O17: =SUM(O10:O16) -> 683151.13 | P17: =SUM(D17:O17) -> 9328567.6
D19: =+D5 -> 0 | E19: =+E5 -> 1 | F19: =+F5 -> 2 | G19: =+G5 -> 3 | H19: =+H5 -> 4 | I19: =+I5 -> 5 | J19: =+J5 -> 6 | K19: =+K5 -> 7 | ... O19: =+O5 -> 11
D20: =IF(YEAR(Assumptions!C32)>LEFT(D9,4)*1,0,1) -> 0 | E20: =+D21+1 -> 1 | F20: =+E21+1 -> -36 | G20: =+F21+1 -> -24 | H20: =+G21+1 -> -12 | I20: =+H21+1 -> 0 | J20: =+I21+1 -> 12 | K20: =+J21+1 -> 24 | L20: =+K21+1 -> 36 | ... O20: =+N21+1 -> 72
D21: =IF(D20=0,0,ROUND(((IF(YEAR(Assumptions!D8)<YEAR(Assumptions!C32),(Assumptions!D8+365)-Assumptions!C32,Assumptions!D8-Assumptions!C32))/30),0)) -> 0 | E21: =IF(D21=0,ROUND(((IF(YEAR(Assumptions!D8)<YEAR(Assumptions!C32),(Assumptions!D8+365)-Assumptions!C32,Assumptions!D8-Assumptions!C32))/30),0),IF(Assumptions!$C$36*12>D21+12,D21+12,Assumptions!$C$36*12)) -> -37 | F21: =IF(Assumptions!$C$36*12>E21+12,E21+12,Assumptions!$C$36*12) -> -25 | G21: =IF(Assumptions!$C$36*12>F21+12,F21+12,Assumptions!$C$36*12) -> -13 | H21: =IF(Assumptions!$C$36*12>G21+12,G21+12,Assumptions!$C$36*12) -> -1 | I21: =IF(Assumptions!$C$36*12>H21+12,H21+12,Assumptions!$C$36*12) -> 11 | J21: =IF(Assumptions!$C$36*12>I21+12,I21+12,Assumptions!$C$36*12) -> 23 | K21: =IF(Assumptions!$C$36*12>J21+12,J21+12,Assumptions!$C$36*12) -> 35 | L21: =IF(Assumptions!$C$36*12>K21+12,K21+12,Assumptions!$C$36*12) -> 47 | M21: =IF(Assumptions!$C$36*12>L21+12,L21+12,Assumptions!$C$36*12) -> 59 | ... O21: =IF(Assumptions!$C$36*12>N21+12,N21+12,Assumptions!$C$36*12) -> 83
A23: EXPENSES | B23: GL | C23: Name | D23: =+D9 -> 2013 Budget | E23: =+E9 -> 2014 | F23: =+F9 -> 2015 | G23: =+G9 -> 2016 | H23: =+H9 -> 2017 | I23: =+I9 -> 2018 | J23: =+J9 -> 2019 | K23: =+K9 -> 2020 | ... M23: =+M9 -> 2022 | N23: =+M23+1 -> 2023 | O23: =+N23+1 -> 2024 | P23: Total
B24: =IF('Option 1'!B24="","",'Option 1'!B24) | C24: =IF('Option 1'!C24="","",'Option 1'!C24) -> Sitework Elements | D24: =IF('Option 1'!D24="","",'Option 1'!D24) | E24: =IF('Option 1'!E24="","",'Option 1'!E24) | F24: =IF('Option 1'!F24="","",'Option 1'!F24) | G24: =IF('Option 1'!G24="","",'Option 1'!G24) | H24: =IF('Option 1'!H24="","",'Option 1'!H24) | I24: =IF('Option 1'!I24="","",'Option 1'!I24) | ... O24: =IF('Option 1'!O24="","",'Option 1'!O24) | P24: =IF(SUM(D24:O24)=0,0,SUM(D24:O24)) -> 0
B25: =IF('Option 1'!B25="","",'Option 1'!B25) | C25: =IF('Option 1'!C25="","",'Option 1'!C25) -> East Entry Street Asphalt Pavement | D25: =IF('Option 1'!D25="","",'Option 1'!D25) | E25: =IF('Option 1'!E25="","",'Option 1'!E25) | F25: =IF('Option 1'!F25="","",'Option 1'!F25) | G25: =IF('Option 1'!G25="","",'Option 1'!G25) | H25: =IF('Option 1'!H25="","",'Option 1'!H25) | I25: =IF('Option 1'!I25="","",'Option 1'!I25) | ... O25: =IF('Option 1'!O25="","",'Option 1'!O25) | P25: =IF(SUM(D25:O25)=0,0,SUM(D25:O25)) -> 0
B26: =IF('Option 1'!B26="","",'Option 1'!B26) | C26: =IF('Option 1'!C26="","",'Option 1'!C26) -> East Entry Street Asphalt Sealcoating | D26: =IF('Option 1'!D26="","",'Option 1'!D26) | E26: =IF('Option 1'!E26="","",'Option 1'!E26) | F26: =IF('Option 1'!F26="","",'Option 1'!F26) | G26: =IF('Option 1'!G26="","",'Option 1'!G26) | H26: =IF('Option 1'!H26="","",'Option 1'!H26) | I26: =IF('Option 1'!I26="","",'Option 1'!I26) | ... O26: =IF('Option 1'!O26="","",'Option 1'!O26) | P26: =IF(SUM(D26:O26)=0,0,SUM(D26:O26)) -> 0
B27: =IF('Option 1'!B27="","",'Option 1'!B27) | C27: =IF('Option 1'!C27="","",'Option 1'!C27) -> West Entry Street Asphalt Pavement | D27: =IF('Option 1'!D27="","",'Option 1'!D27) | E27: =IF('Option 1'!E27="","",'Option 1'!E27) | F27: =IF('Option 1'!F27="","",'Option 1'!F27) | G27: =IF('Option 1'!G27="","",'Option 1'!G27) | H27: =IF('Option 1'!H27="","",'Option 1'!H27) | I27: =IF('Option 1'!I27="","",'Option 1'!I27) | ... O27: =IF('Option 1'!O27="","",'Option 1'!O27) | P27: =IF(SUM(D27:O27)=0,0,SUM(D27:O27)) -> 0
B28: =IF('Option 1'!B28="","",'Option 1'!B28) | C28: =IF('Option 1'!C28="","",'Option 1'!C28) -> West Entry Street Asphalt Sealcoating | D28: =IF('Option 1'!D28="","",'Option 1'!D28) | E28: =IF('Option 1'!E28="","",'Option 1'!E28) | F28: =IF('Option 1'!F28="","",'Option 1'!F28) | G28: =IF('Option 1'!G28="","",'Option 1'!G28) | H28: =IF('Option 1'!H28="","",'Option 1'!H28) | I28: =IF('Option 1'!I28="","",'Option 1'!I28) | ... O28: =IF('Option 1'!O28="","",'Option 1'!O28) | P28: =IF(SUM(D28:O28)=0,0,SUM(D28:O28)) -> 0
B29: =IF('Option 1'!B29="","",'Option 1'!B29) | C29: =IF('Option 1'!C29="","",'Option 1'!C29) -> East, South, & West Central Road Pavement | D29: =IF('Option 1'!D29="","",'Option 1'!D29) | E29: =IF('Option 1'!E29="","",'Option 1'!E29) | F29: =IF('Option 1'!F29="","",'Option 1'!F29) | G29: =IF('Option 1'!G29="","",'Option 1'!G29) | H29: =IF('Option 1'!H29="","",'Option 1'!H29) | I29: =IF('Option 1'!I29="","",'Option 1'!I29) | ... O29: =IF('Option 1'!O29="","",'Option 1'!O29) | P29: =IF(SUM(D29:O29)=0,0,SUM(D29:O29)) -> 0
B30: =IF('Option 1'!B30="","",'Option 1'!B30) | C30: =IF('Option 1'!C30="","",'Option 1'!C30) -> East, South, & West Central Road Sealcoating | D30: =IF('Option 1'!D30="","",'Option 1'!D30) | E30: =IF('Option 1'!E30="","",'Option 1'!E30) | F30: =IF('Option 1'!F30="","",'Option 1'!F30) | G30: =IF('Option 1'!G30="","",'Option 1'!G30) | H30: =IF('Option 1'!H30="","",'Option 1'!H30) | I30: =IF('Option 1'!I30="","",'Option 1'!I30) | ... O30: =IF('Option 1'!O30="","",'Option 1'!O30) | P30: =IF(SUM(D30:O30)=0,0,SUM(D30:O30)) -> 0
B31: =IF('Option 1'!B31="","",'Option 1'!B31) | C31: =IF('Option 1'!C31="","",'Option 1'!C31) -> Asphalt Fire Lane Pavement (Grind and Resurface) | D31: =IF('Option 1'!D31="","",'Option 1'!D31) | E31: =IF('Option 1'!E31="","",'Option 1'!E31) | F31: =IF('Option 1'!F31="","",'Option 1'!F31) | G31: =IF('Option 1'!G31="","",'Option 1'!G31) | H31: =IF('Option 1'!H31="","",'Option 1'!H31) | I31: =IF('Option 1'!I31="","",'Option 1'!I31) -> 1023820 | ... O31: =IF('Option 1'!O31="","",'Option 1'!O31) | P31: =IF(SUM(D31:O31)=0,0,SUM(D31:O31)) -> 1023820
B32: =IF('Option 1'!B32="","",'Option 1'!B32) | C32: =IF('Option 1'!C32="","",'Option 1'!C32) -> Asphalt Fire Lane Pavement Sealcoating | D32: =IF('Option 1'!D32="","",'Option 1'!D32) | E32: =IF('Option 1'!E32="","",'Option 1'!E32) | F32: =IF('Option 1'!F32="","",'Option 1'!F32) | G32: =IF('Option 1'!G32="","",'Option 1'!G32) | H32: =IF('Option 1'!H32="","",'Option 1'!H32) | I32: =IF('Option 1'!I32="","",'Option 1'!I32) | ... O32: =IF('Option 1'!O32="","",'Option 1'!O32) | P32: =IF(SUM(D32:O32)=0,0,SUM(D32:O32)) -> 46150
B33: =IF('Option 1'!B33="","",'Option 1'!B33) | C33: =IF('Option 1'!C33="","",'Option 1'!C33) -> Asphalt Parking Lot Pavement | D33: =IF('Option 1'!D33="","",'Option 1'!D33) | E33: =IF('Option 1'!E33="","",'Option 1'!E33) -> 120000 | F33: =IF('Option 1'!F33="","",'Option 1'!F33) | G33: =IF('Option 1'!G33="","",'Option 1'!G33) | H33: =IF('Option 1'!H33="","",'Option 1'!H33) | I33: =IF('Option 1'!I33="","",'Option 1'!I33) | ... O33: =IF('Option 1'!O33="","",'Option 1'!O33) | P33: =IF(SUM(D33:O33)=0,0,SUM(D33:O33)) -> 1667881
B34: =IF('Option 1'!B34="","",'Option 1'!B34) | C34: =IF('Option 1'!C34="","",'Option 1'!C34) -> Asphalt Parking Lot Sealcoating | D34: =IF('Option 1'!D34="","",'Option 1'!D34) | E34: =IF('Option 1'!E34="","",'Option 1'!E34) | F34: =IF('Option 1'!F34="","",'Option 1'!F34) | G34: =IF('Option 1'!G34="","",'Option 1'!G34) | H34: =IF('Option 1'!H34="","",'Option 1'!H34) | I34: =IF('Option 1'!I34="","",'Option 1'!I34) | ... O34: =IF('Option 1'!O34="","",'Option 1'!O34) | P34: =IF(SUM(D34:O34)=0,0,SUM(D34:O34)) -> 0
B35: =IF('Option 1'!B35="","",'Option 1'!B35) | C35: =IF('Option 1'!C35="","",'Option 1'!C35) -> Ramp Asphalt Pavement (Grind and Resurface) | D35: =IF('Option 1'!D35="","",'Option 1'!D35) | E35: =IF('Option 1'!E35="","",'Option 1'!E35) | F35: =IF('Option 1'!F35="","",'Option 1'!F35) | G35: =IF('Option 1'!G35="","",'Option 1'!G35) | H35: =IF('Option 1'!H35="","",'Option 1'!H35) | I35: =IF('Option 1'!I35="","",'Option 1'!I35) | ... O35: =IF('Option 1'!O35="","",'Option 1'!O35) | P35: =IF(SUM(D35:O35)=0,0,SUM(D35:O35)) -> 50460
... B234: =IF('Option 1'!B234="","",'Option 1'!B234) | C234: =IF('Option 1'!C234="","",'Option 1'!C234) | D234: =IF('Option 1'!D234="","",'Option 1'!D234) | E234: =IF('Option 1'!E234="","",'Option 1'!E234) | F234: =IF('Option 1'!F234="","",'Option 1'!F234) | G234: =IF('Option 1'!G234="","",'Option 1'!G234) | H234: =IF('Option 1'!H234="","",'Option 1'!H234) | I234: =IF('Option 1'!I234="","",'Option 1'!I234) | ... O234: =IF('Option 1'!O234="","",'Option 1'!O234) | P234: =IF(SUM(D234:O234)=0,0,SUM(D234:O234)) -> 0
P235: =IF(SUM(D235:O235)=0,0,SUM(D235:O235)) -> 0
C236: Special Assessment Admin Fee | D236: =IF(Assumptions!$C$21=0,0,IF(YEAR(Assumptions!C22)>Assumptions!D7,0,IF(ISERROR(IF((Assumptions!$D$13*1.75*Assumptions!$C$24*12)>1000,(Assumptions!$D$13*1.75*Assumptions!$C$24*12)/2+((((Assumptions!$D$13*1.75*Assumptions!$C$24*12)/2)/(Assumptions!$C$24*12))*Calc!$B$43),1000)),0,IF((Assumptions!$D$13*1.75*Assumptions!$C$24*12)>1000,(Assumptions!$D$13*1.75*Assumptions!$C$24*12)/2+((((Assumptions!$D$13*1.75*Assumptions!$C$24*12)/2)/(Assumptions!$C$24*12))*Calc!$B$43),1000)))) -> 0 | E236: =IF(Assumptions!$C$21=0,0,IF(D236=0,IF(ISERROR(IF((Assumptions!$D$13*1.75*Assumptions!$C$24*12)>1000,(Assumptions!$D$13*1.75*Assumptions!$C$24*12)/2+((((Assumptions!$D$13*1.75*Assumptions!$C$24*12)/2)/(Assumptions!$C$24*12))*Calc!$B$43),1000)),0,IF((Assumptions!$D$13*1.75*Assumptions!$C$24*12)>1000,(Assumptions!$D$13*1.75*Assumptions!$C$24*12)/2+((((Assumptions!$D$13*1.75*Assumptions!$C$24*12)/2)/(Assumptions!$C$24*12))*Calc!$B$43),1000))+IF(ISERROR(((((Assumptions!$D$13*1.75*Assumptions!$C$24*12)/2)/(Assumptions!$C$24*12))*Calc!C43)),0,((((Assumptions!$D$13*1.75*Assumptions!$C$24*12)/2)/(Assumptions!$C$24*12))*Calc!C43)),IF(ISERROR(((((Assumptions!$D$13*1.75*Assumptions!$C$24*12)/2)/(Assumptions!$C$24*12))*Calc!C43)),0,((((Assumptions!$D$13*1.75*Assumptions!$C$24*12)/2)/(Assumptions!$C$24*12))*Calc!C43)))) -> 0 | F236: =IF(Assumptions!$C$21=0,0,IF(ISERROR(((((Assumptions!$D$13*1.75*Assumptions!$C$24*12)/2)/(Assumptions!$C$24*12))*Calc!D43)),0,((((Assumptions!$D$13*1.75*Assumptions!$C$24*12)/2)/(Assumptions!$C$24*12))*Calc!D43))) -> 0 | G236: =IF(Assumptions!$C$21=0,0,IF(ISERROR(((((Assumptions!$D$13*1.75*Assumptions!$C$24*12)/2)/(Assumptions!$C$24*12))*Calc!E43)),0,((((Assumptions!$D$13*1.75*Assumptions!$C$24*12)/2)/(Assumptions!$C$24*12))*Calc!E43))) -> 0 | H236: =IF(Assumptions!$C$21=0,0,IF(ISERROR(((((Assumptions!$D$13*1.75*Assumptions!$C$24*12)/2)/(Assumptions!$C$24*12))*Calc!F43)),0,((((Assumptions!$D$13*1.75*Assumptions!$C$24*12)/2)/(Assumptions!$C$24*12))*Calc!F43))) -> 0 | I236: =IF(Assumptions!$C$21=0,0,IF(ISERROR(((((Assumptions!$D$13*1.75*Assumptions!$C$24*12)/2)/(Assumptions!$C$24*12))*Calc!G43)),0,((((Assumptions!$D$13*1.75*Assumptions!$C$24*12)/2)/(Assumptions!$C$24*12))*Calc!G43))) -> 0 | J236: =IF(Assumptions!$C$21=0,0,IF(ISERROR(((((Assumptions!$D$13*1.75*Assumptions!$C$24*12)/2)/(Assumptions!$C$24*12))*Calc!H43)),0,((((Assumptions!$D$13*1.75*Assumptions!$C$24*12)/2)/(Assumptions!$C$24*12))*Calc!H43))) -> 0 | K236: =IF(Assumptions!$C$21=0,0,IF(ISERROR(((((Assumptions!$D$13*1.75*Assumptions!$C$24*12)/2)/(Assumptions!$C$24*12))*Calc!I43)),0,((((Assumptions!$D$13*1.75*Assumptions!$C$24*12)/2)/(Assumptions!$C$24*12))*Calc!I43))) -> 0 | L236: =IF(Assumptions!$C$21=0,0,IF(ISERROR(((((Assumptions!$D$13*1.75*Assumptions!$C$24*12)/2)/(Assumptions!$C$24*12))*Calc!J43)),0,((((Assumptions!$D$13*1.75*Assumptions!$C$24*12)/2)/(Assumptions!$C$24*12))*Calc!J43))) -> 0 | M236: =IF(Assumptions!$C$21=0,0,IF(ISERROR(((((Assumptions!$D$13*1.75*Assumptions!$C$24*12)/2)/(Assumptions!$C$24*12))*Calc!K43)),0,((((Assumptions!$D$13*1.75*Assumptions!$C$24*12)/2)/(Assumptions!$C$24*12))*Calc!K43))) -> 0 | ... O236: =IF(Assumptions!$C$21=0,0,IF(ISERROR(((((Assumptions!$D$13*1.75*Assumptions!$C$24*12)/2)/(Assumptions!$C$24*12))*Calc!M43)),0,((((Assumptions!$D$13*1.75*Assumptions!$C$24*12)/2)/(Assumptions!$C$24*12))*Calc!M43))) -> 0 | P236: =IF(SUM(D236:O236)=0,0,SUM(D236:O236)) -> 0
P237: =IF(SUM(D237:O237)=0,0,SUM(D237:O237)) -> 0
P238: =IF(SUM(D238:O238)=0,0,SUM(D238:O238)) -> 0
B239: 9184 | C239: Loan Payment - Interest | D239: =IF(Assumptions!$C$30=0,IF(ISERROR(-CUMIPMT(0.00000000001/12,Assumptions!$C$36*12,Assumptions!$C$30,D20,D21,0)),0,-CUMIPMT(0.00000000001/12,Assumptions!$C$36*12,Assumptions!$C$30,D20,D21,0)),IF(ISERROR(-CUMIPMT(Assumptions!$C$33/12,Assumptions!$C$36*12,Assumptions!$C$30,D20,D21,0)),0,-CUMIPMT(Assumptions!$C$33/12,Assumptions!$C$36*12,Assumptions!$C$30,D20,D21,0))) -> 0 | E239: =IF(Assumptions!$C$30=0,IF(ISERROR(-CUMIPMT(0.00000000001/12,Assumptions!$C$36*12,Assumptions!$C$30,E20,E21,0)),0,-CUMIPMT(0.00000000001/12,Assumptions!$C$36*12,Assumptions!$C$30,E20,E21,0)),IF(ISERROR(-CUMIPMT(Assumptions!$C$33/12,Assumptions!$C$36*12,Assumptions!$C$30,E20,E21,0)),0,-CUMIPMT(Assumptions!$C$33/12,Assumptions!$C$36*12,Assumptions!$C$30,E20,E21,0))) -> 0 | F239: =IF(Assumptions!$C$30=0,IF(ISERROR(-CUMIPMT(0.00000000001/12,Assumptions!$C$36*12,Assumptions!$C$30,F20,F21,0)),0,-CUMIPMT(0.00000000001/12,Assumptions!$C$36*12,Assumptions!$C$30,F20,F21,0)),IF(ISERROR(-CUMIPMT(Assumptions!$C$33/12,Assumptions!$C$36*12,Assumptions!$C$30,F20,F21,0)),0,-CUMIPMT(Assumptions!$C$33/12,Assumptions!$C$36*12,Assumptions!$C$30,F20,F21,0))) -> 0 | G239: =IF(Assumptions!$C$30=0,IF(ISERROR(-CUMIPMT(0.00000000001/12,Assumptions!$C$36*12,Assumptions!$C$30,G20,G21,0)),0,-CUMIPMT(0.00000000001/12,Assumptions!$C$36*12,Assumptions!$C$30,G20,G21,0)),IF(ISERROR(-CUMIPMT(Assumptions!$C$33/12,Assumptions!$C$36*12,Assumptions!$C$30,G20,G21,0)),0,-CUMIPMT(Assumptions!$C$33/12,Assumptions!$C$36*12,Assumptions!$C$30,G20,G21,0))) -> 0 | H239: =IF(Assumptions!$C$30=0,IF(ISERROR(-CUMIPMT(0.00000000001/12,Assumptions!$C$36*12,Assumptions!$C$30,H20,H21,0)),0,-CUMIPMT(0.00000000001/12,Assumptions!$C$36*12,Assumptions!$C$30,H20,H21,0)),IF(ISERROR(-CUMIPMT(Assumptions!$C$33/12,Assumptions!$C$36*12,Assumptions!$C$30,H20,H21,0)),0,-CUMIPMT(Assumptions!$C$33/12,Assumptions!$C$36*12,Assumptions!$C$30,H20,H21,0))) -> 0 | I239: =IF(Assumptions!$C$30=0,IF(ISERROR(-CUMIPMT(0.00000000001/12,Assumptions!$C$36*12,Assumptions!$C$30,I20,I21,0)),0,-CUMIPMT(0.00000000001/12,Assumptions!$C$36*12,Assumptions!$C$30,I20,I21,0)),IF(ISERROR(-CUMIPMT(Assumptions!$C$33/12,Assumptions!$C$36*12,Assumptions!$C$30,I20,I21,0)),0,-CUMIPMT(Assumptions!$C$33/12,Assumptions!$C$36*12,Assumptions!$C$30,I20,I21,0))) -> 0 | J239: =IF(Assumptions!$C$30=0,IF(ISERROR(-CUMIPMT(0.00000000001/12,Assumptions!$C$36*12,Assumptions!$C$30,J20,J21,0)),0,-CUMIPMT(0.00000000001/12,Assumptions!$C$36*12,Assumptions!$C$30,J20,J21,0)),IF(ISERROR(-CUMIPMT(Assumptions!$C$33/12,Assumptions!$C$36*12,Assumptions!$C$30,J20,J21,0)),0,-CUMIPMT(Assumptions!$C$33/12,Assumptions!$C$36*12,Assumptions!$C$30,J20,J21,0))) -> 108570.64 | K239: =IF(Assumptions!$C$30=0,IF(ISERROR(-CUMIPMT(0.00000000001/12,Assumptions!$C$36*12,Assumptions!$C$30,K20,K21,0)),0,-CUMIPMT(0.00000000001/12,Assumptions!$C$36*12,Assumptions!$C$30,K20,K21,0)),IF(ISERROR(-CUMIPMT(Assumptions!$C$33/12,Assumptions!$C$36*12,Assumptions!$C$30,K20,K21,0)),0,-CUMIPMT(Assumptions!$C$33/12,Assumptions!$C$36*12,Assumptions!$C$30,K20,K21,0))) -> 99455.716 | ... O239: =IF(Assumptions!$C$30=0,IF(ISERROR(-CUMIPMT(0.00000000001/12,Assumptions!$C$36*12,Assumptions!$C$30,O20,O21,0)),0,-CUMIPMT(0.00000000001/12,Assumptions!$C$36*12,Assumptions!$C$30,O20,O21,0)),IF(ISERROR(-CUMIPMT(Assumptions!$C$33/12,Assumptions!$C$36*12,Assumptions!$C$30,O20,O21,0)),0,-CUMIPMT(Assumptions!$C$33/12,Assumptions!$C$36*12,Assumptions!$C$30,O20,O21,0))) -> 54776.261 | P239: =IF(SUM(D239:O239)=0,0,SUM(D239:O239)) -> 498595.7
C240: Loan Payment - Principal | D240: =IF(Assumptions!$C$30=0,IF(ISERROR(-CUMPRINC(0.00000000001/12,Assumptions!$C$36*12,Assumptions!$C$30,D20,D21,0)),0,(-CUMPRINC(0.00000000001/12,Assumptions!$C$36*12,Assumptions!$C$30,D20,D21,0))),IF(ISERROR(-CUMPRINC(Assumptions!$C$33/12,Assumptions!$C$36*12,Assumptions!$C$30,D20,D21,0)),0,(-CUMPRINC(Assumptions!$C$33/12,Assumptions!$C$36*12,Assumptions!$C$30,D20,D21,0)))) -> 0 | E240: =IF(Assumptions!$C$30=0,IF(ISERROR(-CUMPRINC(0.00000000001/12,Assumptions!$C$36*12,Assumptions!$C$30,E20,E21,0)),0,(-CUMPRINC(0.00000000001/12,Assumptions!$C$36*12,Assumptions!$C$30,E20,E21,0))),IF(ISERROR(-CUMPRINC(Assumptions!$C$33/12,Assumptions!$C$36*12,Assumptions!$C$30,E20,E21,0)),0,(-CUMPRINC(Assumptions!$C$33/12,Assumptions!$C$36*12,Assumptions!$C$30,E20,E21,0)))) -> 0 | F240: =IF(Assumptions!$C$30=0,IF(ISERROR(-CUMPRINC(0.00000000001/12,Assumptions!$C$36*12,Assumptions!$C$30,F20,F21,0)),0,(-CUMPRINC(0.00000000001/12,Assumptions!$C$36*12,Assumptions!$C$30,F20,F21,0))),IF(ISERROR(-CUMPRINC(Assumptions!$C$33/12,Assumptions!$C$36*12,Assumptions!$C$30,F20,F21,0)),0,(-CUMPRINC(Assumptions!$C$33/12,Assumptions!$C$36*12,Assumptions!$C$30,F20,F21,0)))) -> 0 | G240: =IF(Assumptions!$C$30=0,IF(ISERROR(-CUMPRINC(0.00000000001/12,Assumptions!$C$36*12,Assumptions!$C$30,G20,G21,0)),0,(-CUMPRINC(0.00000000001/12,Assumptions!$C$36*12,Assumptions!$C$30,G20,G21,0))),IF(ISERROR(-CUMPRINC(Assumptions!$C$33/12,Assumptions!$C$36*12,Assumptions!$C$30,G20,G21,0)),0,(-CUMPRINC(Assumptions!$C$33/12,Assumptions!$C$36*12,Assumptions!$C$30,G20,G21,0)))) -> 0 | H240: =IF(Assumptions!$C$30=0,IF(ISERROR(-CUMPRINC(0.00000000001/12,Assumptions!$C$36*12,Assumptions!$C$30,H20,H21,0)),0,(-CUMPRINC(0.00000000001/12,Assumptions!$C$36*12,Assumptions!$C$30,H20,H21,0))),IF(ISERROR(-CUMPRINC(Assumptions!$C$33/12,Assumptions!$C$36*12,Assumptions!$C$30,H20,H21,0)),0,(-CUMPRINC(Assumptions!$C$33/12,Assumptions!$C$36*12,Assumptions!$C$30,H20,H21,0)))) -> 0 | I240: =IF(Assumptions!$C$30=0,IF(ISERROR(-CUMPRINC(0.00000000001/12,Assumptions!$C$36*12,Assumptions!$C$30,I20,I21,0)),0,(-CUMPRINC(0.00000000001/12,Assumptions!$C$36*12,Assumptions!$C$30,I20,I21,0))),IF(ISERROR(-CUMPRINC(Assumptions!$C$33/12,Assumptions!$C$36*12,Assumptions!$C$30,I20,I21,0)),0,(-CUMPRINC(Assumptions!$C$33/12,Assumptions!$C$36*12,Assumptions!$C$30,I20,I21,0)))) -> 0 | J240: =IF(Assumptions!$C$30=0,IF(ISERROR(-CUMPRINC(0.00000000001/12,Assumptions!$C$36*12,Assumptions!$C$30,J20,J21,0)),0,(-CUMPRINC(0.00000000001/12,Assumptions!$C$36*12,Assumptions!$C$30,J20,J21,0))),IF(ISERROR(-CUMPRINC(Assumptions!$C$33/12,Assumptions!$C$36*12,Assumptions!$C$30,J20,J21,0)),0,(-CUMPRINC(Assumptions!$C$33/12,Assumptions!$C$36*12,Assumptions!$C$30,J20,J21,0)))) -> 109819.03 | K240: =IF(Assumptions!$C$30=0,IF(ISERROR(-CUMPRINC(0.00000000001/12,Assumptions!$C$36*12,Assumptions!$C$30,K20,K21,0)),0,(-CUMPRINC(0.00000000001/12,Assumptions!$C$36*12,Assumptions!$C$30,K20,K21,0))),IF(ISERROR(-CUMPRINC(Assumptions!$C$33/12,Assumptions!$C$36*12,Assumptions!$C$30,K20,K21,0)),0,(-CUMPRINC(Assumptions!$C$33/12,Assumptions!$C$36*12,Assumptions!$C$30,K20,K21,0)))) -> 118933.95 | ... O240: =IF(Assumptions!$C$30=0,IF(ISERROR(-CUMPRINC(0.00000000001/12,Assumptions!$C$36*12,Assumptions!$C$30,O20,O21,0)),0,(-CUMPRINC(0.00000000001/12,Assumptions!$C$36*12,Assumptions!$C$30,O20,O21,0))),IF(ISERROR(-CUMPRINC(Assumptions!$C$33/12,Assumptions!$C$36*12,Assumptions!$C$30,O20,O21,0)),0,(-CUMPRINC(Assumptions!$C$33/12,Assumptions!$C$36*12,Assumptions!$C$30,O20,O21,0)))) -> 163613.41 | P240: =IF(SUM(D240:O240)=0,0,SUM(D240:O240)) -> 811742.32
B241: 9199 | C241: Funds Trsfr Res to Checking | D241: 0 | P241: =IF(SUM(D241:O241)=0,0,SUM(D241:O241)) -> 0
P242: =IF(SUM(D242:O242)=0,0,SUM(D242:O242)) -> 0
P243: =IF(SUM(D243:O243)=0,0,SUM(D243:O243)) -> 0
P244: =IF(SUM(D244:O244)=0,0,SUM(D244:O244)) -> 0
C245: Total Expense | D245: =SUM(D24:D244) -> 595247 | E245: =SUM(E24:E244) -> 481097 | F245: =SUM(F24:F244) -> 520204 | G245: =SUM(G24:G244) -> 1760567 | H245: =SUM(H24:H244) -> 1819065 | I245: =SUM(I24:I244) -> 2197785 | J245: =SUM(J24:J244) -> 1011609.7 | K245: =SUM(K24:K244) -> 1756450.7 | ... O245: =SUM(O24:O244) -> 482632.67 | P245: =IF(SUM(D245:O245)=0,0,SUM(D245:O245)) -> 13606190
B247: Beginning Cash - Reserve | D247: =+Assumptions!D15 -> 623745 | E247: =+D252 -> 290817.53 | F247: =+E252 -> 462904.84 | G247: =+F252 -> 618612.01 | H247: =+G252 -> -441255.22 | I247: =+H252 -> -1556982.1 | J247: =+I252 -> -1560163.6 | K247: =+J252 -> -1863044.2 | L247: =+K252 -> -2906501.4 | ... O247: =+N252 -> -3854395.8
D249: =SUM(D24:D244) -> 595247 | E249: =SUM(E24:E244) -> 481097 | F249: =SUM(F24:F244) -> 520204 | G249: =SUM(G24:G244) -> 1760567 | H249: =SUM(H24:H244) -> 1819065 | I249: =SUM(I24:I244) -> 2197785 | J249: =SUM(J24:J244) -> 1011609.7 | K249: =SUM(K24:K244) -> 1756450.7 | ... O249: =SUM(O24:O244) -> 482632.67
B250: Annual Net Reserve Income/(Loss) | D250: =+D17-D249 -> -332927.47 | E250: =+E17-E249 -> 172087.31 | F250: =+F17-F249 -> 155707.17 | G250: =+G17-G249 -> -1059867.2 | H250: =+H17-H249 -> -1115726.9 | I250: =+I17-I249 -> -3181.4485 | J250: =+J17-J249 -> -302880.63 | K250: =+K17-K249 -> -1043457.3 | ... O250: =+O17-O249 -> 200518.46
B252: Cumulative Reserve Cash Flow | D252: =+D247+D250 -> 290817.53 | E252: =+E247+E250 -> 462904.84 | F252: =+F247+F250 -> 618612.01 | G252: =+G247+G250 -> -441255.22 | H252: =+H247+H250 -> -1556982.1 | I252: =+I247+I250 -> -1560163.6 | J252: =+J247+J250 -> -1863044.2 | K252: =+K247+K250 -> -2906501.4 | ... O252: =+O247+O250 -> -3653877.4
B254: LOC / Loan Outstanding @ 12/31/20XX | D254: =IF(ISERROR(+D15-D240),0,+D15-D240) -> 0 | E254: =IF(ISERROR(IF(D254=0,E15-E240,D254-E240)),0,IF(D254=0,E15-E240,D254+E15-E240-E234)) -> 0 | F254: =IF(ISERROR(IF(E254=0,F15-F240,E254-F240)),0,IF(E254=0,F15-F240,E254-F240)) -> 0 | G254: =IF(ISERROR(IF(F254=0,G15-G240,F254-G240)),0,IF(F254=0,G15-G240,F254-G240)) -> 0 | H254: =IF(ISERROR(IF(G254=0,H15-H240,G254-H240)),0,IF(G254=0,H15-H240,G254-H240)) -> 0 | I254: =IF(ISERROR(IF(H254=0,I15-I240,H254-I240)),0,IF(H254=0,I15-I240,H254-I240)) -> 1500000 | J254: =IF(ISERROR(IF(I254=0,J15-J240,I254-J240)),0,IF(I254=0,J15-J240,I254-J240)) -> 1390181 | K254: =IF(ISERROR(IF(J254=0,K15-K240,J254-K240)),0,IF(J254=0,K15-K240,J254-K240)) -> 1271247 | L254: =IF(ISERROR(IF(K254=0,L15-L240,K254-L240)),0,IF(K254=0,L15-L240,K254-L240)) -> 1142441.6 | M254: =IF(ISERROR(IF(L254=0,M15-M240,L254-M240)),0,IF(L254=0,M15-M240,L254-M240)) -> 1002945.4 | ... O254: =IF(ISERROR(IF(N254=0,O15-O240,N254-O240)),0,IF(N254=0,O15-O240,N254-O240)) -> 688257.68
A10137: FALSE
B10145: TRUE

Sheet Option 3
B1: =Assumptions!D5&" - Reserve & Special Assessment Analysis Option 3" -> Dana Point - Reserve & Special Assessment Analysis Option 3
B2: =+Assumptions!D7&" Reserve Study 10-Year Projection" -> 2013 Reserve Study 10-Year Projection
C4: Special Assessment | D4: =Assumptions!D21 -> 1000000
E5: =IF(YEAR(Assumptions!$D8)<YEAR(Assumptions!D22),0,1) -> 0 | F5: =+E5+1 -> 1 | G5: =+F5+1 -> 2 | H5: =+G5+1 -> 3 | I5: =+H5+1 -> 4 | J5: =+I5+1 -> 5 | K5: =+J5+1 -> 6 | L5: =+K5+1 -> 7 | M5: =+L5+1 -> 8 | ... O5: =+N5+1 -> 10
D6: =IF(YEAR(Assumptions!D22)>LEFT(D9,4)*1,0,1) -> 0 | E6: =+D7+1 -> 1 | F6: =+E7+1 -> 13 | G6: =+F7+1 -> 25 | H6: =+G7+1 -> 37 | I6: =+H7+1 -> 49 | J6: =+I7+1 -> 61 | K6: =+J7+1 -> 73 | L6: =+K7+1 -> 85 | ... O6: =+N7+1 -> 121
D7: =IF(D6=0,0,ROUND(((IF(YEAR(Assumptions!D8)<YEAR(Assumptions!D22),(Assumptions!D8+365)-Assumptions!D22,Assumptions!D8-Assumptions!D22))/30),0)) -> 0 | E7: =IF(D7=0,ROUND(((IF(YEAR(Assumptions!D8)<YEAR(Assumptions!D22),(Assumptions!D8+365)-Assumptions!D22,Assumptions!D8-Assumptions!D22))/30),0),IF(Assumptions!$D$24*12>D7+12,D7+12,Assumptions!$D$24*12)) -> 12 | F7: =IF(Assumptions!$D$24*12>E7+12,E7+12,Assumptions!$D$24*12) -> 24 | G7: =IF(Assumptions!$D$24*12>F7+12,F7+12,Assumptions!$D$24*12) -> 36 | H7: =IF(Assumptions!$D$24*12>G7+12,G7+12,Assumptions!$D$24*12) -> 48 | I7: =IF(Assumptions!$D$24*12>H7+12,H7+12,Assumptions!$D$24*12) -> 60 | J7: =IF(Assumptions!$D$24*12>I7+12,I7+12,Assumptions!$D$24*12) -> 72 | K7: =IF(Assumptions!$D$24*12>J7+12,J7+12,Assumptions!$D$24*12) -> 84 | L7: =IF(Assumptions!$D$24*12>K7+12,K7+12,Assumptions!$D$24*12) -> 96 | M7: =IF(Assumptions!$D$24*12>L7+12,L7+12,Assumptions!$D$24*12) -> 108 | ... O7: =IF(Assumptions!$D$24*12>N7+12,N7+12,Assumptions!$D$24*12) -> 120
A9: INCOME | B9: GL | C9: Name | D9: =Assumptions!D7&" Budget" -> 2013 Budget | E9: =+Assumptions!D7+1 -> 2014 | F9: =+E9+1 -> 2015 | G9: =+F9+1 -> 2016 | H9: =+G9+1 -> 2017 | I9: =+H9+1 -> 2018 | J9: =+I9+1 -> 2019 | K9: =+J9+1 -> 2020 | L9: =+K9+1 -> 2021 | M9: =+L9+1 -> 2022 | ... O9: =+N9+1 -> 2024 | P9: TOTAL
B10: 9001 | C10: Budgeted Operating Funds to Reserves | D10: =ROUND((+Assumptions!D10/12*Calc!$G$9),0) -> 202156 | E10: =+(Assumptions!D10)*(1+Assumptions!K26) -> 499729.22 | F10: =+E10*(1+Assumptions!K27) -> 514721.1 | G10: =+F10*(1+Assumptions!K28) -> 530162.73 | H10: =+G10*(1+Assumptions!K29) -> 546067.61 | I10: =+H10*(1+Assumptions!K30) -> 562449.64 | J10: =+I10*(1+Assumptions!K31) -> 579323.13 | K10: =+J10*(1+Assumptions!K32) -> 596702.82 | L10: =+K10*(1+Assumptions!K33) -> 614603.91 | M10: =+L10*(1+Assumptions!K34) -> 633042.02 | N10: =+M10*(1+Assumptions!K35) -> 652033.29 | O10: =+N10*(1+Assumptions!K36) -> 671594.28 | P10: =SUM(D10:O10) -> 6602585.8
B11: 9005 | C11: Budgeted Operating Funds to Reserves | D11: =+'Option 1'!D11 -> 58604.167 | E11: =+'Option 1'!E11 -> 152001 | F11: =+'Option 1'!F11 -> 156561.03 | G11: =+'Option 1'!G11 -> 161257.86 | H11: =+'Option 1'!H11 -> 166095.6 | I11: =+'Option 1'!I11 -> 171078.46 | J11: =+'Option 1'!J11 -> 176210.82 | K11: =+'Option 1'!K11 -> 181497.14 | ... O11: =+'Option 1'!O11 -> 204276.63 | P11: =SUM(D11:O11) -> 2005401.9
