Workbook
Name gllu: LU!$A$1:$B$838

Sheet LU
A1: Account | B1: Long Desc
A2: 4009 | B2: Assessments, Res 1
A3: 4010 | B3: Assessments - Regular
A4: 4010-1 | B4: Other Assessment Inc
A5: 4010-2 | B5: Other Assessment Inc
A6: 4010-3 | B6: Other Assessment Inc
A7: 4010-4 | B7: Other Assessment Inc
A8: 4010-5 | B8: Other Assessment Inc
A9: 4011 | B9: Assessment, Reserve
A10: 4011-1 | B10: Other Reserve Assmt
A11: 4011-2 | B11: Other Reserve Assmt
A12: 4011-3 | B12: Other Reserve Assmt
... A838: C9186 | B838: Loan Legal/Bank Fees

Sheet Operating Main Budget
A1: Prev Agnt Acct # | B1: Prev Agnt Desc | C1: LMS Acct # | D1: LMS Desc | E1: Amount | F1: O/R | H1: Jan | I1: Feb | J1: Mar | K1: Apr | L1: May | M1: Jun | N1: Jul | O1: Aug | P1: Sep | Q1: Oct | R1: Nov | S1: Dec | T1: Error Check
A2: 5120 | B2: rental income | C2: 4140 | D2: =VLOOKUP(C2,gllu,2,0) -> Unit Rental Income | E2: -67260 | F2: O | G2: =C1=C2 -> FALSE | H2: =ROUND(($E2/12),0) -> -5605 | I2: =ROUND(($E2/12),0) -> -5605 | J2: =ROUND(($E2/12),0) -> -5605 | K2: =ROUND(($E2/12),0) -> -5605 | L2: =ROUND(($E2/12),0) -> -5605 | M2: =ROUND(($E2/12),0) -> -5605 | N2: =ROUND(($E2/12),0) -> -5605 | O2: =ROUND(($E2/12),0) -> -5605 | ... R2: =ROUND(($E2/12),0) -> -5605 | S2: =ROUND((E2-((ROUND(($E2/12),0))*11)),0) -> -5605 | T2: =SUM(H2:S2)-E2 -> 0
A3: 5130 | B3: assessments | C3: 4010 | D3: =VLOOKUP(C3,gllu,2,0) -> Assessments - Regular | E3: -1258300 | F3: O | G3: =C2=C3 -> FALSE | H3: =ROUND(($E3/12),0) -> -104858 | I3: =ROUND(($E3/12),0) -> -104858 | J3: =ROUND(($E3/12),0) -> -104858 | K3: =ROUND(($E3/12),0) -> -104858 | L3: =ROUND(($E3/12),0) -> -104858 | M3: =ROUND(($E3/12),0) -> -104858 | N3: =ROUND(($E3/12),0) -> -104858 | O3: =ROUND(($E3/12),0) -> -104858 | ... R3: =ROUND(($E3/12),0) -> -104858 | S3: =ROUND((E3-((ROUND(($E3/12),0))*11)),0) -> -104862 | T3: =SUM(H3:S3)-E3 -> 0
A4: 5135 | B4: replacement reserve assessment | C4: 4011 | D4: =VLOOKUP(C4,gllu,2,0) -> Assessment, Reserve | E4: -485174 | F4: O | G4: =C3=C4 -> FALSE | H4: =ROUND(($E4/12),0) -> -40431 | I4: =ROUND(($E4/12),0) -> -40431 | J4: =ROUND(($E4/12),0) -> -40431 | K4: =ROUND(($E4/12),0) -> -40431 | L4: =ROUND(($E4/12),0) -> -40431 | M4: =ROUND(($E4/12),0) -> -40431 | N4: =ROUND(($E4/12),0) -> -40431 | O4: =ROUND(($E4/12),0) -> -40431 | ... R4: =ROUND(($E4/12),0) -> -40431 | S4: =ROUND((E4-((ROUND(($E4/12),0))*11)),0) -> -40433 | T4: =SUM(H4:S4)-E4 -> 0
A5: 5151 | B5: bank loan payment | C5: 4012 | D5: =VLOOKUP(C5,gllu,2,0) -> Prior Year Assessments | E5: -140650.08 | F5: O | G5: =C4=C5 -> FALSE | H5: =ROUND(($E5/12),0) -> -11721 | I5: =ROUND(($E5/12),0) -> -11721 | J5: =ROUND(($E5/12),0) -> -11721 | K5: =ROUND(($E5/12),0) -> -11721 | L5: =ROUND(($E5/12),0) -> -11721 | M5: =ROUND(($E5/12),0) -> -11721 | N5: =ROUND(($E5/12),0) -> -11721 | O5: =ROUND(($E5/12),0) -> -11721 | ... R5: =ROUND(($E5/12),0) -> -11721 | S5: =ROUND((E5-((ROUND(($E5/12),0))*11)),0) -> -11719 | T5: =SUM(H5:S5)-E5 -> 0.08
A6: 5418 | B6: interest income - operating account | C6: 4610 | D6: =VLOOKUP(C6,gllu,2,0) -> Checking Account Interest | E6: -100 | F6: O | G6: =C5=C6 -> FALSE | H6: =ROUND(($E6/12),0) -> -8 | I6: =ROUND(($E6/12),0) -> -8 | J6: =ROUND(($E6/12),0) -> -8 | K6: =ROUND(($E6/12),0) -> -8 | L6: =ROUND(($E6/12),0) -> -8 | M6: =ROUND(($E6/12),0) -> -8 | N6: =ROUND(($E6/12),0) -> -8 | O6: =ROUND(($E6/12),0) -> -8 | ... R6: =ROUND(($E6/12),0) -> -8 | S6: =ROUND((E6-((ROUND(($E6/12),0))*11)),0) -> -12 | T6: =SUM(H6:S6)-E6 -> 0
A7: 5301 | B7: laundry room income | C7: 4110 | D7: =VLOOKUP(C7,gllu,2,0) -> Laundry Room Income | E7: -52000 | F7: O | G7: =C6=C7 -> FALSE | H7: =ROUND(($E7/12),0) -> -4333 | I7: =ROUND(($E7/12),0) -> -4333 | J7: =ROUND(($E7/12),0) -> -4333 | K7: =ROUND(($E7/12),0) -> -4333 | L7: =ROUND(($E7/12),0) -> -4333 | M7: =ROUND(($E7/12),0) -> -4333 | N7: =ROUND(($E7/12),0) -> -4333 | O7: =ROUND(($E7/12),0) -> -4333 | ... R7: =ROUND(($E7/12),0) -> -4333 | S7: =ROUND((E7-((ROUND(($E7/12),0))*11)),0) -> -4337 | T7: =SUM(H7:S7)-E7 -> 0
A8: 5903 | B8: late fees | C8: 4020 | D8: =VLOOKUP(C8,gllu,2,0) -> Late Charges | E8: -3600 | F8: O | G8: =C7=C8 -> FALSE | H8: =ROUND(($E8/12),0) -> -300 | I8: =ROUND(($E8/12),0) -> -300 | J8: =ROUND(($E8/12),0) -> -300 | K8: =ROUND(($E8/12),0) -> -300 | L8: =ROUND(($E8/12),0) -> -300 | M8: =ROUND(($E8/12),0) -> -300 | N8: =ROUND(($E8/12),0) -> -300 | O8: =ROUND(($E8/12),0) -> -300 | ... R8: =ROUND(($E8/12),0) -> -300 | S8: =ROUND((E8-((ROUND(($E8/12),0))*11)),0) -> -300 | T8: =SUM(H8:S8)-E8 -> 0
A9: 5909 | B9: miscellaneous sundry income | C9: 4995 | D9: =VLOOKUP(C9,gllu,2,0) -> Miscellaneous Income | E9: -1000 | F9: O | G9: =C8=C9 -> FALSE | H9: =ROUND(($E9/12),0) -> -83 | I9: =ROUND(($E9/12),0) -> -83 | J9: =ROUND(($E9/12),0) -> -83 | K9: =ROUND(($E9/12),0) -> -83 | L9: =ROUND(($E9/12),0) -> -83 | M9: =ROUND(($E9/12),0) -> -83 | N9: =ROUND(($E9/12),0) -> -83 | O9: =ROUND(($E9/12),0) -> -83 | ... R9: =ROUND(($E9/12),0) -> -83 | S9: =ROUND((E9-((ROUND(($E9/12),0))*11)),0) -> -87 | T9: =SUM(H9:S9)-E9 -> 0
A10: 5914 | B10: fines & violations | C10: 4050 | D10: =VLOOKUP(C10,gllu,2,0) -> Violation Income | E10: -600 | F10: O | G10: =C9=C10 -> FALSE | H10: =ROUND(($E10/12),0) -> -50 | I10: =ROUND(($E10/12),0) -> -50 | J10: =ROUND(($E10/12),0) -> -50 | K10: =ROUND(($E10/12),0) -> -50 | L10: =ROUND(($E10/12),0) -> -50 | M10: =ROUND(($E10/12),0) -> -50 | N10: =ROUND(($E10/12),0) -> -50 | O10: =ROUND(($E10/12),0) -> -50 | ... R10: =ROUND(($E10/12),0) -> -50 | S10: =ROUND((E10-((ROUND(($E10/12),0))*11)),0) -> -50 | T10: =SUM(H10:S10)-E10 -> 0
A11: 5915 | B11: document sales fees | C11: 4330 | D11: =VLOOKUP(C11,gllu,2,0) -> PAL/Transfer Fees | E11: -6000 | F11: O | G11: =C10=C11 -> FALSE | H11: =ROUND(($E11/12),0) -> -500 | I11: =ROUND(($E11/12),0) -> -500 | J11: =ROUND(($E11/12),0) -> -500 | K11: =ROUND(($E11/12),0) -> -500 | L11: =ROUND(($E11/12),0) -> -500 | M11: =ROUND(($E11/12),0) -> -500 | N11: =ROUND(($E11/12),0) -> -500 | O11: =ROUND(($E11/12),0) -> -500 | ... R11: =ROUND(($E11/12),0) -> -500 | S11: =ROUND((E11-((ROUND(($E11/12),0))*11)),0) -> -500 | T11: =SUM(H11:S11)-E11 -> 0
A12: 5919 | B12: moving fees | C12: 4030 | D12: =VLOOKUP(C12,gllu,2,0) -> Move In/Move Out Fees | E12: -10000 | F12: O | G12: =C11=C12 -> FALSE | H12: =ROUND(($E12/12),0) -> -833 | I12: =ROUND(($E12/12),0) -> -833 | J12: =ROUND(($E12/12),0) -> -833 | K12: =ROUND(($E12/12),0) -> -833 | L12: =ROUND(($E12/12),0) -> -833 | M12: =ROUND(($E12/12),0) -> -833 | N12: =ROUND(($E12/12),0) -> -833 | O12: =ROUND(($E12/12),0) -> -833 | ... R12: =ROUND(($E12/12),0) -> -833 | S12: =ROUND((E12-((ROUND(($E12/12),0))*11)),0) -> -837 | T12: =SUM(H12:S12)-E12 -> 0
A13: 5990 | B13: storage locker fees | C13: 4070 | D13: =VLOOKUP(C13,gllu,2,0) -> Storage Space Rent | E13: -15360 | F13: O | G13: =C12=C13 -> FALSE | H13: =ROUND(($E13/12),0) -> -1280 | I13: =ROUND(($E13/12),0) -> -1280 | J13: =ROUND(($E13/12),0) -> -1280 | K13: =ROUND(($E13/12),0) -> -1280 | L13: =ROUND(($E13/12),0) -> -1280 | M13: =ROUND(($E13/12),0) -> -1280 | N13: =ROUND(($E13/12),0) -> -1280 | O13: =ROUND(($E13/12),0) -> -1280 | ... R13: =ROUND(($E13/12),0) -> -1280 | S13: =ROUND((E13-((ROUND(($E13/12),0))*11)),0) -> -1280 | T13: =SUM(H13:S13)-E13 -> 0
... A76: 6898 | B76: replacement reserve deposit | C76: 8801 | D76: =VLOOKUP(C76,gllu,2,0) -> Budgeted Trsf to Res | E76: 485174 | F76: O | G76: =C75=C76 -> FALSE | H76: =ROUND(($E76/12),0) -> 40431 | I76: =ROUND(($E76/12),0) -> 40431 | J76: =ROUND(($E76/12),0) -> 40431 | K76: =ROUND(($E76/12),0) -> 40431 | L76: =ROUND(($E76/12),0) -> 40431 | M76: =ROUND(($E76/12),0) -> 40431 | N76: =ROUND(($E76/12),0) -> 40431 | O76: =ROUND(($E76/12),0) -> 40431 | ... R76: =ROUND(($E76/12),0) -> 40431 | S76: =ROUND((E76-((ROUND(($E76/12),0))*11)),0) -> 40433 | T76: =SUM(H76:S76)-E76 -> 0
E78: =SUM(E2:E77) -> 800

Sheet Reserve Budget Main
A1: Prev Agnt Acct # | B1: Prev Agnt Desc | C1: LMS Acct # | D1: LMS Desc | E1: Amount | F1: O/R | H1: Jan | I1: Feb | J1: Mar | K1: Apr | L1: May | M1: Jun | N1: Jul | O1: Aug | P1: Sep | Q1: Oct | R1: Nov | S1: Dec | T1: Error Check
A2: 7010 | B2: replacement reserve deposit | C2: 9001 | D2: =VLOOKUP(C2,gllu,2,0) -> Budgeted Operating Fund to Reserves | E2: -485174 | F2: R | H2: =ROUND(($E2/12),0) -> -40431 | I2: =ROUND(($E2/12),0) -> -40431 | J2: =ROUND(($E2/12),0) -> -40431 | K2: =ROUND(($E2/12),0) -> -40431 | L2: =ROUND(($E2/12),0) -> -40431 | M2: =ROUND(($E2/12),0) -> -40431 | N2: =ROUND(($E2/12),0) -> -40431 | O2: =ROUND(($E2/12),0) -> -40431 | ... R2: =ROUND(($E2/12),0) -> -40431 | S2: =ROUND((E2-((ROUND(($E2/12),0))*11)),0) -> -40433 | T2: =SUM(H2:S2)-E2 -> 0
A3: 7927-4 | B3: pool | C3: 9180 | D3: =VLOOKUP(C3,gllu,2,0) -> Swimming Pool Capital Expense | E3: 2400 | F3: R | H3: =ROUND(($E3/12),0) -> 200 | I3: =ROUND(($E3/12),0) -> 200 | J3: =ROUND(($E3/12),0) -> 200 | K3: =ROUND(($E3/12),0) -> 200 | L3: =ROUND(($E3/12),0) -> 200 | M3: =ROUND(($E3/12),0) -> 200 | N3: =ROUND(($E3/12),0) -> 200 | O3: =ROUND(($E3/12),0) -> 200 | ... R3: =ROUND(($E3/12),0) -> 200 | S3: =ROUND((E3-((ROUND(($E3/12),0))*11)),0) -> 200 | T3: =SUM(H3:S3)-E3 -> 0
A4: 7927-6 | B4: street lights | C4: 9174 | D4: =VLOOKUP(C4,gllu,2,0) -> Electrical Capital Expense | E4: 1500 | F4: R | H4: =ROUND(($E4/12),0) -> 125 | I4: =ROUND(($E4/12),0) -> 125 | J4: =ROUND(($E4/12),0) -> 125 | K4: =ROUND(($E4/12),0) -> 125 | L4: =ROUND(($E4/12),0) -> 125 | M4: =ROUND(($E4/12),0) -> 125 | N4: =ROUND(($E4/12),0) -> 125 | O4: =ROUND(($E4/12),0) -> 125 | ... R4: =ROUND(($E4/12),0) -> 125 | S4: =ROUND((E4-((ROUND(($E4/12),0))*11)),0) -> 125 | T4: =SUM(H4:S4)-E4 -> 0
A5: 7927-7 | B5: pavement | C5: 9173 | D5: =VLOOKUP(C5,gllu,2,0) -> Asphalt Capital Expense | E5: 100000 | F5: R | H5: =ROUND(($E5/12),0) -> 8333 | I5: =ROUND(($E5/12),0) -> 8333 | J5: =ROUND(($E5/12),0) -> 8333 | K5: =ROUND(($E5/12),0) -> 8333 | L5: =ROUND(($E5/12),0) -> 8333 | M5: =ROUND(($E5/12),0) -> 8333 | N5: =ROUND(($E5/12),0) -> 8333 | O5: =ROUND(($E5/12),0) -> 8333 | ... R5: =ROUND(($E5/12),0) -> 8333 | S5: =ROUND((E5-((ROUND(($E5/12),0))*11)),0) -> 8337 | T5: =SUM(H5:S5)-E5 -> 0
A6: 7927-8 | B6: concrete | C6: 9164 | D6: =VLOOKUP(C6,gllu,2,0) -> Concrete Capital Expense | E6: 3500 | F6: R | H6: =ROUND(($E6/12),0) -> 292 | I6: =ROUND(($E6/12),0) -> 292 | J6: =ROUND(($E6/12),0) -> 292 | K6: =ROUND(($E6/12),0) -> 292 | L6: =ROUND(($E6/12),0) -> 292 | M6: =ROUND(($E6/12),0) -> 292 | N6: =ROUND(($E6/12),0) -> 292 | O6: =ROUND(($E6/12),0) -> 292 | ... R6: =ROUND(($E6/12),0) -> 292 | S6: =ROUND((E6-((ROUND(($E6/12),0))*11)),0) -> 288 | T6: =SUM(H6:S6)-E6 -> 0
A7: 7927-12 | B7: balcony | C7: 9163-6 | D7: =VLOOKUP(C7,gllu,2,0) -> Carpentry-Balcony Repair/Replacement | E7: 220000 | F7: R | H7: =ROUND(($E7/12),0) -> 18333 | I7: =ROUND(($E7/12),0) -> 18333 | J7: =ROUND(($E7/12),0) -> 18333 | K7: =ROUND(($E7/12),0) -> 18333 | L7: =ROUND(($E7/12),0) -> 18333 | M7: =ROUND(($E7/12),0) -> 18333 | N7: =ROUND(($E7/12),0) -> 18333 | O7: =ROUND(($E7/12),0) -> 18333 | ... R7: =ROUND(($E7/12),0) -> 18333 | S7: =ROUND((E7-((ROUND(($E7/12),0))*11)),0) -> 18337 | T7: =SUM(H7:S7)-E7 -> 0
A8: 7927-14 | B8: garage | C8: 9182 | D8: =VLOOKUP(C8,gllu,2,0) -> Garage Capital Expense | E8: 4600 | F8: R | H8: =ROUND(($E8/12),0) -> 383 | I8: =ROUND(($E8/12),0) -> 383 | J8: =ROUND(($E8/12),0) -> 383 | K8: =ROUND(($E8/12),0) -> 383 | L8: =ROUND(($E8/12),0) -> 383 | M8: =ROUND(($E8/12),0) -> 383 | N8: =ROUND(($E8/12),0) -> 383 | O8: =ROUND(($E8/12),0) -> 383 | ... R8: =ROUND(($E8/12),0) -> 383 | S8: =ROUND((E8-((ROUND(($E8/12),0))*11)),0) -> 387 | T8: =SUM(H8:S8)-E8 -> 0
A9: 7927-17 | B9: air conditioning/HVAC | C9: 9168 | D9: =VLOOKUP(C9,gllu,2,0) -> HVAC Capital Expense | E9: 12000 | F9: R | H9: =ROUND(($E9/12),0) -> 1000 | I9: =ROUND(($E9/12),0) -> 1000 | J9: =ROUND(($E9/12),0) -> 1000 | K9: =ROUND(($E9/12),0) -> 1000 | L9: =ROUND(($E9/12),0) -> 1000 | M9: =ROUND(($E9/12),0) -> 1000 | N9: =ROUND(($E9/12),0) -> 1000 | O9: =ROUND(($E9/12),0) -> 1000 | ... R9: =ROUND(($E9/12),0) -> 1000 | S9: =ROUND((E9-((ROUND(($E9/12),0))*11)),0) -> 1000 | T9: =SUM(H9:S9)-E9 -> 0
A10: 7927-19 | B10: water heater | C10: 9169-3 | D10: =VLOOKUP(C10,gllu,2,0) -> Plumbing-Water Heaters | E10: 6000 | F10: R | H10: =ROUND(($E10/12),0) -> 500 | I10: =ROUND(($E10/12),0) -> 500 | J10: =ROUND(($E10/12),0) -> 500 | K10: =ROUND(($E10/12),0) -> 500 | L10: =ROUND(($E10/12),0) -> 500 | M10: =ROUND(($E10/12),0) -> 500 | N10: =ROUND(($E10/12),0) -> 500 | O10: =ROUND(($E10/12),0) -> 500 | ... R10: =ROUND(($E10/12),0) -> 500 | S10: =ROUND((E10-((ROUND(($E10/12),0))*11)),0) -> 500 | T10: =SUM(H10:S10)-E10 -> 0
A11: 7927-25 | B11: fire system A3288 | C11: 9160-1 | D11: =VLOOKUP(C11,gllu,2,0) -> Building Capital Expenses | E11: 12000 | F11: R | H11: =ROUND(($E11/12),0) -> 1000 | I11: =ROUND(($E11/12),0) -> 1000 | J11: =ROUND(($E11/12),0) -> 1000 | K11: =ROUND(($E11/12),0) -> 1000 | L11: =ROUND(($E11/12),0) -> 1000 | M11: =ROUND(($E11/12),0) -> 1000 | N11: =ROUND(($E11/12),0) -> 1000 | O11: =ROUND(($E11/12),0) -> 1000 | ... R11: =ROUND(($E11/12),0) -> 1000 | S11: =ROUND((E11-((ROUND(($E11/12),0))*11)),0) -> 1000 | T11: =SUM(H11:S11)-E11 -> 0
A12: 7927-28 | B12: plumbing | C12: 9169 | D12: =VLOOKUP(C12,gllu,2,0) -> Plumbing Capital Expense | E12: 40000 | F12: R | H12: =ROUND(($E12/12),0) -> 3333 | I12: =ROUND(($E12/12),0) -> 3333 | J12: =ROUND(($E12/12),0) -> 3333 | K12: =ROUND(($E12/12),0) -> 3333 | L12: =ROUND(($E12/12),0) -> 3333 | M12: =ROUND(($E12/12),0) -> 3333 | N12: =ROUND(($E12/12),0) -> 3333 | O12: =ROUND(($E12/12),0) -> 3333 | ... R12: =ROUND(($E12/12),0) -> 3333 | S12: =ROUND((E12-((ROUND(($E12/12),0))*11)),0) -> 3337 | T12: =SUM(H12:S12)-E12 -> 0
A13: 7927-29 | B13: structural | C13: 9162 | D13: =VLOOKUP(C13,gllu,2,0) -> Masonry/Tuckpointing Capital Expense | E13: 10000 | F13: R | H13: =ROUND(($E13/12),0) -> 833 | I13: =ROUND(($E13/12),0) -> 833 | J13: =ROUND(($E13/12),0) -> 833 | K13: =ROUND(($E13/12),0) -> 833 | L13: =ROUND(($E13/12),0) -> 833 | M13: =ROUND(($E13/12),0) -> 833 | N13: =ROUND(($E13/12),0) -> 833 | O13: =ROUND(($E13/12),0) -> 833 | ... R13: =ROUND(($E13/12),0) -> 833 | S13: =ROUND((E13-((ROUND(($E13/12),0))*11)),0) -> 837 | T13: =SUM(H13:S13)-E13 -> 0
A14: 7927-31 | B14: reserve study | C14: 9150 | D14: =VLOOKUP(C14,gllu,2,0) -> Reserve Study | E14: 5000 | F14: R | H14: =ROUND(($E14/12),0) -> 417 | I14: =ROUND(($E14/12),0) -> 417 | J14: =ROUND(($E14/12),0) -> 417 | K14: =ROUND(($E14/12),0) -> 417 | L14: =ROUND(($E14/12),0) -> 417 | M14: =ROUND(($E14/12),0) -> 417 | N14: =ROUND(($E14/12),0) -> 417 | O14: =ROUND(($E14/12),0) -> 417 | ... R14: =ROUND(($E14/12),0) -> 417 | S14: =ROUND((E14-((ROUND(($E14/12),0))*11)),0) -> 413 | T14: =SUM(H14:S14)-E14 -> 0
... A19: 7927-52 | B19: exterior lights | C19: 9174-1 | D19: =VLOOKUP(C19,gllu,2,0) -> Electrical-Fixture Replacement | E19: 1500 | F19: R | H19: =ROUND(($E19/12),0) -> 125 | I19: =ROUND(($E19/12),0) -> 125 | J19: =ROUND(($E19/12),0) -> 125 | K19: =ROUND(($E19/12),0) -> 125 | L19: =ROUND(($E19/12),0) -> 125 | M19: =ROUND(($E19/12),0) -> 125 | N19: =ROUND(($E19/12),0) -> 125 | O19: =ROUND(($E19/12),0) -> 125 | ... R19: =ROUND(($E19/12),0) -> 125 | S19: =ROUND((E19-((ROUND(($E19/12),0))*11)),0) -> 125 | T19: =SUM(H19:S19)-E19 -> 0
C20: 9005 | D20: =VLOOKUP(C20,gllu,2,0) -> Bdgt Oper Fnd to Res | E20: -140650.08 | F20: R | H20: =ROUND(($E20/12),0) -> -11721 | I20: =ROUND(($E20/12),0) -> -11721 | J20: =ROUND(($E20/12),0) -> -11721 | K20: =ROUND(($E20/12),0) -> -11721 | L20: =ROUND(($E20/12),0) -> -11721 | M20: =ROUND(($E20/12),0) -> -11721 | N20: =ROUND(($E20/12),0) -> -11721 | O20: =ROUND(($E20/12),0) -> -11721 | ... R20: =ROUND(($E20/12),0) -> -11721 | S20: =ROUND((E20-((ROUND(($E20/12),0))*11)),0) -> -11719 | T20: =SUM(H20:S20)-E20 -> 0.08
C21: 9184 | D21: =VLOOKUP(C21,gllu,2,0) -> Capital Loan Payment | E21: 11948.52 | F21: R | H21: =ROUND(($E21/12),0) -> 996 | I21: =ROUND(($E21/12),0) -> 996 | J21: =ROUND(($E21/12),0) -> 996 | K21: =ROUND(($E21/12),0) -> 996 | L21: =ROUND(($E21/12),0) -> 996 | M21: =ROUND(($E21/12),0) -> 996 | N21: =ROUND(($E21/12),0) -> 996 | O21: =ROUND(($E21/12),0) -> 996 | ... R21: =ROUND(($E21/12),0) -> 996 | S21: =ROUND((E21-((ROUND(($E21/12),0))*11)),0) -> 993 | T21: =SUM(H21:S21)-E21 -> 0.48
C22: 9184-P | D22: =VLOOKUP(C22,gllu,2,0) -> Loan Principal Pymt | E22: 128701.56 | F22: R | H22: =ROUND(($E22/12),0) -> 10725 | I22: =ROUND(($E22/12),0) -> 10725 | J22: =ROUND(($E22/12),0) -> 10725 | K22: =ROUND(($E22/12),0) -> 10725 | L22: =ROUND(($E22/12),0) -> 10725 | M22: =ROUND(($E22/12),0) -> 10725 | N22: =ROUND(($E22/12),0) -> 10725 | O22: =ROUND(($E22/12),0) -> 10725 | ... R22: =ROUND(($E22/12),0) -> 10725 | S22: =ROUND((E22-((ROUND(($E22/12),0))*11)),0) -> 10727 | T22: =SUM(H22:S22)-E22 -> 0.44
C23: 9025 | D23: =VLOOKUP(C23,gllu,2,0) -> Reserve Interest Inc | E23: -800 | F23: R | H23: =ROUND(($E23/12),0) -> -67 | I23: =ROUND(($E23/12),0) -> -67 | J23: =ROUND(($E23/12),0) -> -67 | K23: =ROUND(($E23/12),0) -> -67 | L23: =ROUND(($E23/12),0) -> -67 | M23: =ROUND(($E23/12),0) -> -67 | N23: =ROUND(($E23/12),0) -> -67 | O23: =ROUND(($E23/12),0) -> -67 | ... R23: =ROUND(($E23/12),0) -> -67 | S23: =ROUND((E23-((ROUND(($E23/12),0))*11)),0) -> -63 | T23: =SUM(H23:S23)-E23 -> 0
E25: =SUM(E2:E24) -> -49274

Sheet Operating Upload
A1: 0554 | B1: 2013
C2: JAN | D2: FEB | E2: MAR | F2: APR | G2: MAY | H2: JUN | I2: JUL | J2: AUG | K2: SEP | L2: OCT | M2: NOV | N2: DEC
C3: 2013 | D3: 2013 | E3: 2013 | F3: 2013 | G3: 2013 | H3: 2013 | I3: 2013 | J3: 2013 | K3: 2013 | L3: 2013 | M3: 2013 | N3: 2013
A4: 4140 | C4: =VLOOKUP($A4,'Operating Main Budget'!$C:$S,6,0) -> -5605 | D4: =VLOOKUP($A4,'Operating Main Budget'!$C:$S,7,0) -> -5605 | E4: =VLOOKUP($A4,'Operating Main Budget'!$C:$S,8,0) -> -5605 | F4: =VLOOKUP($A4,'Operating Main Budget'!$C:$S,9,0) -> -5605 | G4: =VLOOKUP($A4,'Operating Main Budget'!$C:$S,10,0) -> -5605 | H4: =VLOOKUP($A4,'Operating Main Budget'!$C:$S,11,0) -> -5605 | I4: =VLOOKUP($A4,'Operating Main Budget'!$C:$S,12,0) -> -5605 | J4: =VLOOKUP($A4,'Operating Main Budget'!$C:$S,13,0) -> -5605 | K4: =VLOOKUP($A4,'Operating Main Budget'!$C:$S,14,0) -> -5605 | L4: =VLOOKUP($A4,'Operating Main Budget'!$C:$S,15,0) -> -5605 | M4: =VLOOKUP($A4,'Operating Main Budget'!$C:$S,16,0) -> -5605 | N4: =VLOOKUP($A4,'Operating Main Budget'!$C:$S,17,0) -> -5605
A5: 4010 | C5: =VLOOKUP($A5,'Operating Main Budget'!$C:$S,6,0) -> -104858 | D5: =VLOOKUP($A5,'Operating Main Budget'!$C:$S,7,0) -> -104858 | E5: =VLOOKUP($A5,'Operating Main Budget'!$C:$S,8,0) -> -104858 | F5: =VLOOKUP($A5,'Operating Main Budget'!$C:$S,9,0) -> -104858 | G5: =VLOOKUP($A5,'Operating Main Budget'!$C:$S,10,0) -> -104858 | H5: =VLOOKUP($A5,'Operating Main Budget'!$C:$S,11,0) -> -104858 | I5: =VLOOKUP($A5,'Operating Main Budget'!$C:$S,12,0) -> -104858 | J5: =VLOOKUP($A5,'Operating Main Budget'!$C:$S,13,0) -> -104858 | K5: =VLOOKUP($A5,'Operating Main Budget'!$C:$S,14,0) -> -104858 | L5: =VLOOKUP($A5,'Operating Main Budget'!$C:$S,15,0) -> -104858 | M5: =VLOOKUP($A5,'Operating Main Budget'!$C:$S,16,0) -> -104858 | N5: =VLOOKUP($A5,'Operating Main Budget'!$C:$S,17,0) -> -104862
A6: 4011 | C6: =VLOOKUP($A6,'Operating Main Budget'!$C:$S,6,0) -> -40431 | D6: =VLOOKUP($A6,'Operating Main Budget'!$C:$S,7,0) -> -40431 | E6: =VLOOKUP($A6,'Operating Main Budget'!$C:$S,8,0) -> -40431 | F6: =VLOOKUP($A6,'Operating Main Budget'!$C:$S,9,0) -> -40431 | G6: =VLOOKUP($A6,'Operating Main Budget'!$C:$S,10,0) -> -40431 | H6: =VLOOKUP($A6,'Operating Main Budget'!$C:$S,11,0) -> -40431 | I6: =VLOOKUP($A6,'Operating Main Budget'!$C:$S,12,0) -> -40431 | J6: =VLOOKUP($A6,'Operating Main Budget'!$C:$S,13,0) -> -40431 | K6: =VLOOKUP($A6,'Operating Main Budget'!$C:$S,14,0) -> -40431 | L6: =VLOOKUP($A6,'Operating Main Budget'!$C:$S,15,0) -> -40431 | M6: =VLOOKUP($A6,'Operating Main Budget'!$C:$S,16,0) -> -40431 | N6: =VLOOKUP($A6,'Operating Main Budget'!$C:$S,17,0) -> -40433
A7: 4012 | C7: =VLOOKUP($A7,'Operating Main Budget'!$C:$S,6,0) -> -11721 | D7: =VLOOKUP($A7,'Operating Main Budget'!$C:$S,7,0) -> -11721 | E7: =VLOOKUP($A7,'Operating Main Budget'!$C:$S,8,0) -> -11721 | F7: =VLOOKUP($A7,'Operating Main Budget'!$C:$S,9,0) -> -11721 | G7: =VLOOKUP($A7,'Operating Main Budget'!$C:$S,10,0) -> -11721 | H7: =VLOOKUP($A7,'Operating Main Budget'!$C:$S,11,0) -> -11721 | I7: =VLOOKUP($A7,'Operating Main Budget'!$C:$S,12,0) -> -11721 | J7: =VLOOKUP($A7,'Operating Main Budget'!$C:$S,13,0) -> -11721 | K7: =VLOOKUP($A7,'Operating Main Budget'!$C:$S,14,0) -> -11721 | L7: =VLOOKUP($A7,'Operating Main Budget'!$C:$S,15,0) -> -11721 | M7: =VLOOKUP($A7,'Operating Main Budget'!$C:$S,16,0) -> -11721 | N7: =VLOOKUP($A7,'Operating Main Budget'!$C:$S,17,0) -> -11719
A8: 4610 | C8: =VLOOKUP($A8,'Operating Main Budget'!$C:$S,6,0) -> -8 | D8: =VLOOKUP($A8,'Operating Main Budget'!$C:$S,7,0) -> -8 | E8: =VLOOKUP($A8,'Operating Main Budget'!$C:$S,8,0) -> -8 | F8: =VLOOKUP($A8,'Operating Main Budget'!$C:$S,9,0) -> -8 | G8: =VLOOKUP($A8,'Operating Main Budget'!$C:$S,10,0) -> -8 | H8: =VLOOKUP($A8,'Operating Main Budget'!$C:$S,11,0) -> -8 | I8: =VLOOKUP($A8,'Operating Main Budget'!$C:$S,12,0) -> -8 | J8: =VLOOKUP($A8,'Operating Main Budget'!$C:$S,13,0) -> -8 | K8: =VLOOKUP($A8,'Operating Main Budget'!$C:$S,14,0) -> -8 | L8: =VLOOKUP($A8,'Operating Main Budget'!$C:$S,15,0) -> -8 | M8: =VLOOKUP($A8,'Operating Main Budget'!$C:$S,16,0) -> -8 | N8: =VLOOKUP($A8,'Operating Main Budget'!$C:$S,17,0) -> -12
A9: 4110 | C9: =VLOOKUP($A9,'Operating Main Budget'!$C:$S,6,0) -> -4333 | D9: =VLOOKUP($A9,'Operating Main Budget'!$C:$S,7,0) -> -4333 | E9: =VLOOKUP($A9,'Operating Main Budget'!$C:$S,8,0) -> -4333 | F9: =VLOOKUP($A9,'Operating Main Budget'!$C:$S,9,0) -> -4333 | G9: =VLOOKUP($A9,'Operating Main Budget'!$C:$S,10,0) -> -4333 | H9: =VLOOKUP($A9,'Operating Main Budget'!$C:$S,11,0) -> -4333 | I9: =VLOOKUP($A9,'Operating Main Budget'!$C:$S,12,0) -> -4333 | J9: =VLOOKUP($A9,'Operating Main Budget'!$C:$S,13,0) -> -4333 | K9: =VLOOKUP($A9,'Operating Main Budget'!$C:$S,14,0) -> -4333 | L9: =VLOOKUP($A9,'Operating Main Budget'!$C:$S,15,0) -> -4333 | M9: =VLOOKUP($A9,'Operating Main Budget'!$C:$S,16,0) -> -4333 | N9: =VLOOKUP($A9,'Operating Main Budget'!$C:$S,17,0) -> -4337
A10: 4020 | C10: =VLOOKUP($A10,'Operating Main Budget'!$C:$S,6,0) -> -300 | D10: =VLOOKUP($A10,'Operating Main Budget'!$C:$S,7,0) -> -300 | E10: =VLOOKUP($A10,'Operating Main Budget'!$C:$S,8,0) -> -300 | F10: =VLOOKUP($A10,'Operating Main Budget'!$C:$S,9,0) -> -300 | G10: =VLOOKUP($A10,'Operating Main Budget'!$C:$S,10,0) -> -300 | H10: =VLOOKUP($A10,'Operating Main Budget'!$C:$S,11,0) -> -300 | I10: =VLOOKUP($A10,'Operating Main Budget'!$C:$S,12,0) -> -300 | J10: =VLOOKUP($A10,'Operating Main Budget'!$C:$S,13,0) -> -300 | K10: =VLOOKUP($A10,'Operating Main Budget'!$C:$S,14,0) -> -300 | L10: =VLOOKUP($A10,'Operating Main Budget'!$C:$S,15,0) -> -300 | M10: =VLOOKUP($A10,'Operating Main Budget'!$C:$S,16,0) -> -300 | N10: =VLOOKUP($A10,'Operating Main Budget'!$C:$S,17,0) -> -300
A11: 4995 | C11: =VLOOKUP($A11,'Operating Main Budget'!$C:$S,6,0) -> -83 | D11: =VLOOKUP($A11,'Operating Main Budget'!$C:$S,7,0) -> -83 | E11: =VLOOKUP($A11,'Operating Main Budget'!$C:$S,8,0) -> -83 | F11: =VLOOKUP($A11,'Operating Main Budget'!$C:$S,9,0) -> -83 | G11: =VLOOKUP($A11,'Operating Main Budget'!$C:$S,10,0) -> -83 | H11: =VLOOKUP($A11,'Operating Main Budget'!$C:$S,11,0) -> -83 | I11: =VLOOKUP($A11,'Operating Main Budget'!$C:$S,12,0) -> -83 | J11: =VLOOKUP($A11,'Operating Main Budget'!$C:$S,13,0) -> -83 | K11: =VLOOKUP($A11,'Operating Main Budget'!$C:$S,14,0) -> -83 | L11: =VLOOKUP($A11,'Operating Main Budget'!$C:$S,15,0) -> -83 | M11: =VLOOKUP($A11,'Operating Main Budget'!$C:$S,16,0) -> -83 | N11: =VLOOKUP($A11,'Operating Main Budget'!$C:$S,17,0) -> -87
A12: 4050 | C12: =VLOOKUP($A12,'Operating Main Budget'!$C:$S,6,0) -> -50 | D12: =VLOOKUP($A12,'Operating Main Budget'!$C:$S,7,0) -> -50 | E12: =VLOOKUP($A12,'Operating Main Budget'!$C:$S,8,0) -> -50 | F12: =VLOOKUP($A12,'Operating Main Budget'!$C:$S,9,0) -> -50 | G12: =VLOOKUP($A12,'Operating Main Budget'!$C:$S,10,0) -> -50 | H12: =VLOOKUP($A12,'Operating Main Budget'!$C:$S,11,0) -> -50 | I12: =VLOOKUP($A12,'Operating Main Budget'!$C:$S,12,0) -> -50 | J12: =VLOOKUP($A12,'Operating Main Budget'!$C:$S,13,0) -> -50 | K12: =VLOOKUP($A12,'Operating Main Budget'!$C:$S,14,0) -> -50 | L12: =VLOOKUP($A12,'Operating Main Budget'!$C:$S,15,0) -> -50 | M12: =VLOOKUP($A12,'Operating Main Budget'!$C:$S,16,0) -> -50 | N12: =VLOOKUP($A12,'Operating Main Budget'!$C:$S,17,0) -> -50
A13: 4330 | C13: =VLOOKUP($A13,'Operating Main Budget'!$C:$S,6,0) -> -500 | D13: =VLOOKUP($A13,'Operating Main Budget'!$C:$S,7,0) -> -500 | E13: =VLOOKUP($A13,'Operating Main Budget'!$C:$S,8,0) -> -500 | F13: =VLOOKUP($A13,'Operating Main Budget'!$C:$S,9,0) -> -500 | G13: =VLOOKUP($A13,'Operating Main Budget'!$C:$S,10,0) -> -500 | H13: =VLOOKUP($A13,'Operating Main Budget'!$C:$S,11,0) -> -500 | I13: =VLOOKUP($A13,'Operating Main Budget'!$C:$S,12,0) -> -500 | J13: =VLOOKUP($A13,'Operating Main Budget'!$C:$S,13,0) -> -500 | K13: =VLOOKUP($A13,'Operating Main Budget'!$C:$S,14,0) -> -500 | L13: =VLOOKUP($A13,'Operating Main Budget'!$C:$S,15,0) -> -500 | M13: =VLOOKUP($A13,'Operating Main Budget'!$C:$S,16,0) -> -500 | N13: =VLOOKUP($A13,'Operating Main Budget'!$C:$S,17,0) -> -500
A14: 4030 | C14: =VLOOKUP($A14,'Operating Main Budget'!$C:$S,6,0) -> -833 | D14: =VLOOKUP($A14,'Operating Main Budget'!$C:$S,7,0) -> -833 | E14: =VLOOKUP($A14,'Operating Main Budget'!$C:$S,8,0) -> -833 | F14: =VLOOKUP($A14,'Operating Main Budget'!$C:$S,9,0) -> -833 | G14: =VLOOKUP($A14,'Operating Main Budget'!$C:$S,10,0) -> -833 | H14: =VLOOKUP($A14,'Operating Main Budget'!$C:$S,11,0) -> -833 | I14: =VLOOKUP($A14,'Operating Main Budget'!$C:$S,12,0) -> -833 | J14: =VLOOKUP($A14,'Operating Main Budget'!$C:$S,13,0) -> -833 | K14: =VLOOKUP($A14,'Operating Main Budget'!$C:$S,14,0) -> -833 | L14: =VLOOKUP($A14,'Operating Main Budget'!$C:$S,15,0) -> -833 | M14: =VLOOKUP($A14,'Operating Main Budget'!$C:$S,16,0) -> -833 | N14: =VLOOKUP($A14,'Operating Main Budget'!$C:$S,17,0) -> -837
A15: 4070 | C15: =VLOOKUP($A15,'Operating Main Budget'!$C:$S,6,0) -> -1280 | D15: =VLOOKUP($A15,'Operating Main Budget'!$C:$S,7,0) -> -1280 | E15: =VLOOKUP($A15,'Operating Main Budget'!$C:$S,8,0) -> -1280 | F15: =VLOOKUP($A15,'Operating Main Budget'!$C:$S,9,0) -> -1280 | G15: =VLOOKUP($A15,'Operating Main Budget'!$C:$S,10,0) -> -1280 | H15: =VLOOKUP($A15,'Operating Main Budget'!$C:$S,11,0) -> -1280 | I15: =VLOOKUP($A15,'Operating Main Budget'!$C:$S,12,0) -> -1280 | J15: =VLOOKUP($A15,'Operating Main Budget'!$C:$S,13,0) -> -1280 | K15: =VLOOKUP($A15,'Operating Main Budget'!$C:$S,14,0) -> -1280 | L15: =VLOOKUP($A15,'Operating Main Budget'!$C:$S,15,0) -> -1280 | M15: =VLOOKUP($A15,'Operating Main Budget'!$C:$S,16,0) -> -1280 | N15: =VLOOKUP($A15,'Operating Main Budget'!$C:$S,17,0) -> -1280
... A78: 8801 | C78: =VLOOKUP($A78,'Operating Main Budget'!$C:$S,6,0) -> 40431 | D78: =VLOOKUP($A78,'Operating Main Budget'!$C:$S,7,0) -> 40431 | E78: =VLOOKUP($A78,'Operating Main Budget'!$C:$S,8,0) -> 40431 | F78: =VLOOKUP($A78,'Operating Main Budget'!$C:$S,9,0) -> 40431 | G78: =VLOOKUP($A78,'Operating Main Budget'!$C:$S,10,0) -> 40431 | H78: =VLOOKUP($A78,'Operating Main Budget'!$C:$S,11,0) -> 40431 | I78: =VLOOKUP($A78,'Operating Main Budget'!$C:$S,12,0) -> 40431 | J78: =VLOOKUP($A78,'Operating Main Budget'!$C:$S,13,0) -> 40431 | K78: =VLOOKUP($A78,'Operating Main Budget'!$C:$S,14,0) -> 40431 | L78: =VLOOKUP($A78,'Operating Main Budget'!$C:$S,15,0) -> 40431 | M78: =VLOOKUP($A78,'Operating Main Budget'!$C:$S,16,0) -> 40431 | N78: =VLOOKUP($A78,'Operating Main Budget'!$C:$S,17,0) -> 40433

Sheet Reserve Upload
A1: R554 | B1: 2013
C2: JAN | D2: FEB | E2: MAR | F2: APR | G2: MAY | H2: JUN | I2: JUL | J2: AUG | K2: SEP | L2: OCT | M2: NOV | N2: DEC
C3: 2013 | D3: 2013 | E3: 2013 | F3: 2013 | G3: 2013 | H3: 2013 | I3: 2013 | J3: 2013 | K3: 2013 | L3: 2013 | M3: 2013 | N3: 2013
A4: 9001 | C4: =VLOOKUP($A4,'Reserve Budget Main'!$C:$S,6,0) -> -40431 | D4: =VLOOKUP($A4,'Reserve Budget Main'!$C:$S,7,0) -> -40431 | E4: =VLOOKUP($A4,'Reserve Budget Main'!$C:$S,8,0) -> -40431 | F4: =VLOOKUP($A4,'Reserve Budget Main'!$C:$S,9,0) -> -40431 | G4: =VLOOKUP($A4,'Reserve Budget Main'!$C:$S,10,0) -> -40431 | H4: =VLOOKUP($A4,'Reserve Budget Main'!$C:$S,11,0) -> -40431 | I4: =VLOOKUP($A4,'Reserve Budget Main'!$C:$S,12,0) -> -40431 | J4: =VLOOKUP($A4,'Reserve Budget Main'!$C:$S,13,0) -> -40431 | K4: =VLOOKUP($A4,'Reserve Budget Main'!$C:$S,14,0) -> -40431 | L4: =VLOOKUP($A4,'Reserve Budget Main'!$C:$S,15,0) -> -40431 | M4: =VLOOKUP($A4,'Reserve Budget Main'!$C:$S,16,0) -> -40431 | N4: =VLOOKUP($A4,'Reserve Budget Main'!$C:$S,17,0) -> -40433
A5: 9180 | C5: =VLOOKUP($A5,'Reserve Budget Main'!$C:$S,6,0) -> 200 | D5: =VLOOKUP($A5,'Reserve Budget Main'!$C:$S,7,0) -> 200 | E5: =VLOOKUP($A5,'Reserve Budget Main'!$C:$S,8,0) -> 200 | F5: =VLOOKUP($A5,'Reserve Budget Main'!$C:$S,9,0) -> 200 | G5: =VLOOKUP($A5,'Reserve Budget Main'!$C:$S,10,0) -> 200 | H5: =VLOOKUP($A5,'Reserve Budget Main'!$C:$S,11,0) -> 200 | I5: =VLOOKUP($A5,'Reserve Budget Main'!$C:$S,12,0) -> 200 | J5: =VLOOKUP($A5,'Reserve Budget Main'!$C:$S,13,0) -> 200 | K5: =VLOOKUP($A5,'Reserve Budget Main'!$C:$S,14,0) -> 200 | L5: =VLOOKUP($A5,'Reserve Budget Main'!$C:$S,15,0) -> 200 | M5: =VLOOKUP($A5,'Reserve Budget Main'!$C:$S,16,0) -> 200 | N5: =VLOOKUP($A5,'Reserve Budget Main'!$C:$S,17,0) -> 200
A6: 9174 | C6: =VLOOKUP($A6,'Reserve Budget Main'!$C:$S,6,0) -> 125 | D6: =VLOOKUP($A6,'Reserve Budget Main'!$C:$S,7,0) -> 125 | E6: =VLOOKUP($A6,'Reserve Budget Main'!$C:$S,8,0) -> 125 | F6: =VLOOKUP($A6,'Reserve Budget Main'!$C:$S,9,0) -> 125 | G6: =VLOOKUP($A6,'Reserve Budget Main'!$C:$S,10,0) -> 125 | H6: =VLOOKUP($A6,'Reserve Budget Main'!$C:$S,11,0) -> 125 | I6: =VLOOKUP($A6,'Reserve Budget Main'!$C:$S,12,0) -> 125 | J6: =VLOOKUP($A6,'Reserve Budget Main'!$C:$S,13,0) -> 125 | K6: =VLOOKUP($A6,'Reserve Budget Main'!$C:$S,14,0) -> 125 | L6: =VLOOKUP($A6,'Reserve Budget Main'!$C:$S,15,0) -> 125 | M6: =VLOOKUP($A6,'Reserve Budget Main'!$C:$S,16,0) -> 125 | N6: =VLOOKUP($A6,'Reserve Budget Main'!$C:$S,17,0) -> 125
A7: 9173 | C7: =VLOOKUP($A7,'Reserve Budget Main'!$C:$S,6,0) -> 8333 | D7: =VLOOKUP($A7,'Reserve Budget Main'!$C:$S,7,0) -> 8333 | E7: =VLOOKUP($A7,'Reserve Budget Main'!$C:$S,8,0) -> 8333 | F7: =VLOOKUP($A7,'Reserve Budget Main'!$C:$S,9,0) -> 8333 | G7: =VLOOKUP($A7,'Reserve Budget Main'!$C:$S,10,0) -> 8333 | H7: =VLOOKUP($A7,'Reserve Budget Main'!$C:$S,11,0) -> 8333 | I7: =VLOOKUP($A7,'Reserve Budget Main'!$C:$S,12,0) -> 8333 | J7: =VLOOKUP($A7,'Reserve Budget Main'!$C:$S,13,0) -> 8333 | K7: =VLOOKUP($A7,'Reserve Budget Main'!$C:$S,14,0) -> 8333 | L7: =VLOOKUP($A7,'Reserve Budget Main'!$C:$S,15,0) -> 8333 | M7: =VLOOKUP($A7,'Reserve Budget Main'!$C:$S,16,0) -> 8333 | N7: =VLOOKUP($A7,'Reserve Budget Main'!$C:$S,17,0) -> 8337
A8: 9164 | C8: =VLOOKUP($A8,'Reserve Budget Main'!$C:$S,6,0) -> 292 | D8: =VLOOKUP($A8,'Reserve Budget Main'!$C:$S,7,0) -> 292 | E8: =VLOOKUP($A8,'Reserve Budget Main'!$C:$S,8,0) -> 292 | F8: =VLOOKUP($A8,'Reserve Budget Main'!$C:$S,9,0) -> 292 | G8: =VLOOKUP($A8,'Reserve Budget Main'!$C:$S,10,0) -> 292 | H8: =VLOOKUP($A8,'Reserve Budget Main'!$C:$S,11,0) -> 292 | I8: =VLOOKUP($A8,'Reserve Budget Main'!$C:$S,12,0) -> 292 | J8: =VLOOKUP($A8,'Reserve Budget Main'!$C:$S,13,0) -> 292 | K8: =VLOOKUP($A8,'Reserve Budget Main'!$C:$S,14,0) -> 292 | L8: =VLOOKUP($A8,'Reserve Budget Main'!$C:$S,15,0) -> 292 | M8: =VLOOKUP($A8,'Reserve Budget Main'!$C:$S,16,0) -> 292 | N8: =VLOOKUP($A8,'Reserve Budget Main'!$C:$S,17,0) -> 288
A9: 9163-6 | C9: =VLOOKUP($A9,'Reserve Budget Main'!$C:$S,6,0) -> 18333 | D9: =VLOOKUP($A9,'Reserve Budget Main'!$C:$S,7,0) -> 18333 | E9: =VLOOKUP($A9,'Reserve Budget Main'!$C:$S,8,0) -> 18333 | F9: =VLOOKUP($A9,'Reserve Budget Main'!$C:$S,9,0) -> 18333 | G9: =VLOOKUP($A9,'Reserve Budget Main'!$C:$S,10,0) -> 18333 | H9: =VLOOKUP($A9,'Reserve Budget Main'!$C:$S,11,0) -> 18333 | I9: =VLOOKUP($A9,'Reserve Budget Main'!$C:$S,12,0) -> 18333 | J9: =VLOOKUP($A9,'Reserve Budget Main'!$C:$S,13,0) -> 18333 | K9: =VLOOKUP($A9,'Reserve Budget Main'!$C:$S,14,0) -> 18333 | L9: =VLOOKUP($A9,'Reserve Budget Main'!$C:$S,15,0) -> 18333 | M9: =VLOOKUP($A9,'Reserve Budget Main'!$C:$S,16,0) -> 18333 | N9: =VLOOKUP($A9,'Reserve Budget Main'!$C:$S,17,0) -> 18337
A10: 9182 | C10: =VLOOKUP($A10,'Reserve Budget Main'!$C:$S,6,0) -> 383 | D10: =VLOOKUP($A10,'Reserve Budget Main'!$C:$S,7,0) -> 383 | E10: =VLOOKUP($A10,'Reserve Budget Main'!$C:$S,8,0) -> 383 | F10: =VLOOKUP($A10,'Reserve Budget Main'!$C:$S,9,0) -> 383 | G10: =VLOOKUP($A10,'Reserve Budget Main'!$C:$S,10,0) -> 383 | H10: =VLOOKUP($A10,'Reserve Budget Main'!$C:$S,11,0) -> 383 | I10: =VLOOKUP($A10,'Reserve Budget Main'!$C:$S,12,0) -> 383 | J10: =VLOOKUP($A10,'Reserve Budget Main'!$C:$S,13,0) -> 383 | K10: =VLOOKUP($A10,'Reserve Budget Main'!$C:$S,14,0) -> 383 | L10: =VLOOKUP($A10,'Reserve Budget Main'!$C:$S,15,0) -> 383 | M10: =VLOOKUP($A10,'Reserve Budget Main'!$C:$S,16,0) -> 383 | N10: =VLOOKUP($A10,'Reserve Budget Main'!$C:$S,17,0) -> 387
A11: 9168 | C11: =VLOOKUP($A11,'Reserve Budget Main'!$C:$S,6,0) -> 1000 | D11: =VLOOKUP($A11,'Reserve Budget Main'!$C:$S,7,0) -> 1000 | E11: =VLOOKUP($A11,'Reserve Budget Main'!$C:$S,8,0) -> 1000 | F11: =VLOOKUP($A11,'Reserve Budget Main'!$C:$S,9,0) -> 1000 | G11: =VLOOKUP($A11,'Reserve Budget Main'!$C:$S,10,0) -> 1000 | H11: =VLOOKUP($A11,'Reserve Budget Main'!$C:$S,11,0) -> 1000 | I11: =VLOOKUP($A11,'Reserve Budget Main'!$C:$S,12,0) -> 1000 | J11: =VLOOKUP($A11,'Reserve Budget Main'!$C:$S,13,0) -> 1000 | K11: =VLOOKUP($A11,'Reserve Budget Main'!$C:$S,14,0) -> 1000 | L11: =VLOOKUP($A11,'Reserve Budget Main'!$C:$S,15,0) -> 1000 | M11: =VLOOKUP($A11,'Reserve Budget Main'!$C:$S,16,0) -> 1000 | N11: =VLOOKUP($A11,'Reserve Budget Main'!$C:$S,17,0) -> 1000
A12: 9169-3 | C12: =VLOOKUP($A12,'Reserve Budget Main'!$C:$S,6,0) -> 500 | D12: =VLOOKUP($A12,'Reserve Budget Main'!$C:$S,7,0) -> 500 | E12: =VLOOKUP($A12,'Reserve Budget Main'!$C:$S,8,0) -> 500 | F12: =VLOOKUP($A12,'Reserve Budget Main'!$C:$S,9,0) -> 500 | G12: =VLOOKUP($A12,'Reserve Budget Main'!$C:$S,10,0) -> 500 | H12: =VLOOKUP($A12,'Reserve Budget Main'!$C:$S,11,0) -> 500 | I12: =VLOOKUP($A12,'Reserve Budget Main'!$C:$S,12,0) -> 500 | J12: =VLOOKUP($A12,'Reserve Budget Main'!$C:$S,13,0) -> 500 | K12: =VLOOKUP($A12,'Reserve Budget Main'!$C:$S,14,0) -> 500 | L12: =VLOOKUP($A12,'Reserve Budget Main'!$C:$S,15,0) -> 500 | M12: =VLOOKUP($A12,'Reserve Budget Main'!$C:$S,16,0) -> 500 | N12: =VLOOKUP($A12,'Reserve Budget Main'!$C:$S,17,0) -> 500
A13: 9160-1 | C13: =VLOOKUP($A13,'Reserve Budget Main'!$C:$S,6,0) -> 1000 | D13: =VLOOKUP($A13,'Reserve Budget Main'!$C:$S,7,0) -> 1000 | E13: =VLOOKUP($A13,'Reserve Budget Main'!$C:$S,8,0) -> 1000 | F13: =VLOOKUP($A13,'Reserve Budget Main'!$C:$S,9,0) -> 1000 | G13: =VLOOKUP($A13,'Reserve Budget Main'!$C:$S,10,0) -> 1000 | H13: =VLOOKUP($A13,'Reserve Budget Main'!$C:$S,11,0) -> 1000 | I13: =VLOOKUP($A13,'Reserve Budget Main'!$C:$S,12,0) -> 1000 | J13: =VLOOKUP($A13,'Reserve Budget Main'!$C:$S,13,0) -> 1000 | K13: =VLOOKUP($A13,'Reserve Budget Main'!$C:$S,14,0) -> 1000 | L13: =VLOOKUP($A13,'Reserve Budget Main'!$C:$S,15,0) -> 1000 | M13: =VLOOKUP($A13,'Reserve Budget Main'!$C:$S,16,0) -> 1000 | N13: =VLOOKUP($A13,'Reserve Budget Main'!$C:$S,17,0) -> 1000
A14: 9169 | C14: =VLOOKUP($A14,'Reserve Budget Main'!$C:$S,6,0) -> 3333 | D14: =VLOOKUP($A14,'Reserve Budget Main'!$C:$S,7,0) -> 3333 | E14: =VLOOKUP($A14,'Reserve Budget Main'!$C:$S,8,0) -> 3333 | F14: =VLOOKUP($A14,'Reserve Budget Main'!$C:$S,9,0) -> 3333 | G14: =VLOOKUP($A14,'Reserve Budget Main'!$C:$S,10,0) -> 3333 | H14: =VLOOKUP($A14,'Reserve Budget Main'!$C:$S,11,0) -> 3333 | I14: =VLOOKUP($A14,'Reserve Budget Main'!$C:$S,12,0) -> 3333 | J14: =VLOOKUP($A14,'Reserve Budget Main'!$C:$S,13,0) -> 3333 | K14: =VLOOKUP($A14,'Reserve Budget Main'!$C:$S,14,0) -> 3333 | L14: =VLOOKUP($A14,'Reserve Budget Main'!$C:$S,15,0) -> 3333 | M14: =VLOOKUP($A14,'Reserve Budget Main'!$C:$S,16,0) -> 3333 | N14: =VLOOKUP($A14,'Reserve Budget Main'!$C:$S,17,0) -> 3337
A15: 9162 | C15: =VLOOKUP($A15,'Reserve Budget Main'!$C:$S,6,0) -> 833 | D15: =VLOOKUP($A15,'Reserve Budget Main'!$C:$S,7,0) -> 833 | E15: =VLOOKUP($A15,'Reserve Budget Main'!$C:$S,8,0) -> 833 | F15: =VLOOKUP($A15,'Reserve Budget Main'!$C:$S,9,0) -> 833 | G15: =VLOOKUP($A15,'Reserve Budget Main'!$C:$S,10,0) -> 833 | H15: =VLOOKUP($A15,'Reserve Budget Main'!$C:$S,11,0) -> 833 | I15: =VLOOKUP($A15,'Reserve Budget Main'!$C:$S,12,0) -> 833 | J15: =VLOOKUP($A15,'Reserve Budget Main'!$C:$S,13,0) -> 833 | K15: =VLOOKUP($A15,'Reserve Budget Main'!$C:$S,14,0) -> 833 | L15: =VLOOKUP($A15,'Reserve Budget Main'!$C:$S,15,0) -> 833 | M15: =VLOOKUP($A15,'Reserve Budget Main'!$C:$S,16,0) -> 833 | N15: =VLOOKUP($A15,'Reserve Budget Main'!$C:$S,17,0) -> 837
... A25: 9025 | C25: =VLOOKUP($A25,'Reserve Budget Main'!$C:$S,6,0) -> -67 | D25: =VLOOKUP($A25,'Reserve Budget Main'!$C:$S,7,0) -> -67 | E25: =VLOOKUP($A25,'Reserve Budget Main'!$C:$S,8,0) -> -67 | F25: =VLOOKUP($A25,'Reserve Budget Main'!$C:$S,9,0) -> -67 | G25: =VLOOKUP($A25,'Reserve Budget Main'!$C:$S,10,0) -> -67 | H25: =VLOOKUP($A25,'Reserve Budget Main'!$C:$S,11,0) -> -67 | I25: =VLOOKUP($A25,'Reserve Budget Main'!$C:$S,12,0) -> -67 | J25: =VLOOKUP($A25,'Reserve Budget Main'!$C:$S,13,0) -> -67 | K25: =VLOOKUP($A25,'Reserve Budget Main'!$C:$S,14,0) -> -67 | L25: =VLOOKUP($A25,'Reserve Budget Main'!$C:$S,15,0) -> -67 | M25: =VLOOKUP($A25,'Reserve Budget Main'!$C:$S,16,0) -> -67 | N25: =VLOOKUP($A25,'Reserve Budget Main'!$C:$S,17,0) -> -63
